Workbook

Sheet Sheet1

Sheet Forecast vs Actuals
O1: F4W | R1: F8W | W1: IM FCST RR | AJ1: IM FCST YoY | AW1: OP FCST RR | BJ1: OP FCST YoY | BW1: IM F8W GAP | CD1: IM F4W GAP
W2: =W6 -> 46103 | X2: =X6 -> 46110 | Y2: =Y6 -> 46117 | Z2: =Z6 -> 46124 | AA2: =AA6 -> 46131 | AB2: =AB6 -> 46138 | AC2: =AC6 -> 46145 | AD2: =AD6 -> 46152 | ... AH2: =AH6 -> 46180 | AW2: =AW6 -> 46103 | AX2: =AX6 -> 46110 | AY2: =AY6 -> 46117 | AZ2: =AZ6 -> 46124 | BA2: =BA6 -> 46131 | BB2: =BB6 -> 46138 | BC2: =BC6 -> 46145 | BD2: =BD6 -> 46152 | ... BH2: =BH6 -> 46180
E3: LY | L3: L6W RR | M3: L6W YoY | O3: IM | P3: IM | R3: IM | S3: IM | T3: AE | U3: AE | W3: CW+1 | X3: CW+2 | Y3: CW+3 | Z3: CW+4 | AA3: CW+5 | AB3: CW+6 | AC3: CW+7 | AD3: CW+8 | AE3: CW+9 | AF3: CW+10 | AG3: CW+11 | AH3: CW+12 | AJ3: CW+1 | AK3: CW+2 | AL3: CW+3 | AM3: CW+4 | AN3: CW+5 | AO3: CW+6 | AP3: CW+7 | AQ3: CW+8 | AR3: CW+9 | AS3: CW+10 | AT3: CW+11 | AU3: CW+12 | AW3: CW+1 | AX3: CW+2 | AY3: CW+3 | AZ3: CW+4 | BA3: CW+5 | BB3: CW+6 | BC3: CW+7 | BD3: CW+8 | BE3: CW+9 | BF3: CW+10 | BG3: CW+11 | BH3: CW+12 | BJ3: CW+1 | BK3: CW+2 | BL3: CW+3 | BM3: CW+4 | BN3: CW+5 | BO3: CW+6 | BP3: CW+7 | BQ3: CW+8 | BR3: CW+9 | BS3: CW+10 | BT3: CW+11 | BU3: CW+12 | BW3: LY | BX3: F8W YoY | BY3: L6W | BZ3: F8W | CA3: YoY Contribution | CD3: LY | CE3: F4W YoY | CF3: L6W | CG3: F4W | CH3: YoY Contribution
B4: ALL BRANDS | C4: Cohort | D4: PATTERN AMERICAS | E4: =SUM(E8:E537) -> 1169397 | F4: =SUM(F8:F537) -> 1639556 | G4: =SUM(G8:G537) -> 1625930 | H4: =SUM(H8:H537) -> 1625180 | I4: =SUM(I8:I537) -> 1625697 | J4: =SUM(J8:J537) -> 1640755 | K4: =SUM(K8:K537) -> 1667790 | L4: =SUM(L8:L537) -> 1637239 | M4: =(L4-E4)/E4 -> 0.40007115 | O4: =AVERAGE(W4:Z4) -> 1720832.8 | P4: =CE4 -> 0.44180583 | R4: =AVERAGE(W4:AD4) -> 1730051 | S4: =BX4 -> 0.42168532 | T4: =AVERAGE(AW4:BD4) -> 1478394.4 | U4: =#REF! -> #REF! | W4: =SUM(W8:W537) -> 1749250 | X4: =SUM(X8:X537) -> 1715561 | Y4: =SUM(Y8:Y537) -> 1706954 | Z4: =SUM(Z8:Z537) -> 1711566 | AA4: =SUM(AA8:AA537) -> 1717107 | AB4: =SUM(AB8:AB537) -> 1747078 | AC4: =SUM(AC8:AC537) -> 1762487 | AD4: =SUM(AD8:AD537) -> 1730405 | ... AH4: =SUM(AH8:AH537) -> 1750245 | AJ4: =(W4-SUMIFS('Forecast Data'!$H:$H,'Forecast Data'!$B:$B,$B4,'Forecast Data'!$C:$C,AJ$6))/SUMIFS('Forecast Data'!$H:$H,'Forecast Data'!$B:$B,$B4,'Forecast Data'!$C:$C,AJ$6) -> 0.4623733 | AK4: =(X4-SUMIFS('Forecast Data'!$H:$H,'Forecast Data'!$B:$B,$B4,'Forecast Data'!$C:$C,AK$6))/SUMIFS('Forecast Data'!$H:$H,'Forecast Data'!$B:$B,$B4,'Forecast Data'!$C:$C,AK$6) -> 0.42914588 | AL4: =(Y4-SUMIFS('Forecast Data'!$H:$H,'Forecast Data'!$B:$B,$B4,'Forecast Data'!$C:$C,AL$6))/SUMIFS('Forecast Data'!$H:$H,'Forecast Data'!$B:$B,$B4,'Forecast Data'!$C:$C,AL$6) -> 0.45917824 | AM4: =(Z4-SUMIFS('Forecast Data'!$H:$H,'Forecast Data'!$B:$B,$B4,'Forecast Data'!$C:$C,AM$6))/SUMIFS('Forecast Data'!$H:$H,'Forecast Data'!$B:$B,$B4,'Forecast Data'!$C:$C,AM$6) -> 0.41719128 | AN4: =(AA4-SUMIFS('Forecast Data'!$H:$H,'Forecast Data'!$B:$B,$B4,'Forecast Data'!$C:$C,AN$6))/SUMIFS('Forecast Data'!$H:$H,'Forecast Data'!$B:$B,$B4,'Forecast Data'!$C:$C,AN$6) -> 0.40656663 | AO4: =(AB4-SUMIFS('Forecast Data'!$H:$H,'Forecast Data'!$B:$B,$B4,'Forecast Data'!$C:$C,AO$6))/SUMIFS('Forecast Data'!$H:$H,'Forecast Data'!$B:$B,$B4,'Forecast Data'!$C:$C,AO$6) -> 0.38556915 | AP4: =(AC4-SUMIFS('Forecast Data'!$H:$H,'Forecast Data'!$B:$B,$B4,'Forecast Data'!$C:$C,AP$6))/SUMIFS('Forecast Data'!$H:$H,'Forecast Data'!$B:$B,$B4,'Forecast Data'!$C:$C,AP$6) -> 0.43020933 | AQ4: =(AD4-SUMIFS('Forecast Data'!$H:$H,'Forecast Data'!$B:$B,$B4,'Forecast Data'!$C:$C,AQ$6))/SUMIFS('Forecast Data'!$H:$H,'Forecast Data'!$B:$B,$B4,'Forecast Data'!$C:$C,AQ$6) -> 0.38755311 | ... AU4: =(AH4-SUMIFS('Forecast Data'!$H:$H,'Forecast Data'!$B:$B,$B4,'Forecast Data'!$C:$C,AU$6))/SUMIFS('Forecast Data'!$H:$H,'Forecast Data'!$B:$B,$B4,'Forecast Data'!$C:$C,AU$6) -> 0.38976388 | AW4: =SUM(AW8:AW537) -> 1431629 | AX4: =SUM(AX8:AX537) -> 1497491 | AY4: =SUM(AY8:AY537) -> 1488441 | AZ4: =SUM(AZ8:AZ537) -> 1522161 | BA4: =SUM(BA8:BA537) -> 1498053 | BB4: =SUM(BB8:BB537) -> 1519932 | BC4: =SUM(BC8:BC537) -> 1444287 | BD4: =SUM(BD8:BD537) -> 1425161 | ... BH4: =SUM(BH8:BH537) -> 1434476 | BJ4: =IFERROR((SUMIFS('OP Units'!E:E,'OP Units'!$A:$A,$B4)-SUMIFS('Forecast Data'!$H:$H,'Forecast Data'!$C:$C,BJ$6,'Forecast Data'!$B:$B,$B4))/SUMIFS('Forecast Data'!$H:$H,'Forecast Data'!$C:$C,BJ$6,'Forecast Data'!$B:$B,$B4),"") -> 0.19207689 | BK4: =IFERROR((SUMIFS('OP Units'!F:F,'OP Units'!$A:$A,$B4)-SUMIFS('Forecast Data'!$H:$H,'Forecast Data'!$C:$C,BK$6,'Forecast Data'!$B:$B,$B4))/SUMIFS('Forecast Data'!$H:$H,'Forecast Data'!$C:$C,BK$6,'Forecast Data'!$B:$B,$B4),"") -> 0.24251631 | BL4: =IFERROR((SUMIFS('OP Units'!G:G,'OP Units'!$A:$A,$B4)-SUMIFS('Forecast Data'!$H:$H,'Forecast Data'!$C:$C,BL$6,'Forecast Data'!$B:$B,$B4))/SUMIFS('Forecast Data'!$H:$H,'Forecast Data'!$C:$C,BL$6,'Forecast Data'!$B:$B,$B4),"") -> 0.26559042 | BM4: =IFERROR((SUMIFS('OP Units'!H:H,'OP Units'!$A:$A,$B4)-SUMIFS('Forecast Data'!$H:$H,'Forecast Data'!$C:$C,BM$6,'Forecast Data'!$B:$B,$B4))/SUMIFS('Forecast Data'!$H:$H,'Forecast Data'!$C:$C,BM$6,'Forecast Data'!$B:$B,$B4),"") -> 0.25349565 | BN4: =IFERROR((SUMIFS('OP Units'!I:I,'OP Units'!$A:$A,$B4)-SUMIFS('Forecast Data'!$H:$H,'Forecast Data'!$C:$C,BN$6,'Forecast Data'!$B:$B,$B4))/SUMIFS('Forecast Data'!$H:$H,'Forecast Data'!$C:$C,BN$6,'Forecast Data'!$B:$B,$B4),"") -> 0.22025035 | BO4: =IFERROR((SUMIFS('OP Units'!J:J,'OP Units'!$A:$A,$B4)-SUMIFS('Forecast Data'!$H:$H,'Forecast Data'!$C:$C,BO$6,'Forecast Data'!$B:$B,$B4))/SUMIFS('Forecast Data'!$H:$H,'Forecast Data'!$C:$C,BO$6,'Forecast Data'!$B:$B,$B4),"") -> 0.19838926 | BP4: =IFERROR((SUMIFS('OP Units'!K:K,'OP Units'!$A:$A,$B4)-SUMIFS('Forecast Data'!$H:$H,'Forecast Data'!$C:$C,BP$6,'Forecast Data'!$B:$B,$B4))/SUMIFS('Forecast Data'!$H:$H,'Forecast Data'!$C:$C,BP$6,'Forecast Data'!$B:$B,$B4),"") -> 0.16759256 | BQ4: =IFERROR((SUMIFS('OP Units'!L:L,'OP Units'!$A:$A,$B4)-SUMIFS('Forecast Data'!$H:$H,'Forecast Data'!$C:$C,BQ$6,'Forecast Data'!$B:$B,$B4))/SUMIFS('Forecast Data'!$H:$H,'Forecast Data'!$C:$C,BQ$6,'Forecast Data'!$B:$B,$B4),"") -> 0.13849992 | BR4: =IFERROR((SUMIFS('OP Units'!M:M,'OP Units'!$A:$A,$B4)-SUMIFS('Forecast Data'!$H:$H,'Forecast Data'!$C:$C,BR$6,'Forecast Data'!$B:$B,$B4))/SUMIFS('Forecast Data'!$H:$H,'Forecast Data'!$C:$C,BR$6,'Forecast Data'!$B:$B,$B4),"") -> 0.13941445 | BS4: =IFERROR((SUMIFS('OP Units'!N:N,'OP Units'!$A:$A,$B4)-SUMIFS('Forecast Data'!$H:$H,'Forecast Data'!$C:$C,BS$6,'Forecast Data'!$B:$B,$B4))/SUMIFS('Forecast Data'!$H:$H,'Forecast Data'!$C:$C,BS$6,'Forecast Data'!$B:$B,$B4),"") -> 0.17100688 | BT4: =IFERROR((SUMIFS('OP Units'!O:O,'OP Units'!$A:$A,$B4)-SUMIFS('Forecast Data'!$H:$H,'Forecast Data'!$C:$C,BT$6,'Forecast Data'!$B:$B,$B4))/SUMIFS('Forecast Data'!$H:$H,'Forecast Data'!$C:$C,BT$6,'Forecast Data'!$B:$B,$B4),"") -> 0.17591798 | BU4: =IFERROR((SUMIFS('OP Units'!P:P,'OP Units'!$A:$A,$B4)-SUMIFS('Forecast Data'!$H:$H,'Forecast Data'!$C:$C,BU$6,'Forecast Data'!$B:$B,$B4))/SUMIFS('Forecast Data'!$H:$H,'Forecast Data'!$C:$C,BU$6,'Forecast Data'!$B:$B,$B4),"") -> 0.13731486 | BW4: =SUM(BW8:BW537) -> 1217238.4 | BX4: =IFERROR((SUM(W4:AD4)-(SUMIFS('Forecast Data'!H:H,'Forecast Data'!B:B,B4,'Forecast Data'!C:C,BJ$6)+SUMIFS('Forecast Data'!H:H,'Forecast Data'!B:B,B4,'Forecast Data'!C:C,BK$6)+SUMIFS('Forecast Data'!H:H,'Forecast Data'!B:B,B4,'Forecast Data'!C:C,BL$6)+SUMIFS('Forecast Data'!H:H,'Forecast Data'!B:B,B4,'Forecast Data'!C:C,BM$6)+SUMIFS('Forecast Data'!H:H,'Forecast Data'!B:B,B4,'Forecast Data'!C:C,BN$6)+SUMIFS('Forecast Data'!H:H,'Forecast Data'!B:B,B4,'Forecast Data'!C:C,BO$6)+SUMIFS('Forecast Data'!H:H,'Forecast Data'!B:B,B4,'Forecast Data'!C:C,BP$6)+SUMIFS('Forecast Data'!H:H,'Forecast Data'!B:B,B4,'Forecast Data'!C:C,BQ$6)))/(SUMIFS('Forecast Data'!H:H,'Forecast Data'!B:B,B4,'Forecast Data'!C:C,BJ$6)+SUMIFS('Forecast Data'!H:H,'Forecast Data'!B:B,B4,'Forecast Data'!C:C,BK$6)+SUMIFS('Forecast Data'!H:H,'Forecast Data'!B:B,B4,'Forecast Data'!C:C,BL$6)+SUMIFS('Forecast Data'!H:H,'Forecast Data'!B:B,B4,'Forecast Data'!C:C,BM$6)+SUMIFS('Forecast Data'!H:H,'Forecast Data'!B:B,B4,'Forecast Data'!C:C,BN$6)+SUMIFS('Forecast Data'!H:H,'Forecast Data'!B:B,B4,'Forecast Data'!C:C,BO$6)+SUMIFS('Forecast Data'!H:H,'Forecast Data'!B:B,B4,'Forecast Data'!C:C,BP$6)+SUMIFS('Forecast Data'!H:H,'Forecast Data'!B:B,B4,'Forecast Data'!C:C,BQ$6)),"") -> 0.42168532 | BY4: =SUM(BY8:BY508) -> 0.32845347 | BZ4: =SUM(BZ8:BZ508) -> 0.41139785 | CA4: =SUM(CA8:CA537) -> -2.1614174 | CD4: =SUM(CD8:CD537) -> 1193860.8 | CE4: =IFERROR((SUM(W4:Z4)-(SUMIFS('Forecast Data'!H:H,'Forecast Data'!B:B,B4,'Forecast Data'!C:C,BJ$6)+SUMIFS('Forecast Data'!H:H,'Forecast Data'!B:B,B4,'Forecast Data'!C:C,BK$6)+SUMIFS('Forecast Data'!H:H,'Forecast Data'!B:B,B4,'Forecast Data'!C:C,BL$6)+SUMIFS('Forecast Data'!H:H,'Forecast Data'!B:B,B4,'Forecast Data'!C:C,BM$6)))/(SUMIFS('Forecast Data'!H:H,'Forecast Data'!B:B,B4,'Forecast Data'!C:C,BJ$6)+SUMIFS('Forecast Data'!H:H,'Forecast Data'!B:B,B4,'Forecast Data'!C:C,BK$6)+SUMIFS('Forecast Data'!H:H,'Forecast Data'!B:B,B4,'Forecast Data'!C:C,BL$6)+SUMIFS('Forecast Data'!H:H,'Forecast Data'!B:B,B4,'Forecast Data'!C:C,BM$6)),"") -> 0.44180583 | CF4: =SUM(CF8:CF508) -> 0.32845347 | CG4: =SUM(CG8:CG508) -> 0.4192761 | CH4: =SUM(CH8:CH537) -> -4.1734686
W6: 46103 | X6: =W6+7 -> 46110 | Y6: =X6+7 -> 46117 | Z6: =Y6+7 -> 46124 | AA6: =Z6+7 -> 46131 | AB6: =AA6+7 -> 46138 | AC6: =AB6+7 -> 46145 | AD6: =AC6+7 -> 46152 | AE6: =AD6+7 -> 46159 | ... AH6: =AG6+7 -> 46180 | AJ6: =W6 -> 46103 | AK6: =X6 -> 46110 | AL6: =Y6 -> 46117 | AM6: =Z6 -> 46124 | AN6: =AA6 -> 46131 | AO6: =AB6 -> 46138 | AP6: =AC6 -> 46145 | AQ6: =AD6 -> 46152 | ... AU6: =AH6 -> 46180 | AW6: =AJ6 -> 46103 | AX6: =AK6 -> 46110 | AY6: =AL6 -> 46117 | AZ6: =AM6 -> 46124 | BA6: =AN6 -> 46131 | BB6: =AO6 -> 46138 | BC6: =AP6 -> 46145 | BD6: =AQ6 -> 46152 | ... BH6: =AU6 -> 46180 | BJ6: =AW6 -> 46103 | BK6: =AX6 -> 46110 | BL6: =AY6 -> 46117 | BM6: =AZ6 -> 46124 | BN6: =BA6 -> 46131 | BO6: =BB6 -> 46138 | BP6: =BC6 -> 46145 | BQ6: =BD6 -> 46152 | ... BU6: =BH6 -> 46180
E7: LY | F7: LW-5 | G7: LW-4 | H7: LW-3 | I7: LW-2 | J7: LW-1 | K7: LW | L7: L6W RR | M7: L6W YoY | O7: IM | P7: IM | R7: IM | S7: IM | T7: AE | U7: AE | W7: CW+1 | X7: CW+2 | Y7: CW+3 | Z7: CW+4 | AA7: CW+5 | AB7: CW+6 | AC7: CW+7 | AD7: CW+8 | AE7: CW+9 | AF7: CW+10 | AG7: CW+11 | AH7: CW+12 | AJ7: CW+1 | AK7: CW+2 | AL7: CW+3 | AM7: CW+4 | AN7: CW+5 | AO7: CW+6 | AP7: CW+7 | AQ7: CW+8 | AR7: CW+9 | AS7: CW+10 | AT7: CW+11 | AU7: CW+12 | AW7: CW+1 | AX7: CW+2 | AY7: CW+3 | AZ7: CW+4 | BA7: CW+5 | BB7: CW+6 | BC7: CW+7 | BD7: CW+8 | BE7: CW+9 | BF7: CW+10 | BG7: CW+11 | BH7: CW+12 | BJ7: CW+1 | BK7: CW+2 | BL7: CW+3 | BM7: CW+4 | BN7: CW+5 | BO7: CW+6 | BP7: CW+7 | BQ7: CW+8 | BR7: CW+9 | BS7: CW+10 | BT7: CW+11 | BU7: CW+12
B8: =D8 -> Thorne Research | D8: Thorne Research | E8: =SUMIFS('Fin Data'!F:F,'Fin Data'!A:A,D8) -> 180195 | F8: =SUMIFS('Fin Data with 6 week hist'!I:I,'Fin Data with 6 week hist'!$A:$A,$D8) -> 285756 | G8: =SUMIFS('Fin Data with 6 week hist'!J:J,'Fin Data with 6 week hist'!$A:$A,$D8) -> 281931 | H8: =SUMIFS('Fin Data with 6 week hist'!K:K,'Fin Data with 6 week hist'!$A:$A,$D8)+SUMIFS('Unit Cancellations'!D:D,'Unit Cancellations'!$B:$B,$D8) -> 280344 | I8: =SUMIFS('Fin Data with 6 week hist'!L:L,'Fin Data with 6 week hist'!$A:$A,$D8)+SUMIFS('Unit Cancellations'!E:E,'Unit Cancellations'!$B:$B,$D8) -> 283674 | J8: =SUMIFS('Fin Data with 6 week hist'!M:M,'Fin Data with 6 week hist'!$A:$A,$D8)+SUMIFS('Unit Cancellations'!F:F,'Unit Cancellations'!$B:$B,$D8) -> 287398 | K8: =SUMIFS('Fin Data with 6 week hist'!N:N,'Fin Data with 6 week hist'!$A:$A,$D8)+SUMIFS('Unit Cancellations'!G:G,'Unit Cancellations'!$B:$B,$D8) -> 295501 | L8: =SUMIFS('Fin Data'!AN:AN,'Fin Data'!A:A,D8) -> 285767.33 | M8: =IFERROR(SUMIFS('Fin Data'!AO:AO,'Fin Data'!A:A,D8),"") -> 0.58587826 | O8: =AVERAGE(W8:Z8) -> 290945.75 | P8: =CE8 -> 0.61210216 | R8: =AVERAGE(W8:AD8) -> 292095.25 | S8: =BX8 -> 0.57114157 | T8: =AVERAGE(AW8:BD8) -> 235822.75 | U8: =#REF! -> #REF! | W8: =SUMIFS('Forecast Data'!$D:$D,'Forecast Data'!$C:$C,W$6,'Forecast Data'!$B:$B,$D8) -> 289133 | X8: =SUMIFS('Forecast Data'!$D:$D,'Forecast Data'!$C:$C,X$6,'Forecast Data'!$B:$B,$D8) -> 289774 | Y8: =SUMIFS('Forecast Data'!$D:$D,'Forecast Data'!$C:$C,Y$6,'Forecast Data'!$B:$B,$D8) -> 292319 | Z8: =SUMIFS('Forecast Data'!$D:$D,'Forecast Data'!$C:$C,Z$6,'Forecast Data'!$B:$B,$D8) -> 292557 | AA8: =SUMIFS('Forecast Data'!$D:$D,'Forecast Data'!$C:$C,AA$6,'Forecast Data'!$B:$B,$D8) -> 292472 | AB8: =SUMIFS('Forecast Data'!$D:$D,'Forecast Data'!$C:$C,AB$6,'Forecast Data'!$B:$B,$D8) -> 291768 | AC8: =SUMIFS('Forecast Data'!$D:$D,'Forecast Data'!$C:$C,AC$6,'Forecast Data'!$B:$B,$D8) -> 294096 | AD8: =SUMIFS('Forecast Data'!$D:$D,'Forecast Data'!$C:$C,AD$6,'Forecast Data'!$B:$B,$D8) -> 294643 | ... AH8: =SUMIFS('Forecast Data'!$D:$D,'Forecast Data'!$C:$C,AH$6,'Forecast Data'!$B:$B,$D8) -> 295151 | AJ8: =IF(SUMIFS('Forecast Data'!$E:$E,'Forecast Data'!$C:$C,AJ$6,'Forecast Data'!$B:$B,$D8)=0,"",SUMIFS('Forecast Data'!$E:$E,'Forecast Data'!$C:$C,AJ$6,'Forecast Data'!$B:$B,$D8)) -> 0.62 | AK8: =IF(SUMIFS('Forecast Data'!$E:$E,'Forecast Data'!$C:$C,AK$6,'Forecast Data'!$B:$B,$D8)=0,"",SUMIFS('Forecast Data'!$E:$E,'Forecast Data'!$C:$C,AK$6,'Forecast Data'!$B:$B,$D8)) -> 0.61 | AL8: =IF(SUMIFS('Forecast Data'!$E:$E,'Forecast Data'!$C:$C,AL$6,'Forecast Data'!$B:$B,$D8)=0,"",SUMIFS('Forecast Data'!$E:$E,'Forecast Data'!$C:$C,AL$6,'Forecast Data'!$B:$B,$D8)) -> 0.66 | AM8: =IF(SUMIFS('Forecast Data'!$E:$E,'Forecast Data'!$C:$C,AM$6,'Forecast Data'!$B:$B,$D8)=0,"",SUMIFS('Forecast Data'!$E:$E,'Forecast Data'!$C:$C,AM$6,'Forecast Data'!$B:$B,$D8)) -> 0.57 | AN8: =IF(SUMIFS('Forecast Data'!$E:$E,'Forecast Data'!$C:$C,AN$6,'Forecast Data'!$B:$B,$D8)=0,"",SUMIFS('Forecast Data'!$E:$E,'Forecast Data'!$C:$C,AN$6,'Forecast Data'!$B:$B,$D8)) -> 0.52 | AO8: =IF(SUMIFS('Forecast Data'!$E:$E,'Forecast Data'!$C:$C,AO$6,'Forecast Data'!$B:$B,$D8)=0,"",SUMIFS('Forecast Data'!$E:$E,'Forecast Data'!$C:$C,AO$6,'Forecast Data'!$B:$B,$D8)) -> 0.49 | AP8: =IF(SUMIFS('Forecast Data'!$E:$E,'Forecast Data'!$C:$C,AP$6,'Forecast Data'!$B:$B,$D8)=0,"",SUMIFS('Forecast Data'!$E:$E,'Forecast Data'!$C:$C,AP$6,'Forecast Data'!$B:$B,$D8)) -> 0.59 | AQ8: =IF(SUMIFS('Forecast Data'!$E:$E,'Forecast Data'!$C:$C,AQ$6,'Forecast Data'!$B:$B,$D8)=0,"",SUMIFS('Forecast Data'!$E:$E,'Forecast Data'!$C:$C,AQ$6,'Forecast Data'!$B:$B,$D8)) -> 0.53 | ... AU8: =IF(SUMIFS('Forecast Data'!$E:$E,'Forecast Data'!$C:$C,AU$6,'Forecast Data'!$B:$B,$D8)=0,"",SUMIFS('Forecast Data'!$E:$E,'Forecast Data'!$C:$C,AU$6,'Forecast Data'!$B:$B,$D8)) -> 0.5 | AW8: =SUMIFS('OP Units'!E:E,'OP Units'!$A:$A,$D8) -> 234450 | AX8: =SUMIFS('OP Units'!F:F,'OP Units'!$A:$A,$D8) -> 246136 | AY8: =SUMIFS('OP Units'!G:G,'OP Units'!$A:$A,$D8) -> 234443 | AZ8: =SUMIFS('OP Units'!H:H,'OP Units'!$A:$A,$D8) -> 245277 | BA8: =SUMIFS('OP Units'!I:I,'OP Units'!$A:$A,$D8) -> 233353 | BB8: =SUMIFS('OP Units'!J:J,'OP Units'!$A:$A,$D8) -> 225162 | BC8: =SUMIFS('OP Units'!K:K,'OP Units'!$A:$A,$D8) -> 234102 | BD8: =SUMIFS('OP Units'!L:L,'OP Units'!$A:$A,$D8) -> 233659 | BE8: =SUMIFS('OP Units'!M:M,'OP Units'!$A:$A,$D8) -> 233749 | BF8: =SUMIFS('OP Units'!N:N,'OP Units'!$A:$A,$D8) -> 235561 | BG8: =SUMIFS('OP Units'!O:O,'OP Units'!$A:$A,$D8) -> 238972 | BH8: =SUMIFS('OP Units'!P:P,'OP Units'!$A:$A,$D8) -> 235680 | BJ8: =IFERROR((SUMIFS('OP Units'!E:E,'OP Units'!$A:$A,$D8)-SUMIFS('Forecast Data'!$H:$H,'Forecast Data'!$C:$C,BJ$6,'Forecast Data'!$B:$B,$D8))/SUMIFS('Forecast Data'!$H:$H,'Forecast Data'!$C:$C,BJ$6,'Forecast Data'!$B:$B,$D8),"") -> 0.31006197 | BK8: =IFERROR((SUMIFS('OP Units'!F:F,'OP Units'!$A:$A,$D8)-SUMIFS('Forecast Data'!$H:$H,'Forecast Data'!$C:$C,BK$6,'Forecast Data'!$B:$B,$D8))/SUMIFS('Forecast Data'!$H:$H,'Forecast Data'!$C:$C,BK$6,'Forecast Data'!$B:$B,$D8),"") -> 0.36764256 | BL8: =IFERROR((SUMIFS('OP Units'!G:G,'OP Units'!$A:$A,$D8)-SUMIFS('Forecast Data'!$H:$H,'Forecast Data'!$C:$C,BL$6,'Forecast Data'!$B:$B,$D8))/SUMIFS('Forecast Data'!$H:$H,'Forecast Data'!$C:$C,BL$6,'Forecast Data'!$B:$B,$D8),"") -> 0.33120025 | BM8: =IFERROR((SUMIFS('OP Units'!H:H,'OP Units'!$A:$A,$D8)-SUMIFS('Forecast Data'!$H:$H,'Forecast Data'!$C:$C,BM$6,'Forecast Data'!$B:$B,$D8))/SUMIFS('Forecast Data'!$H:$H,'Forecast Data'!$C:$C,BM$6,'Forecast Data'!$B:$B,$D8),"") -> 0.31263847 | BN8: =IFERROR((SUMIFS('OP Units'!I:I,'OP Units'!$A:$A,$D8)-SUMIFS('Forecast Data'!$H:$H,'Forecast Data'!$C:$C,BN$6,'Forecast Data'!$B:$B,$D8))/SUMIFS('Forecast Data'!$H:$H,'Forecast Data'!$C:$C,BN$6,'Forecast Data'!$B:$B,$D8),"") -> 0.21163172 | BO8: =IFERROR((SUMIFS('OP Units'!J:J,'OP Units'!$A:$A,$D8)-SUMIFS('Forecast Data'!$H:$H,'Forecast Data'!$C:$C,BO$6,'Forecast Data'!$B:$B,$D8))/SUMIFS('Forecast Data'!$H:$H,'Forecast Data'!$C:$C,BO$6,'Forecast Data'!$B:$B,$D8),"") -> 0.14806524 | BP8: =IFERROR((SUMIFS('OP Units'!K:K,'OP Units'!$A:$A,$D8)-SUMIFS('Forecast Data'!$H:$H,'Forecast Data'!$C:$C,BP$6,'Forecast Data'!$B:$B,$D8))/SUMIFS('Forecast Data'!$H:$H,'Forecast Data'!$C:$C,BP$6,'Forecast Data'!$B:$B,$D8),"") -> 0.26847427 | BQ8: =IFERROR((SUMIFS('OP Units'!L:L,'OP Units'!$A:$A,$D8)-SUMIFS('Forecast Data'!$H:$H,'Forecast Data'!$C:$C,BQ$6,'Forecast Data'!$B:$B,$D8))/SUMIFS('Forecast Data'!$H:$H,'Forecast Data'!$C:$C,BQ$6,'Forecast Data'!$B:$B,$D8),"") -> 0.21616951 | BR8: =IFERROR((SUMIFS('OP Units'!M:M,'OP Units'!$A:$A,$D8)-SUMIFS('Forecast Data'!$H:$H,'Forecast Data'!$C:$C,BR$6,'Forecast Data'!$B:$B,$D8))/SUMIFS('Forecast Data'!$H:$H,'Forecast Data'!$C:$C,BR$6,'Forecast Data'!$B:$B,$D8),"") -> 0.18951997 | BS8: =IFERROR((SUMIFS('OP Units'!N:N,'OP Units'!$A:$A,$D8)-SUMIFS('Forecast Data'!$H:$H,'Forecast Data'!$C:$C,BS$6,'Forecast Data'!$B:$B,$D8))/SUMIFS('Forecast Data'!$H:$H,'Forecast Data'!$C:$C,BS$6,'Forecast Data'!$B:$B,$D8),"") -> 0.18097 | BT8: =IFERROR((SUMIFS('OP Units'!O:O,'OP Units'!$A:$A,$D8)-SUMIFS('Forecast Data'!$H:$H,'Forecast Data'!$C:$C,BT$6,'Forecast Data'!$B:$B,$D8))/SUMIFS('Forecast Data'!$H:$H,'Forecast Data'!$C:$C,BT$6,'Forecast Data'!$B:$B,$D8),"") -> 0.21982992 | BU8: =IFERROR((SUMIFS('OP Units'!P:P,'OP Units'!$A:$A,$D8)-SUMIFS('Forecast Data'!$H:$H,'Forecast Data'!$C:$C,BU$6,'Forecast Data'!$B:$B,$D8))/SUMIFS('Forecast Data'!$H:$H,'Forecast Data'!$C:$C,BU$6,'Forecast Data'!$B:$B,$D8),"") -> 0.19398146 | BW8: =(SUMIFS('Forecast Data'!H:H,'Forecast Data'!B:B,D8,'Forecast Data'!C:C,BK$6)+SUMIFS('Forecast Data'!H:H,'Forecast Data'!B:B,D8,'Forecast Data'!C:C,BL$6)+SUMIFS('Forecast Data'!H:H,'Forecast Data'!B:B,D8,'Forecast Data'!C:C,BM$6)+SUMIFS('Forecast Data'!H:H,'Forecast Data'!B:B,D8,'Forecast Data'!C:C,BN$6)+SUMIFS('Forecast Data'!H:H,'Forecast Data'!B:B,D8,'Forecast Data'!C:C,BO$6)+SUMIFS('Forecast Data'!H:H,'Forecast Data'!B:B,D8,'Forecast Data'!C:C,BP$6)+SUMIFS('Forecast Data'!H:H,'Forecast Data'!B:B,D8,'Forecast Data'!C:C,BQ$6)+SUMIFS('Forecast Data'!H:H,'Forecast Data'!B:B,D8,'Forecast Data'!C:C,BJ$6))/8 -> 185912.75 | BX8: =IFERROR((SUM(W8:AD8)-(SUMIFS('Forecast Data'!H:H,'Forecast Data'!B:B,B8,'Forecast Data'!C:C,BJ$6)+SUMIFS('Forecast Data'!H:H,'Forecast Data'!B:B,B8,'Forecast Data'!C:C,BK$6)+SUMIFS('Forecast Data'!H:H,'Forecast Data'!B:B,B8,'Forecast Data'!C:C,BL$6)+SUMIFS('Forecast Data'!H:H,'Forecast Data'!B:B,B8,'Forecast Data'!C:C,BM$6)+SUMIFS('Forecast Data'!H:H,'Forecast Data'!B:B,B8,'Forecast Data'!C:C,BN$6)+SUMIFS('Forecast Data'!H:H,'Forecast Data'!B:B,B8,'Forecast Data'!C:C,BO$6)+SUMIFS('Forecast Data'!H:H,'Forecast Data'!B:B,B8,'Forecast Data'!C:C,BP$6)+SUMIFS('Forecast Data'!H:H,'Forecast Data'!B:B,B8,'Forecast Data'!C:C,BQ$6)))/(SUMIFS('Forecast Data'!H:H,'Forecast Data'!B:B,B8,'Forecast Data'!C:C,BJ$6)+SUMIFS('Forecast Data'!H:H,'Forecast Data'!B:B,B8,'Forecast Data'!C:C,BK$6)+SUMIFS('Forecast Data'!H:H,'Forecast Data'!B:B,B8,'Forecast Data'!C:C,BL$6)+SUMIFS('Forecast Data'!H:H,'Forecast Data'!B:B,B8,'Forecast Data'!C:C,BM$6)+SUMIFS('Forecast Data'!H:H,'Forecast Data'!B:B,B8,'Forecast Data'!C:C,BN$6)+SUMIFS('Forecast Data'!H:H,'Forecast Data'!B:B,B8,'Forecast Data'!C:C,BO$6)+SUMIFS('Forecast Data'!H:H,'Forecast Data'!B:B,B8,'Forecast Data'!C:C,BP$6)+SUMIFS('Forecast Data'!H:H,'Forecast Data'!B:B,B8,'Forecast Data'!C:C,BQ$6)),"") -> 0.57114157 | BY8: =((L8-E8)/($L$4-$E$4))*$M$4 -> 0.090279292 | BZ8: =((AVERAGE(W8:AD8)-BW8)/(AVERAGE($W$4:$AD$4)-$BW$4))*$BX$4 -> 0.087313766 | CA8: =(BY8-BZ8)*100 -> 0.29655259 | CB8: =ABS(CA8)/100 -> 0.0029655259 | CD8: =(SUMIFS('Forecast Data'!H:H,'Forecast Data'!B:B,D8,'Forecast Data'!C:C,BK$6)+SUMIFS('Forecast Data'!H:H,'Forecast Data'!B:B,D8,'Forecast Data'!C:C,BL$6)+SUMIFS('Forecast Data'!H:H,'Forecast Data'!B:B,D8,'Forecast Data'!C:C,BM$6)+SUMIFS('Forecast Data'!H:H,'Forecast Data'!B:B,D8,'Forecast Data'!C:C,BJ$6))/4 -> 180476 | CE8: =IFERROR((SUM(W8:Z8)-(SUMIFS('Forecast Data'!H:H,'Forecast Data'!B:B,D8,'Forecast Data'!C:C,BJ$6)+SUMIFS('Forecast Data'!H:H,'Forecast Data'!B:B,D8,'Forecast Data'!C:C,BK$6)+SUMIFS('Forecast Data'!H:H,'Forecast Data'!B:B,D8,'Forecast Data'!C:C,BL$6)+SUMIFS('Forecast Data'!H:H,'Forecast Data'!B:B,D8,'Forecast Data'!C:C,BM$6)))/(SUMIFS('Forecast Data'!H:H,'Forecast Data'!B:B,D8,'Forecast Data'!C:C,BJ$6)+SUMIFS('Forecast Data'!H:H,'Forecast Data'!B:B,D8,'Forecast Data'!C:C,BK$6)+SUMIFS('Forecast Data'!H:H,'Forecast Data'!B:B,D8,'Forecast Data'!C:C,BL$6)+SUMIFS('Forecast Data'!H:H,'Forecast Data'!B:B,D8,'Forecast Data'!C:C,BM$6)),"") -> 0.61210216 | CF8: =(($L8-$E8)/($L$4-$E$4))*$M$4 -> 0.090279292 | CG8: =((AVERAGE(W8:Z8)-CD8)/(AVERAGE($W$4:$Z$4)-$CD$4))*$CE$4 -> 0.092616268 | CH8: =(CF8-CG8)*100 -> -0.2336976
B9: =D9 -> Gaia Herbs | D9: Gaia Herbs | E9: =SUMIFS('Fin Data'!F:F,'Fin Data'!A:A,D9) -> 24696 | F9: =SUMIFS('Fin Data with 6 week hist'!I:I,'Fin Data with 6 week hist'!$A:$A,$D9) -> 26075 | G9: =SUMIFS('Fin Data with 6 week hist'!J:J,'Fin Data with 6 week hist'!$A:$A,$D9) -> 24784 | H9: =SUMIFS('Fin Data with 6 week hist'!K:K,'Fin Data with 6 week hist'!$A:$A,$D9)+SUMIFS('Unit Cancellations'!D:D,'Unit Cancellations'!$B:$B,$D9) -> 23480 | I9: =SUMIFS('Fin Data with 6 week hist'!L:L,'Fin Data with 6 week hist'!$A:$A,$D9)+SUMIFS('Unit Cancellations'!E:E,'Unit Cancellations'!$B:$B,$D9) -> 23101 | J9: =SUMIFS('Fin Data with 6 week hist'!M:M,'Fin Data with 6 week hist'!$A:$A,$D9)+SUMIFS('Unit Cancellations'!F:F,'Unit Cancellations'!$B:$B,$D9) -> 23477 | K9: =SUMIFS('Fin Data with 6 week hist'!N:N,'Fin Data with 6 week hist'!$A:$A,$D9)+SUMIFS('Unit Cancellations'!G:G,'Unit Cancellations'!$B:$B,$D9) -> 24175 | L9: =SUMIFS('Fin Data'!AN:AN,'Fin Data'!A:A,D9) -> 24181.833 | M9: =IFERROR(SUMIFS('Fin Data'!AO:AO,'Fin Data'!A:A,D9),"") -> -0.020819836 | O9: =AVERAGE(W9:Z9) -> 27354.25 | P9: =CE9 -> 0.27171399 | R9: =AVERAGE(W9:AD9) -> 27313.625 | S9: =BX9 -> 0.28465939 | T9: =AVERAGE(AW9:BD9) -> 26771.875 | U9: =#REF! -> #REF! | W9: =SUMIFS('Forecast Data'!$D:$D,'Forecast Data'!$C:$C,W$6,'Forecast Data'!$B:$B,$D9) -> 27328 | X9: =SUMIFS('Forecast Data'!$D:$D,'Forecast Data'!$C:$C,X$6,'Forecast Data'!$B:$B,$D9) -> 27289 | Y9: =SUMIFS('Forecast Data'!$D:$D,'Forecast Data'!$C:$C,Y$6,'Forecast Data'!$B:$B,$D9) -> 27381 | Z9: =SUMIFS('Forecast Data'!$D:$D,'Forecast Data'!$C:$C,Z$6,'Forecast Data'!$B:$B,$D9) -> 27419 | AA9: =SUMIFS('Forecast Data'!$D:$D,'Forecast Data'!$C:$C,AA$6,'Forecast Data'!$B:$B,$D9) -> 27435 | AB9: =SUMIFS('Forecast Data'!$D:$D,'Forecast Data'!$C:$C,AB$6,'Forecast Data'!$B:$B,$D9) -> 27472 | AC9: =SUMIFS('Forecast Data'!$D:$D,'Forecast Data'!$C:$C,AC$6,'Forecast Data'!$B:$B,$D9) -> 27126 | AD9: =SUMIFS('Forecast Data'!$D:$D,'Forecast Data'!$C:$C,AD$6,'Forecast Data'!$B:$B,$D9) -> 27059 | ... AH9: =SUMIFS('Forecast Data'!$D:$D,'Forecast Data'!$C:$C,AH$6,'Forecast Data'!$B:$B,$D9) -> 27335 | AJ9: =IF(SUMIFS('Forecast Data'!$E:$E,'Forecast Data'!$C:$C,AJ$6,'Forecast Data'!$B:$B,$D9)=0,"",SUMIFS('Forecast Data'!$E:$E,'Forecast Data'!$C:$C,AJ$6,'Forecast Data'!$B:$B,$D9)) -> 0.25 | AK9: =IF(SUMIFS('Forecast Data'!$E:$E,'Forecast Data'!$C:$C,AK$6,'Forecast Data'!$B:$B,$D9)=0,"",SUMIFS('Forecast Data'!$E:$E,'Forecast Data'!$C:$C,AK$6,'Forecast Data'!$B:$B,$D9)) -> 0.26 | AL9: =IF(SUMIFS('Forecast Data'!$E:$E,'Forecast Data'!$C:$C,AL$6,'Forecast Data'!$B:$B,$D9)=0,"",SUMIFS('Forecast Data'!$E:$E,'Forecast Data'!$C:$C,AL$6,'Forecast Data'!$B:$B,$D9)) -> 0.3 | AM9: =IF(SUMIFS('Forecast Data'!$E:$E,'Forecast Data'!$C:$C,AM$6,'Forecast Data'!$B:$B,$D9)=0,"",SUMIFS('Forecast Data'!$E:$E,'Forecast Data'!$C:$C,AM$6,'Forecast Data'!$B:$B,$D9)) -> 0.28 | AN9: =IF(SUMIFS('Forecast Data'!$E:$E,'Forecast Data'!$C:$C,AN$6,'Forecast Data'!$B:$B,$D9)=0,"",SUMIFS('Forecast Data'!$E:$E,'Forecast Data'!$C:$C,AN$6,'Forecast Data'!$B:$B,$D9)) -> 0.29 | AO9: =IF(SUMIFS('Forecast Data'!$E:$E,'Forecast Data'!$C:$C,AO$6,'Forecast Data'!$B:$B,$D9)=0,"",SUMIFS('Forecast Data'!$E:$E,'Forecast Data'!$C:$C,AO$6,'Forecast Data'!$B:$B,$D9)) -> 0.23 | AP9: =IF(SUMIFS('Forecast Data'!$E:$E,'Forecast Data'!$C:$C,AP$6,'Forecast Data'!$B:$B,$D9)=0,"",SUMIFS('Forecast Data'!$E:$E,'Forecast Data'!$C:$C,AP$6,'Forecast Data'!$B:$B,$D9)) -> 0.33 | AQ9: =IF(SUMIFS('Forecast Data'!$E:$E,'Forecast Data'!$C:$C,AQ$6,'Forecast Data'!$B:$B,$D9)=0,"",SUMIFS('Forecast Data'!$E:$E,'Forecast Data'!$C:$C,AQ$6,'Forecast Data'!$B:$B,$D9)) -> 0.35 | ... AU9: =IF(SUMIFS('Forecast Data'!$E:$E,'Forecast Data'!$C:$C,AU$6,'Forecast Data'!$B:$B,$D9)=0,"",SUMIFS('Forecast Data'!$E:$E,'Forecast Data'!$C:$C,AU$6,'Forecast Data'!$B:$B,$D9)) -> 0.49 | AW9: =SUMIFS('OP Units'!E:E,'OP Units'!$A:$A,$D9) -> 27125 | AX9: =SUMIFS('OP Units'!F:F,'OP Units'!$A:$A,$D9) -> 28282 | AY9: =SUMIFS('OP Units'!G:G,'OP Units'!$A:$A,$D9) -> 27414 | AZ9: =SUMIFS('OP Units'!H:H,'OP Units'!$A:$A,$D9) -> 28491 | BA9: =SUMIFS('OP Units'!I:I,'OP Units'!$A:$A,$D9) -> 26911 | BB9: =SUMIFS('OP Units'!J:J,'OP Units'!$A:$A,$D9) -> 24801 | BC9: =SUMIFS('OP Units'!K:K,'OP Units'!$A:$A,$D9) -> 25920 | BD9: =SUMIFS('OP Units'!L:L,'OP Units'!$A:$A,$D9) -> 25231 | BE9: =SUMIFS('OP Units'!M:M,'OP Units'!$A:$A,$D9) -> 25403 | BF9: =SUMIFS('OP Units'!N:N,'OP Units'!$A:$A,$D9) -> 23942 | BG9: =SUMIFS('OP Units'!O:O,'OP Units'!$A:$A,$D9) -> 24211 | BH9: =SUMIFS('OP Units'!P:P,'OP Units'!$A:$A,$D9) -> 24065 | BJ9: =IFERROR((SUMIFS('OP Units'!E:E,'OP Units'!$A:$A,$D9)-SUMIFS('Forecast Data'!$H:$H,'Forecast Data'!$C:$C,BJ$6,'Forecast Data'!$B:$B,$D9))/SUMIFS('Forecast Data'!$H:$H,'Forecast Data'!$C:$C,BJ$6,'Forecast Data'!$B:$B,$D9),"") -> 0.24147558 | BK9: =IFERROR((SUMIFS('OP Units'!F:F,'OP Units'!$A:$A,$D9)-SUMIFS('Forecast Data'!$H:$H,'Forecast Data'!$C:$C,BK$6,'Forecast Data'!$B:$B,$D9))/SUMIFS('Forecast Data'!$H:$H,'Forecast Data'!$C:$C,BK$6,'Forecast Data'!$B:$B,$D9),"") -> 0.30729407 | BL9: =IFERROR((SUMIFS('OP Units'!G:G,'OP Units'!$A:$A,$D9)-SUMIFS('Forecast Data'!$H:$H,'Forecast Data'!$C:$C,BL$6,'Forecast Data'!$B:$B,$D9))/SUMIFS('Forecast Data'!$H:$H,'Forecast Data'!$C:$C,BL$6,'Forecast Data'!$B:$B,$D9),"") -> 0.29733567 | BM9: =IFERROR((SUMIFS('OP Units'!H:H,'OP Units'!$A:$A,$D9)-SUMIFS('Forecast Data'!$H:$H,'Forecast Data'!$C:$C,BM$6,'Forecast Data'!$B:$B,$D9))/SUMIFS('Forecast Data'!$H:$H,'Forecast Data'!$C:$C,BM$6,'Forecast Data'!$B:$B,$D9),"") -> 0.32980163 | BN9: =IFERROR((SUMIFS('OP Units'!I:I,'OP Units'!$A:$A,$D9)-SUMIFS('Forecast Data'!$H:$H,'Forecast Data'!$C:$C,BN$6,'Forecast Data'!$B:$B,$D9))/SUMIFS('Forecast Data'!$H:$H,'Forecast Data'!$C:$C,BN$6,'Forecast Data'!$B:$B,$D9),"") -> 0.26212363 | BO9: =IFERROR((SUMIFS('OP Units'!J:J,'OP Units'!$A:$A,$D9)-SUMIFS('Forecast Data'!$H:$H,'Forecast Data'!$C:$C,BO$6,'Forecast Data'!$B:$B,$D9))/SUMIFS('Forecast Data'!$H:$H,'Forecast Data'!$C:$C,BO$6,'Forecast Data'!$B:$B,$D9),"") -> 0.11125549 | BP9: =IFERROR((SUMIFS('OP Units'!K:K,'OP Units'!$A:$A,$D9)-SUMIFS('Forecast Data'!$H:$H,'Forecast Data'!$C:$C,BP$6,'Forecast Data'!$B:$B,$D9))/SUMIFS('Forecast Data'!$H:$H,'Forecast Data'!$C:$C,BP$6,'Forecast Data'!$B:$B,$D9),"") -> 0.26903305 | BQ9: =IFERROR((SUMIFS('OP Units'!L:L,'OP Units'!$A:$A,$D9)-SUMIFS('Forecast Data'!$H:$H,'Forecast Data'!$C:$C,BQ$6,'Forecast Data'!$B:$B,$D9))/SUMIFS('Forecast Data'!$H:$H,'Forecast Data'!$C:$C,BQ$6,'Forecast Data'!$B:$B,$D9),"") -> 0.26237054 | BR9: =IFERROR((SUMIFS('OP Units'!M:M,'OP Units'!$A:$A,$D9)-SUMIFS('Forecast Data'!$H:$H,'Forecast Data'!$C:$C,BR$6,'Forecast Data'!$B:$B,$D9))/SUMIFS('Forecast Data'!$H:$H,'Forecast Data'!$C:$C,BR$6,'Forecast Data'!$B:$B,$D9),"") -> 0.24848872 | BS9: =IFERROR((SUMIFS('OP Units'!N:N,'OP Units'!$A:$A,$D9)-SUMIFS('Forecast Data'!$H:$H,'Forecast Data'!$C:$C,BS$6,'Forecast Data'!$B:$B,$D9))/SUMIFS('Forecast Data'!$H:$H,'Forecast Data'!$C:$C,BS$6,'Forecast Data'!$B:$B,$D9),"") -> 0.26865197 | BT9: =IFERROR((SUMIFS('OP Units'!O:O,'OP Units'!$A:$A,$D9)-SUMIFS('Forecast Data'!$H:$H,'Forecast Data'!$C:$C,BT$6,'Forecast Data'!$B:$B,$D9))/SUMIFS('Forecast Data'!$H:$H,'Forecast Data'!$C:$C,BT$6,'Forecast Data'!$B:$B,$D9),"") -> 0.28413069 | BU9: =IFERROR((SUMIFS('OP Units'!P:P,'OP Units'!$A:$A,$D9)-SUMIFS('Forecast Data'!$H:$H,'Forecast Data'!$C:$C,BU$6,'Forecast Data'!$B:$B,$D9))/SUMIFS('Forecast Data'!$H:$H,'Forecast Data'!$C:$C,BU$6,'Forecast Data'!$B:$B,$D9),"") -> 0.31072985 | BW9: =(SUMIFS('Forecast Data'!H:H,'Forecast Data'!B:B,D9,'Forecast Data'!C:C,BK$6)+SUMIFS('Forecast Data'!H:H,'Forecast Data'!B:B,D9,'Forecast Data'!C:C,BL$6)+SUMIFS('Forecast Data'!H:H,'Forecast Data'!B:B,D9,'Forecast Data'!C:C,BM$6)+SUMIFS('Forecast Data'!H:H,'Forecast Data'!B:B,D9,'Forecast Data'!C:C,BN$6)+SUMIFS('Forecast Data'!H:H,'Forecast Data'!B:B,D9,'Forecast Data'!C:C,BO$6)+SUMIFS('Forecast Data'!H:H,'Forecast Data'!B:B,D9,'Forecast Data'!C:C,BP$6)+SUMIFS('Forecast Data'!H:H,'Forecast Data'!B:B,D9,'Forecast Data'!C:C,BQ$6)+SUMIFS('Forecast Data'!H:H,'Forecast Data'!B:B,D9,'Forecast Data'!C:C,BJ$6))/8 -> 21261.375 | BX9: =IFERROR((SUM(W9:AD9)-(SUMIFS('Forecast Data'!H:H,'Forecast Data'!B:B,B9,'Forecast Data'!C:C,BJ$6)+SUMIFS('Forecast Data'!H:H,'Forecast Data'!B:B,B9,'Forecast Data'!C:C,BK$6)+SUMIFS('Forecast Data'!H:H,'Forecast Data'!B:B,B9,'Forecast Data'!C:C,BL$6)+SUMIFS('Forecast Data'!H:H,'Forecast Data'!B:B,B9,'Forecast Data'!C:C,BM$6)+SUMIFS('Forecast Data'!H:H,'Forecast Data'!B:B,B9,'Forecast Data'!C:C,BN$6)+SUMIFS('Forecast Data'!H:H,'Forecast Data'!B:B,B9,'Forecast Data'!C:C,BO$6)+SUMIFS('Forecast Data'!H:H,'Forecast Data'!B:B,B9,'Forecast Data'!C:C,BP$6)+SUMIFS('Forecast Data'!H:H,'Forecast Data'!B:B,B9,'Forecast Data'!C:C,BQ$6)))/(SUMIFS('Forecast Data'!H:H,'Forecast Data'!B:B,B9,'Forecast Data'!C:C,BJ$6)+SUMIFS('Forecast Data'!H:H,'Forecast Data'!B:B,B9,'Forecast Data'!C:C,BK$6)+SUMIFS('Forecast Data'!H:H,'Forecast Data'!B:B,B9,'Forecast Data'!C:C,BL$6)+SUMIFS('Forecast Data'!H:H,'Forecast Data'!B:B,B9,'Forecast Data'!C:C,BM$6)+SUMIFS('Forecast Data'!H:H,'Forecast Data'!B:B,B9,'Forecast Data'!C:C,BN$6)+SUMIFS('Forecast Data'!H:H,'Forecast Data'!B:B,B9,'Forecast Data'!C:C,BO$6)+SUMIFS('Forecast Data'!H:H,'Forecast Data'!B:B,B9,'Forecast Data'!C:C,BP$6)+SUMIFS('Forecast Data'!H:H,'Forecast Data'!B:B,B9,'Forecast Data'!C:C,BQ$6)),"") -> 0.28465939 | BY9: =((L9-E9)/($L$4-$E$4))*$M$4 -> -0.0004396853 | BZ9: =((AVERAGE(W9:AD9)-BW9)/(AVERAGE($W$4:$AD$4)-$BW$4))*$BX$4 -> 0.0049767593 | CA9: =(BY9-BZ9)*100 -> -0.54164446 | CB9: =ABS(CA9)/100 -> 0.0054164446 | CD9: =(SUMIFS('Forecast Data'!H:H,'Forecast Data'!B:B,D9,'Forecast Data'!C:C,BK$6)+SUMIFS('Forecast Data'!H:H,'Forecast Data'!B:B,D9,'Forecast Data'!C:C,BL$6)+SUMIFS('Forecast Data'!H:H,'Forecast Data'!B:B,D9,'Forecast Data'!C:C,BM$6)+SUMIFS('Forecast Data'!H:H,'Forecast Data'!B:B,D9,'Forecast Data'!C:C,BJ$6))/4 -> 21509.75 | CE9: =IFERROR((SUM(W9:Z9)-(SUMIFS('Forecast Data'!H:H,'Forecast Data'!B:B,D9,'Forecast Data'!C:C,BJ$6)+SUMIFS('Forecast Data'!H:H,'Forecast Data'!B:B,D9,'Forecast Data'!C:C,BK$6)+SUMIFS('Forecast Data'!H:H,'Forecast Data'!B:B,D9,'Forecast Data'!C:C,BL$6)+SUMIFS('Forecast Data'!H:H,'Forecast Data'!B:B,D9,'Forecast Data'!C:C,BM$6)))/(SUMIFS('Forecast Data'!H:H,'Forecast Data'!B:B,D9,'Forecast Data'!C:C,BJ$6)+SUMIFS('Forecast Data'!H:H,'Forecast Data'!B:B,D9,'Forecast Data'!C:C,BK$6)+SUMIFS('Forecast Data'!H:H,'Forecast Data'!B:B,D9,'Forecast Data'!C:C,BL$6)+SUMIFS('Forecast Data'!H:H,'Forecast Data'!B:B,D9,'Forecast Data'!C:C,BM$6)),"") -> 0.27171399 | CF9: =(($L9-$E9)/($L$4-$E$4))*$M$4 -> -0.0004396853 | CG9: =((AVERAGE(W9:Z9)-CD9)/(AVERAGE($W$4:$Z$4)-$CD$4))*$CE$4 -> 0.0048999457 | CH9: =(CF9-CG9)*100 -> -0.5339631
D10: Bath & Body Works | E10: =SUMIFS('Fin Data'!F:F,'Fin Data'!A:A,D10) -> 0 | F10: =SUMIFS('Fin Data with 6 week hist'!I:I,'Fin Data with 6 week hist'!$A:$A,$D10) -> 174 | G10: =SUMIFS('Fin Data with 6 week hist'!J:J,'Fin Data with 6 week hist'!$A:$A,$D10) -> 1556 | H10: =SUMIFS('Fin Data with 6 week hist'!K:K,'Fin Data with 6 week hist'!$A:$A,$D10)+SUMIFS('Unit Cancellations'!D:D,'Unit Cancellations'!$B:$B,$D10) -> 4210 | I10: =SUMIFS('Fin Data with 6 week hist'!L:L,'Fin Data with 6 week hist'!$A:$A,$D10)+SUMIFS('Unit Cancellations'!E:E,'Unit Cancellations'!$B:$B,$D10) -> 5288 | J10: =SUMIFS('Fin Data with 6 week hist'!M:M,'Fin Data with 6 week hist'!$A:$A,$D10)+SUMIFS('Unit Cancellations'!F:F,'Unit Cancellations'!$B:$B,$D10) -> 7186 | K10: =SUMIFS('Fin Data with 6 week hist'!N:N,'Fin Data with 6 week hist'!$A:$A,$D10)+SUMIFS('Unit Cancellations'!G:G,'Unit Cancellations'!$B:$B,$D10) -> 9391 | L10: =SUMIFS('Fin Data'!AN:AN,'Fin Data'!A:A,D10) -> 4634 | M10: =IFERROR(SUMIFS('Fin Data'!AO:AO,'Fin Data'!A:A,D10),"") -> 0 | O10: =AVERAGE(W10:Z10) -> 8125.25 | P10: =CE10 | R10: =AVERAGE(W10:AD10) -> 9512.875 | S10: =BX10 | T10: =AVERAGE(AW10:BD10) -> 0 | U10: =#REF! -> #REF! | W10: =SUMIFS('Forecast Data'!$D:$D,'Forecast Data'!$C:$C,W$6,'Forecast Data'!$B:$B,$D10) -> 8120 | X10: =SUMIFS('Forecast Data'!$D:$D,'Forecast Data'!$C:$C,X$6,'Forecast Data'!$B:$B,$D10) -> 8121 | Y10: =SUMIFS('Forecast Data'!$D:$D,'Forecast Data'!$C:$C,Y$6,'Forecast Data'!$B:$B,$D10) -> 8121 | Z10: =SUMIFS('Forecast Data'!$D:$D,'Forecast Data'!$C:$C,Z$6,'Forecast Data'!$B:$B,$D10) -> 8139 | AA10: =SUMIFS('Forecast Data'!$D:$D,'Forecast Data'!$C:$C,AA$6,'Forecast Data'!$B:$B,$D10) -> 8156 | AB10: =SUMIFS('Forecast Data'!$D:$D,'Forecast Data'!$C:$C,AB$6,'Forecast Data'!$B:$B,$D10) -> 8543 | AC10: =SUMIFS('Forecast Data'!$D:$D,'Forecast Data'!$C:$C,AC$6,'Forecast Data'!$B:$B,$D10) -> 14442 | AD10: =SUMIFS('Forecast Data'!$D:$D,'Forecast Data'!$C:$C,AD$6,'Forecast Data'!$B:$B,$D10) -> 12461 | ... AH10: =SUMIFS('Forecast Data'!$D:$D,'Forecast Data'!$C:$C,AH$6,'Forecast Data'!$B:$B,$D10) -> 9672 | AJ10: =IF(SUMIFS('Forecast Data'!$E:$E,'Forecast Data'!$C:$C,AJ$6,'Forecast Data'!$B:$B,$D10)=0,"",SUMIFS('Forecast Data'!$E:$E,'Forecast Data'!$C:$C,AJ$6,'Forecast Data'!$B:$B,$D10)) | AK10: =IF(SUMIFS('Forecast Data'!$E:$E,'Forecast Data'!$C:$C,AK$6,'Forecast Data'!$B:$B,$D10)=0,"",SUMIFS('Forecast Data'!$E:$E,'Forecast Data'!$C:$C,AK$6,'Forecast Data'!$B:$B,$D10)) | AL10: =IF(SUMIFS('Forecast Data'!$E:$E,'Forecast Data'!$C:$C,AL$6,'Forecast Data'!$B:$B,$D10)=0,"",SUMIFS('Forecast Data'!$E:$E,'Forecast Data'!$C:$C,AL$6,'Forecast Data'!$B:$B,$D10)) | AM10: =IF(SUMIFS('Forecast Data'!$E:$E,'Forecast Data'!$C:$C,AM$6,'Forecast Data'!$B:$B,$D10)=0,"",SUMIFS('Forecast Data'!$E:$E,'Forecast Data'!$C:$C,AM$6,'Forecast Data'!$B:$B,$D10)) | AN10: =IF(SUMIFS('Forecast Data'!$E:$E,'Forecast Data'!$C:$C,AN$6,'Forecast Data'!$B:$B,$D10)=0,"",SUMIFS('Forecast Data'!$E:$E,'Forecast Data'!$C:$C,AN$6,'Forecast Data'!$B:$B,$D10)) | AO10: =IF(SUMIFS('Forecast Data'!$E:$E,'Forecast Data'!$C:$C,AO$6,'Forecast Data'!$B:$B,$D10)=0,"",SUMIFS('Forecast Data'!$E:$E,'Forecast Data'!$C:$C,AO$6,'Forecast Data'!$B:$B,$D10)) | AP10: =IF(SUMIFS('Forecast Data'!$E:$E,'Forecast Data'!$C:$C,AP$6,'Forecast Data'!$B:$B,$D10)=0,"",SUMIFS('Forecast Data'!$E:$E,'Forecast Data'!$C:$C,AP$6,'Forecast Data'!$B:$B,$D10)) | AQ10: =IF(SUMIFS('Forecast Data'!$E:$E,'Forecast Data'!$C:$C,AQ$6,'Forecast Data'!$B:$B,$D10)=0,"",SUMIFS('Forecast Data'!$E:$E,'Forecast Data'!$C:$C,AQ$6,'Forecast Data'!$B:$B,$D10)) | ... AU10: =IF(SUMIFS('Forecast Data'!$E:$E,'Forecast Data'!$C:$C,AU$6,'Forecast Data'!$B:$B,$D10)=0,"",SUMIFS('Forecast Data'!$E:$E,'Forecast Data'!$C:$C,AU$6,'Forecast Data'!$B:$B,$D10)) | AW10: =SUMIFS('OP Units'!E:E,'OP Units'!$A:$A,$D10) -> 0 | AX10: =SUMIFS('OP Units'!F:F,'OP Units'!$A:$A,$D10) -> 0 | AY10: =SUMIFS('OP Units'!G:G,'OP Units'!$A:$A,$D10) -> 0 | AZ10: =SUMIFS('OP Units'!H:H,'OP Units'!$A:$A,$D10) -> 0 | BA10: =SUMIFS('OP Units'!I:I,'OP Units'!$A:$A,$D10) -> 0 | BB10: =SUMIFS('OP Units'!J:J,'OP Units'!$A:$A,$D10) -> 0 | BC10: =SUMIFS('OP Units'!K:K,'OP Units'!$A:$A,$D10) -> 0 | BD10: =SUMIFS('OP Units'!L:L,'OP Units'!$A:$A,$D10) -> 0 | BE10: =SUMIFS('OP Units'!M:M,'OP Units'!$A:$A,$D10) -> 0 | BF10: =SUMIFS('OP Units'!N:N,'OP Units'!$A:$A,$D10) -> 0 | BG10: =SUMIFS('OP Units'!O:O,'OP Units'!$A:$A,$D10) -> 0 | BH10: =SUMIFS('OP Units'!P:P,'OP Units'!$A:$A,$D10) -> 0 | BJ10: =IFERROR((SUMIFS('OP Units'!E:E,'OP Units'!$A:$A,$D10)-SUMIFS('Forecast Data'!$H:$H,'Forecast Data'!$C:$C,BJ$6,'Forecast Data'!$B:$B,$D10))/SUMIFS('Forecast Data'!$H:$H,'Forecast Data'!$C:$C,BJ$6,'Forecast Data'!$B:$B,$D10),"") | BK10: =IFERROR((SUMIFS('OP Units'!F:F,'OP Units'!$A:$A,$D10)-SUMIFS('Forecast Data'!$H:$H,'Forecast Data'!$C:$C,BK$6,'Forecast Data'!$B:$B,$D10))/SUMIFS('Forecast Data'!$H:$H,'Forecast Data'!$C:$C,BK$6,'Forecast Data'!$B:$B,$D10),"") | BL10: =IFERROR((SUMIFS('OP Units'!G:G,'OP Units'!$A:$A,$D10)-SUMIFS('Forecast Data'!$H:$H,'Forecast Data'!$C:$C,BL$6,'Forecast Data'!$B:$B,$D10))/SUMIFS('Forecast Data'!$H:$H,'Forecast Data'!$C:$C,BL$6,'Forecast Data'!$B:$B,$D10),"") | BM10: =IFERROR((SUMIFS('OP Units'!H:H,'OP Units'!$A:$A,$D10)-SUMIFS('Forecast Data'!$H:$H,'Forecast Data'!$C:$C,BM$6,'Forecast Data'!$B:$B,$D10))/SUMIFS('Forecast Data'!$H:$H,'Forecast Data'!$C:$C,BM$6,'Forecast Data'!$B:$B,$D10),"") | BN10: =IFERROR((SUMIFS('OP Units'!I:I,'OP Units'!$A:$A,$D10)-SUMIFS('Forecast Data'!$H:$H,'Forecast Data'!$C:$C,BN$6,'Forecast Data'!$B:$B,$D10))/SUMIFS('Forecast Data'!$H:$H,'Forecast Data'!$C:$C,BN$6,'Forecast Data'!$B:$B,$D10),"") | BO10: =IFERROR((SUMIFS('OP Units'!J:J,'OP Units'!$A:$A,$D10)-SUMIFS('Forecast Data'!$H:$H,'Forecast Data'!$C:$C,BO$6,'Forecast Data'!$B:$B,$D10))/SUMIFS('Forecast Data'!$H:$H,'Forecast Data'!$C:$C,BO$6,'Forecast Data'!$B:$B,$D10),"") | BP10: =IFERROR((SUMIFS('OP Units'!K:K,'OP Units'!$A:$A,$D10)-SUMIFS('Forecast Data'!$H:$H,'Forecast Data'!$C:$C,BP$6,'Forecast Data'!$B:$B,$D10))/SUMIFS('Forecast Data'!$H:$H,'Forecast Data'!$C:$C,BP$6,'Forecast Data'!$B:$B,$D10),"") | BQ10: =IFERROR((SUMIFS('OP Units'!L:L,'OP Units'!$A:$A,$D10)-SUMIFS('Forecast Data'!$H:$H,'Forecast Data'!$C:$C,BQ$6,'Forecast Data'!$B:$B,$D10))/SUMIFS('Forecast Data'!$H:$H,'Forecast Data'!$C:$C,BQ$6,'Forecast Data'!$B:$B,$D10),"") | BR10: =IFERROR((SUMIFS('OP Units'!M:M,'OP Units'!$A:$A,$D10)-SUMIFS('Forecast Data'!$H:$H,'Forecast Data'!$C:$C,BR$6,'Forecast Data'!$B:$B,$D10))/SUMIFS('Forecast Data'!$H:$H,'Forecast Data'!$C:$C,BR$6,'Forecast Data'!$B:$B,$D10),"") | BS10: =IFERROR((SUMIFS('OP Units'!N:N,'OP Units'!$A:$A,$D10)-SUMIFS('Forecast Data'!$H:$H,'Forecast Data'!$C:$C,BS$6,'Forecast Data'!$B:$B,$D10))/SUMIFS('Forecast Data'!$H:$H,'Forecast Data'!$C:$C,BS$6,'Forecast Data'!$B:$B,$D10),"") | BT10: =IFERROR((SUMIFS('OP Units'!O:O,'OP Units'!$A:$A,$D10)-SUMIFS('Forecast Data'!$H:$H,'Forecast Data'!$C:$C,BT$6,'Forecast Data'!$B:$B,$D10))/SUMIFS('Forecast Data'!$H:$H,'Forecast Data'!$C:$C,BT$6,'Forecast Data'!$B:$B,$D10),"") | BU10: =IFERROR((SUMIFS('OP Units'!P:P,'OP Units'!$A:$A,$D10)-SUMIFS('Forecast Data'!$H:$H,'Forecast Data'!$C:$C,BU$6,'Forecast Data'!$B:$B,$D10))/SUMIFS('Forecast Data'!$H:$H,'Forecast Data'!$C:$C,BU$6,'Forecast Data'!$B:$B,$D10),"") | BW10: =(SUMIFS('Forecast Data'!H:H,'Forecast Data'!B:B,D10,'Forecast Data'!C:C,BK$6)+SUMIFS('Forecast Data'!H:H,'Forecast Data'!B:B,D10,'Forecast Data'!C:C,BL$6)+SUMIFS('Forecast Data'!H:H,'Forecast Data'!B:B,D10,'Forecast Data'!C:C,BM$6)+SUMIFS('Forecast Data'!H:H,'Forecast Data'!B:B,D10,'Forecast Data'!C:C,BN$6)+SUMIFS('Forecast Data'!H:H,'Forecast Data'!B:B,D10,'Forecast Data'!C:C,BO$6)+SUMIFS('Forecast Data'!H:H,'Forecast Data'!B:B,D10,'Forecast Data'!C:C,BP$6)+SUMIFS('Forecast Data'!H:H,'Forecast Data'!B:B,D10,'Forecast Data'!C:C,BQ$6)+SUMIFS('Forecast Data'!H:H,'Forecast Data'!B:B,D10,'Forecast Data'!C:C,BJ$6))/8 -> 0 | BX10: =IFERROR((SUM(W10:AD10)-(SUMIFS('Forecast Data'!H:H,'Forecast Data'!B:B,B10,'Forecast Data'!C:C,BJ$6)+SUMIFS('Forecast Data'!H:H,'Forecast Data'!B:B,B10,'Forecast Data'!C:C,BK$6)+SUMIFS('Forecast Data'!H:H,'Forecast Data'!B:B,B10,'Forecast Data'!C:C,BL$6)+SUMIFS('Forecast Data'!H:H,'Forecast Data'!B:B,B10,'Forecast Data'!C:C,BM$6)+SUMIFS('Forecast Data'!H:H,'Forecast Data'!B:B,B10,'Forecast Data'!C:C,BN$6)+SUMIFS('Forecast Data'!H:H,'Forecast Data'!B:B,B10,'Forecast Data'!C:C,BO$6)+SUMIFS('Forecast Data'!H:H,'Forecast Data'!B:B,B10,'Forecast Data'!C:C,BP$6)+SUMIFS('Forecast Data'!H:H,'Forecast Data'!B:B,B10,'Forecast Data'!C:C,BQ$6)))/(SUMIFS('Forecast Data'!H:H,'Forecast Data'!B:B,B10,'Forecast Data'!C:C,BJ$6)+SUMIFS('Forecast Data'!H:H,'Forecast Data'!B:B,B10,'Forecast Data'!C:C,BK$6)+SUMIFS('Forecast Data'!H:H,'Forecast Data'!B:B,B10,'Forecast Data'!C:C,BL$6)+SUMIFS('Forecast Data'!H:H,'Forecast Data'!B:B,B10,'Forecast Data'!C:C,BM$6)+SUMIFS('Forecast Data'!H:H,'Forecast Data'!B:B,B10,'Forecast Data'!C:C,BN$6)+SUMIFS('Forecast Data'!H:H,'Forecast Data'!B:B,B10,'Forecast Data'!C:C,BO$6)+SUMIFS('Forecast Data'!H:H,'Forecast Data'!B:B,B10,'Forecast Data'!C:C,BP$6)+SUMIFS('Forecast Data'!H:H,'Forecast Data'!B:B,B10,'Forecast Data'!C:C,BQ$6)),"") | BY10: =((L10-E10)/($L$4-$E$4))*$M$4 -> 0.0039627261 | BZ10: =((AVERAGE(W10:AD10)-BW10)/(AVERAGE($W$4:$AD$4)-$BW$4))*$BX$4 -> 0.0078224278 | CA10: =(BY10-BZ10)*100 -> -0.38597017 | CB10: =ABS(CA10)/100 -> 0.0038597017 | CD10: =(SUMIFS('Forecast Data'!H:H,'Forecast Data'!B:B,D10,'Forecast Data'!C:C,BK$6)+SUMIFS('Forecast Data'!H:H,'Forecast Data'!B:B,D10,'Forecast Data'!C:C,BL$6)+SUMIFS('Forecast Data'!H:H,'Forecast Data'!B:B,D10,'Forecast Data'!C:C,BM$6)+SUMIFS('Forecast Data'!H:H,'Forecast Data'!B:B,D10,'Forecast Data'!C:C,BJ$6))/4 -> 0 | CE10: =IFERROR((SUM(W10:Z10)-(SUMIFS('Forecast Data'!H:H,'Forecast Data'!B:B,B10,'Forecast Data'!C:C,BJ$6)+SUMIFS('Forecast Data'!H:H,'Forecast Data'!B:B,B10,'Forecast Data'!C:C,BK$6)+SUMIFS('Forecast Data'!H:H,'Forecast Data'!B:B,B10,'Forecast Data'!C:C,BL$6)+SUMIFS('Forecast Data'!H:H,'Forecast Data'!B:B,B10,'Forecast Data'!C:C,BM$6)))/(SUMIFS('Forecast Data'!H:H,'Forecast Data'!B:B,B10,'Forecast Data'!C:C,BJ$6)+SUMIFS('Forecast Data'!H:H,'Forecast Data'!B:B,B10,'Forecast Data'!C:C,BK$6)+SUMIFS('Forecast Data'!H:H,'Forecast Data'!B:B,B10,'Forecast Data'!C:C,BL$6)+SUMIFS('Forecast Data'!H:H,'Forecast Data'!B:B,B10,'Forecast Data'!C:C,BM$6)),"") | CF10: =(($L10-$E10)/($L$4-$E$4))*$M$4 -> 0.0039627261 | CG10: =((AVERAGE(W10:Z10)-CD10)/(AVERAGE($W$4:$Z$4)-$CD$4))*$CE$4 -> 0.0068120941 | CH10: =(CF10-CG10)*100 -> -0.2849368
B11: =D11 -> Youtheory | C11: Holiday | D11: Youtheory | E11: =SUMIFS('Fin Data'!F:F,'Fin Data'!A:A,D11) -> 17051 | F11: =SUMIFS('Fin Data with 6 week hist'!I:I,'Fin Data with 6 week hist'!$A:$A,$D11) -> 19042 | G11: =SUMIFS('Fin Data with 6 week hist'!J:J,'Fin Data with 6 week hist'!$A:$A,$D11) -> 18655 | H11: =SUMIFS('Fin Data with 6 week hist'!K:K,'Fin Data with 6 week hist'!$A:$A,$D11)+SUMIFS('Unit Cancellations'!D:D,'Unit Cancellations'!$B:$B,$D11) -> 19158 | I11: =SUMIFS('Fin Data with 6 week hist'!L:L,'Fin Data with 6 week hist'!$A:$A,$D11)+SUMIFS('Unit Cancellations'!E:E,'Unit Cancellations'!$B:$B,$D11) -> 19064 | J11: =SUMIFS('Fin Data with 6 week hist'!M:M,'Fin Data with 6 week hist'!$A:$A,$D11)+SUMIFS('Unit Cancellations'!F:F,'Unit Cancellations'!$B:$B,$D11) -> 19694 | K11: =SUMIFS('Fin Data with 6 week hist'!N:N,'Fin Data with 6 week hist'!$A:$A,$D11)+SUMIFS('Unit Cancellations'!G:G,'Unit Cancellations'!$B:$B,$D11) -> 19899 | L11: =SUMIFS('Fin Data'!AN:AN,'Fin Data'!A:A,D11) -> 19252.5 | M11: =IFERROR(SUMIFS('Fin Data'!AO:AO,'Fin Data'!A:A,D11),"") -> 0.12911266 | O11: =AVERAGE(W11:Z11) -> 23449.25 | P11: =CE11 -> 0.43631324 | R11: =AVERAGE(W11:AD11) -> 22215.5 | S11: =BX11 -> 0.37412631 | T11: =AVERAGE(AW11:BD11) -> 14043.625 | U11: =#REF! -> #REF! | W11: =SUMIFS('Forecast Data'!$D:$D,'Forecast Data'!$C:$C,W$6,'Forecast Data'!$B:$B,$D11) -> 29395 | X11: =SUMIFS('Forecast Data'!$D:$D,'Forecast Data'!$C:$C,X$6,'Forecast Data'!$B:$B,$D11) -> 22765 | Y11: =SUMIFS('Forecast Data'!$D:$D,'Forecast Data'!$C:$C,Y$6,'Forecast Data'!$B:$B,$D11) -> 20998 | Z11: =SUMIFS('Forecast Data'!$D:$D,'Forecast Data'!$C:$C,Z$6,'Forecast Data'!$B:$B,$D11) -> 20639 | AA11: =SUMIFS('Forecast Data'!$D:$D,'Forecast Data'!$C:$C,AA$6,'Forecast Data'!$B:$B,$D11) -> 20651 | AB11: =SUMIFS('Forecast Data'!$D:$D,'Forecast Data'!$C:$C,AB$6,'Forecast Data'!$B:$B,$D11) -> 21121 | AC11: =SUMIFS('Forecast Data'!$D:$D,'Forecast Data'!$C:$C,AC$6,'Forecast Data'!$B:$B,$D11) -> 21009 | AD11: =SUMIFS('Forecast Data'!$D:$D,'Forecast Data'!$C:$C,AD$6,'Forecast Data'!$B:$B,$D11) -> 21146 | ... AH11: =SUMIFS('Forecast Data'!$D:$D,'Forecast Data'!$C:$C,AH$6,'Forecast Data'!$B:$B,$D11) -> 22162 | AJ11: =IF(SUMIFS('Forecast Data'!$E:$E,'Forecast Data'!$C:$C,AJ$6,'Forecast Data'!$B:$B,$D11)=0,"",SUMIFS('Forecast Data'!$E:$E,'Forecast Data'!$C:$C,AJ$6,'Forecast Data'!$B:$B,$D11)) -> 0.84 | AK11: =IF(SUMIFS('Forecast Data'!$E:$E,'Forecast Data'!$C:$C,AK$6,'Forecast Data'!$B:$B,$D11)=0,"",SUMIFS('Forecast Data'!$E:$E,'Forecast Data'!$C:$C,AK$6,'Forecast Data'!$B:$B,$D11)) -> 0.41 | AL11: =IF(SUMIFS('Forecast Data'!$E:$E,'Forecast Data'!$C:$C,AL$6,'Forecast Data'!$B:$B,$D11)=0,"",SUMIFS('Forecast Data'!$E:$E,'Forecast Data'!$C:$C,AL$6,'Forecast Data'!$B:$B,$D11)) -> 0.28 | AM11: =IF(SUMIFS('Forecast Data'!$E:$E,'Forecast Data'!$C:$C,AM$6,'Forecast Data'!$B:$B,$D11)=0,"",SUMIFS('Forecast Data'!$E:$E,'Forecast Data'!$C:$C,AM$6,'Forecast Data'!$B:$B,$D11)) -> 0.23 | AN11: =IF(SUMIFS('Forecast Data'!$E:$E,'Forecast Data'!$C:$C,AN$6,'Forecast Data'!$B:$B,$D11)=0,"",SUMIFS('Forecast Data'!$E:$E,'Forecast Data'!$C:$C,AN$6,'Forecast Data'!$B:$B,$D11)) -> 0.23 | AO11: =IF(SUMIFS('Forecast Data'!$E:$E,'Forecast Data'!$C:$C,AO$6,'Forecast Data'!$B:$B,$D11)=0,"",SUMIFS('Forecast Data'!$E:$E,'Forecast Data'!$C:$C,AO$6,'Forecast Data'!$B:$B,$D11)) -> 0.34 | AP11: =IF(SUMIFS('Forecast Data'!$E:$E,'Forecast Data'!$C:$C,AP$6,'Forecast Data'!$B:$B,$D11)=0,"",SUMIFS('Forecast Data'!$E:$E,'Forecast Data'!$C:$C,AP$6,'Forecast Data'!$B:$B,$D11)) -> 0.35 | AQ11: =IF(SUMIFS('Forecast Data'!$E:$E,'Forecast Data'!$C:$C,AQ$6,'Forecast Data'!$B:$B,$D11)=0,"",SUMIFS('Forecast Data'!$E:$E,'Forecast Data'!$C:$C,AQ$6,'Forecast Data'!$B:$B,$D11)) -> 0.33 | ... AU11: =IF(SUMIFS('Forecast Data'!$E:$E,'Forecast Data'!$C:$C,AU$6,'Forecast Data'!$B:$B,$D11)=0,"",SUMIFS('Forecast Data'!$E:$E,'Forecast Data'!$C:$C,AU$6,'Forecast Data'!$B:$B,$D11)) -> 0.39 | AW11: =SUMIFS('OP Units'!E:E,'OP Units'!$A:$A,$D11) -> 13755 | AX11: =SUMIFS('OP Units'!F:F,'OP Units'!$A:$A,$D11) -> 15567 | AY11: =SUMIFS('OP Units'!G:G,'OP Units'!$A:$A,$D11) -> 12965 | AZ11: =SUMIFS('OP Units'!H:H,'OP Units'!$A:$A,$D11) -> 12630 | BA11: =SUMIFS('OP Units'!I:I,'OP Units'!$A:$A,$D11) -> 13983 | BB11: =SUMIFS('OP Units'!J:J,'OP Units'!$A:$A,$D11) -> 14931 | BC11: =SUMIFS('OP Units'!K:K,'OP Units'!$A:$A,$D11) -> 14768 | BD11: =SUMIFS('OP Units'!L:L,'OP Units'!$A:$A,$D11) -> 13750 | BE11: =SUMIFS('OP Units'!M:M,'OP Units'!$A:$A,$D11) -> 13171 | BF11: =SUMIFS('OP Units'!N:N,'OP Units'!$A:$A,$D11) -> 12930 | BG11: =SUMIFS('OP Units'!O:O,'OP Units'!$A:$A,$D11) -> 15294 | BH11: =SUMIFS('OP Units'!P:P,'OP Units'!$A:$A,$D11) -> 17408 | BJ11: =IFERROR((SUMIFS('OP Units'!E:E,'OP Units'!$A:$A,$D11)-SUMIFS('Forecast Data'!$H:$H,'Forecast Data'!$C:$C,BJ$6,'Forecast Data'!$B:$B,$D11))/SUMIFS('Forecast Data'!$H:$H,'Forecast Data'!$C:$C,BJ$6,'Forecast Data'!$B:$B,$D11),"") -> -0.13982865 | BK11: =IFERROR((SUMIFS('OP Units'!F:F,'OP Units'!$A:$A,$D11)-SUMIFS('Forecast Data'!$H:$H,'Forecast Data'!$C:$C,BK$6,'Forecast Data'!$B:$B,$D11))/SUMIFS('Forecast Data'!$H:$H,'Forecast Data'!$C:$C,BK$6,'Forecast Data'!$B:$B,$D11),"") -> -0.036099071 | BL11: =IFERROR((SUMIFS('OP Units'!G:G,'OP Units'!$A:$A,$D11)-SUMIFS('Forecast Data'!$H:$H,'Forecast Data'!$C:$C,BL$6,'Forecast Data'!$B:$B,$D11))/SUMIFS('Forecast Data'!$H:$H,'Forecast Data'!$C:$C,BL$6,'Forecast Data'!$B:$B,$D11),"") -> -0.20974034 | BM11: =IFERROR((SUMIFS('OP Units'!H:H,'OP Units'!$A:$A,$D11)-SUMIFS('Forecast Data'!$H:$H,'Forecast Data'!$C:$C,BM$6,'Forecast Data'!$B:$B,$D11))/SUMIFS('Forecast Data'!$H:$H,'Forecast Data'!$C:$C,BM$6,'Forecast Data'!$B:$B,$D11),"") -> -0.24628513 | BN11: =IFERROR((SUMIFS('OP Units'!I:I,'OP Units'!$A:$A,$D11)-SUMIFS('Forecast Data'!$H:$H,'Forecast Data'!$C:$C,BN$6,'Forecast Data'!$B:$B,$D11))/SUMIFS('Forecast Data'!$H:$H,'Forecast Data'!$C:$C,BN$6,'Forecast Data'!$B:$B,$D11),"") -> -0.16509434 | BO11: =IFERROR((SUMIFS('OP Units'!J:J,'OP Units'!$A:$A,$D11)-SUMIFS('Forecast Data'!$H:$H,'Forecast Data'!$C:$C,BO$6,'Forecast Data'!$B:$B,$D11))/SUMIFS('Forecast Data'!$H:$H,'Forecast Data'!$C:$C,BO$6,'Forecast Data'!$B:$B,$D11),"") -> -0.053982133 | BP11: =IFERROR((SUMIFS('OP Units'!K:K,'OP Units'!$A:$A,$D11)-SUMIFS('Forecast Data'!$H:$H,'Forecast Data'!$C:$C,BP$6,'Forecast Data'!$B:$B,$D11))/SUMIFS('Forecast Data'!$H:$H,'Forecast Data'!$C:$C,BP$6,'Forecast Data'!$B:$B,$D11),"") -> -0.050838743 | BQ11: =IFERROR((SUMIFS('OP Units'!L:L,'OP Units'!$A:$A,$D11)-SUMIFS('Forecast Data'!$H:$H,'Forecast Data'!$C:$C,BQ$6,'Forecast Data'!$B:$B,$D11))/SUMIFS('Forecast Data'!$H:$H,'Forecast Data'!$C:$C,BQ$6,'Forecast Data'!$B:$B,$D11),"") -> -0.13749843 | BR11: =IFERROR((SUMIFS('OP Units'!M:M,'OP Units'!$A:$A,$D11)-SUMIFS('Forecast Data'!$H:$H,'Forecast Data'!$C:$C,BR$6,'Forecast Data'!$B:$B,$D11))/SUMIFS('Forecast Data'!$H:$H,'Forecast Data'!$C:$C,BR$6,'Forecast Data'!$B:$B,$D11),"") -> -0.19908787 | BS11: =IFERROR((SUMIFS('OP Units'!N:N,'OP Units'!$A:$A,$D11)-SUMIFS('Forecast Data'!$H:$H,'Forecast Data'!$C:$C,BS$6,'Forecast Data'!$B:$B,$D11))/SUMIFS('Forecast Data'!$H:$H,'Forecast Data'!$C:$C,BS$6,'Forecast Data'!$B:$B,$D11),"") -> -0.20066766 | BT11: =IFERROR((SUMIFS('OP Units'!O:O,'OP Units'!$A:$A,$D11)-SUMIFS('Forecast Data'!$H:$H,'Forecast Data'!$C:$C,BT$6,'Forecast Data'!$B:$B,$D11))/SUMIFS('Forecast Data'!$H:$H,'Forecast Data'!$C:$C,BT$6,'Forecast Data'!$B:$B,$D11),"") -> -0.051358392 | BU11: =IFERROR((SUMIFS('OP Units'!P:P,'OP Units'!$A:$A,$D11)-SUMIFS('Forecast Data'!$H:$H,'Forecast Data'!$C:$C,BU$6,'Forecast Data'!$B:$B,$D11))/SUMIFS('Forecast Data'!$H:$H,'Forecast Data'!$C:$C,BU$6,'Forecast Data'!$B:$B,$D11),"") -> 0.09326132 | BW11: =(SUMIFS('Forecast Data'!H:H,'Forecast Data'!B:B,D11,'Forecast Data'!C:C,BK$6)+SUMIFS('Forecast Data'!H:H,'Forecast Data'!B:B,D11,'Forecast Data'!C:C,BL$6)+SUMIFS('Forecast Data'!H:H,'Forecast Data'!B:B,D11,'Forecast Data'!C:C,BM$6)+SUMIFS('Forecast Data'!H:H,'Forecast Data'!B:B,D11,'Forecast Data'!C:C,BN$6)+SUMIFS('Forecast Data'!H:H,'Forecast Data'!B:B,D11,'Forecast Data'!C:C,BO$6)+SUMIFS('Forecast Data'!H:H,'Forecast Data'!B:B,D11,'Forecast Data'!C:C,BP$6)+SUMIFS('Forecast Data'!H:H,'Forecast Data'!B:B,D11,'Forecast Data'!C:C,BQ$6)+SUMIFS('Forecast Data'!H:H,'Forecast Data'!B:B,D11,'Forecast Data'!C:C,BJ$6))/8 -> 16167 | BX11: =IFERROR((SUM(W11:AD11)-(SUMIFS('Forecast Data'!H:H,'Forecast Data'!B:B,B11,'Forecast Data'!C:C,BJ$6)+SUMIFS('Forecast Data'!H:H,'Forecast Data'!B:B,B11,'Forecast Data'!C:C,BK$6)+SUMIFS('Forecast Data'!H:H,'Forecast Data'!B:B,B11,'Forecast Data'!C:C,BL$6)+SUMIFS('Forecast Data'!H:H,'Forecast Data'!B:B,B11,'Forecast Data'!C:C,BM$6)+SUMIFS('Forecast Data'!H:H,'Forecast Data'!B:B,B11,'Forecast Data'!C:C,BN$6)+SUMIFS('Forecast Data'!H:H,'Forecast Data'!B:B,B11,'Forecast Data'!C:C,BO$6)+SUMIFS('Forecast Data'!H:H,'Forecast Data'!B:B,B11,'Forecast Data'!C:C,BP$6)+SUMIFS('Forecast Data'!H:H,'Forecast Data'!B:B,B11,'Forecast Data'!C:C,BQ$6)))/(SUMIFS('Forecast Data'!H:H,'Forecast Data'!B:B,B11,'Forecast Data'!C:C,BJ$6)+SUMIFS('Forecast Data'!H:H,'Forecast Data'!B:B,B11,'Forecast Data'!C:C,BK$6)+SUMIFS('Forecast Data'!H:H,'Forecast Data'!B:B,B11,'Forecast Data'!C:C,BL$6)+SUMIFS('Forecast Data'!H:H,'Forecast Data'!B:B,B11,'Forecast Data'!C:C,BM$6)+SUMIFS('Forecast Data'!H:H,'Forecast Data'!B:B,B11,'Forecast Data'!C:C,BN$6)+SUMIFS('Forecast Data'!H:H,'Forecast Data'!B:B,B11,'Forecast Data'!C:C,BO$6)+SUMIFS('Forecast Data'!H:H,'Forecast Data'!B:B,B11,'Forecast Data'!C:C,BP$6)+SUMIFS('Forecast Data'!H:H,'Forecast Data'!B:B,B11,'Forecast Data'!C:C,BQ$6)),"") -> 0.37412631 | BY11: =((L11-E11)/($L$4-$E$4))*$M$4 -> 0.0018825942 | BZ11: =((AVERAGE(W11:AD11)-BW11)/(AVERAGE($W$4:$AD$4)-$BW$4))*$BX$4 -> 0.0049736756 | CA11: =(BY11-BZ11)*100 -> -0.30910815 | CB11: =ABS(CA11)/100 -> 0.0030910815 | CD11: =(SUMIFS('Forecast Data'!H:H,'Forecast Data'!B:B,D11,'Forecast Data'!C:C,BK$6)+SUMIFS('Forecast Data'!H:H,'Forecast Data'!B:B,D11,'Forecast Data'!C:C,BL$6)+SUMIFS('Forecast Data'!H:H,'Forecast Data'!B:B,D11,'Forecast Data'!C:C,BM$6)+SUMIFS('Forecast Data'!H:H,'Forecast Data'!B:B,D11,'Forecast Data'!C:C,BJ$6))/4 -> 16326 | CE11: =IFERROR((SUM(W11:Z11)-(SUMIFS('Forecast Data'!H:H,'Forecast Data'!B:B,D11,'Forecast Data'!C:C,BJ$6)+SUMIFS('Forecast Data'!H:H,'Forecast Data'!B:B,D11,'Forecast Data'!C:C,BK$6)+SUMIFS('Forecast Data'!H:H,'Forecast Data'!B:B,D11,'Forecast Data'!C:C,BL$6)+SUMIFS('Forecast Data'!H:H,'Forecast Data'!B:B,D11,'Forecast Data'!C:C,BM$6)))/(SUMIFS('Forecast Data'!H:H,'Forecast Data'!B:B,D11,'Forecast Data'!C:C,BJ$6)+SUMIFS('Forecast Data'!H:H,'Forecast Data'!B:B,D11,'Forecast Data'!C:C,BK$6)+SUMIFS('Forecast Data'!H:H,'Forecast Data'!B:B,D11,'Forecast Data'!C:C,BL$6)+SUMIFS('Forecast Data'!H:H,'Forecast Data'!B:B,D11,'Forecast Data'!C:C,BM$6)),"") -> 0.43631324 | CF11: =(($L11-$E11)/($L$4-$E$4))*$M$4 -> 0.0018825942 | CG11: =((AVERAGE(W11:Z11)-CD11)/(AVERAGE($W$4:$Z$4)-$CD$4))*$CE$4 -> 0.0059720315 | CH11: =(CF11-CG11)*100 -> -0.40894374
B12: =D12 -> Healthy Origins | D12: Healthy Origins | E12: =SUMIFS('Fin Data'!F:F,'Fin Data'!A:A,D12) -> 3703 | F12: =SUMIFS('Fin Data with 6 week hist'!I:I,'Fin Data with 6 week hist'!$A:$A,$D12) -> 7 | G12: =SUMIFS('Fin Data with 6 week hist'!J:J,'Fin Data with 6 week hist'!$A:$A,$D12) -> 4 | H12: =SUMIFS('Fin Data with 6 week hist'!K:K,'Fin Data with 6 week hist'!$A:$A,$D12)+SUMIFS('Unit Cancellations'!D:D,'Unit Cancellations'!$B:$B,$D12) -> 7 | I12: =SUMIFS('Fin Data with 6 week hist'!L:L,'Fin Data with 6 week hist'!$A:$A,$D12)+SUMIFS('Unit Cancellations'!E:E,'Unit Cancellations'!$B:$B,$D12) -> 3 | J12: =SUMIFS('Fin Data with 6 week hist'!M:M,'Fin Data with 6 week hist'!$A:$A,$D12)+SUMIFS('Unit Cancellations'!F:F,'Unit Cancellations'!$B:$B,$D12) -> 1 | K12: =SUMIFS('Fin Data with 6 week hist'!N:N,'Fin Data with 6 week hist'!$A:$A,$D12)+SUMIFS('Unit Cancellations'!G:G,'Unit Cancellations'!$B:$B,$D12) -> 1 | L12: =SUMIFS('Fin Data'!AN:AN,'Fin Data'!A:A,D12) -> 4 | M12: =IFERROR(SUMIFS('Fin Data'!AO:AO,'Fin Data'!A:A,D12),"") -> -0.99891979 | O12: =AVERAGE(W12:Z12) -> 38 | P12: =CE12 -> -0.87085811 | R12: =AVERAGE(W12:AD12) -> 38 | S12: =BX12 -> -0.76917236 | T12: =AVERAGE(AW12:BD12) -> 0 | U12: =#REF! -> #REF! | W12: =SUMIFS('Forecast Data'!$D:$D,'Forecast Data'!$C:$C,W$6,'Forecast Data'!$B:$B,$D12) -> 38 | X12: =SUMIFS('Forecast Data'!$D:$D,'Forecast Data'!$C:$C,X$6,'Forecast Data'!$B:$B,$D12) -> 38 | Y12: =SUMIFS('Forecast Data'!$D:$D,'Forecast Data'!$C:$C,Y$6,'Forecast Data'!$B:$B,$D12) -> 38 | Z12: =SUMIFS('Forecast Data'!$D:$D,'Forecast Data'!$C:$C,Z$6,'Forecast Data'!$B:$B,$D12) -> 38 | AA12: =SUMIFS('Forecast Data'!$D:$D,'Forecast Data'!$C:$C,AA$6,'Forecast Data'!$B:$B,$D12) -> 38 | AB12: =SUMIFS('Forecast Data'!$D:$D,'Forecast Data'!$C:$C,AB$6,'Forecast Data'!$B:$B,$D12) -> 38 | AC12: =SUMIFS('Forecast Data'!$D:$D,'Forecast Data'!$C:$C,AC$6,'Forecast Data'!$B:$B,$D12) -> 38 | AD12: =SUMIFS('Forecast Data'!$D:$D,'Forecast Data'!$C:$C,AD$6,'Forecast Data'!$B:$B,$D12) -> 38 | ... AH12: =SUMIFS('Forecast Data'!$D:$D,'Forecast Data'!$C:$C,AH$6,'Forecast Data'!$B:$B,$D12) -> 38 | AJ12: =IF(SUMIFS('Forecast Data'!$E:$E,'Forecast Data'!$C:$C,AJ$6,'Forecast Data'!$B:$B,$D12)=0,"",SUMIFS('Forecast Data'!$E:$E,'Forecast Data'!$C:$C,AJ$6,'Forecast Data'!$B:$B,$D12)) -> -0.95 | AK12: =IF(SUMIFS('Forecast Data'!$E:$E,'Forecast Data'!$C:$C,AK$6,'Forecast Data'!$B:$B,$D12)=0,"",SUMIFS('Forecast Data'!$E:$E,'Forecast Data'!$C:$C,AK$6,'Forecast Data'!$B:$B,$D12)) -> -0.89 | AL12: =IF(SUMIFS('Forecast Data'!$E:$E,'Forecast Data'!$C:$C,AL$6,'Forecast Data'!$B:$B,$D12)=0,"",SUMIFS('Forecast Data'!$E:$E,'Forecast Data'!$C:$C,AL$6,'Forecast Data'!$B:$B,$D12)) -> -0.37 | AM12: =IF(SUMIFS('Forecast Data'!$E:$E,'Forecast Data'!$C:$C,AM$6,'Forecast Data'!$B:$B,$D12)=0,"",SUMIFS('Forecast Data'!$E:$E,'Forecast Data'!$C:$C,AM$6,'Forecast Data'!$B:$B,$D12)) -> -0.02 | AN12: =IF(SUMIFS('Forecast Data'!$E:$E,'Forecast Data'!$C:$C,AN$6,'Forecast Data'!$B:$B,$D12)=0,"",SUMIFS('Forecast Data'!$E:$E,'Forecast Data'!$C:$C,AN$6,'Forecast Data'!$B:$B,$D12)) -> 0.09 | AO12: =IF(SUMIFS('Forecast Data'!$E:$E,'Forecast Data'!$C:$C,AO$6,'Forecast Data'!$B:$B,$D12)=0,"",SUMIFS('Forecast Data'!$E:$E,'Forecast Data'!$C:$C,AO$6,'Forecast Data'!$B:$B,$D12)) -> 0.03 | AP12: =IF(SUMIFS('Forecast Data'!$E:$E,'Forecast Data'!$C:$C,AP$6,'Forecast Data'!$B:$B,$D12)=0,"",SUMIFS('Forecast Data'!$E:$E,'Forecast Data'!$C:$C,AP$6,'Forecast Data'!$B:$B,$D12)) | AQ12: =IF(SUMIFS('Forecast Data'!$E:$E,'Forecast Data'!$C:$C,AQ$6,'Forecast Data'!$B:$B,$D12)=0,"",SUMIFS('Forecast Data'!$E:$E,'Forecast Data'!$C:$C,AQ$6,'Forecast Data'!$B:$B,$D12)) -> 0.27 | ... AU12: =IF(SUMIFS('Forecast Data'!$E:$E,'Forecast Data'!$C:$C,AU$6,'Forecast Data'!$B:$B,$D12)=0,"",SUMIFS('Forecast Data'!$E:$E,'Forecast Data'!$C:$C,AU$6,'Forecast Data'!$B:$B,$D12)) -> 0.03 | AW12: =SUMIFS('OP Units'!E:E,'OP Units'!$A:$A,$D12) -> 0 | AX12: =SUMIFS('OP Units'!F:F,'OP Units'!$A:$A,$D12) -> 0 | AY12: =SUMIFS('OP Units'!G:G,'OP Units'!$A:$A,$D12) -> 0 | AZ12: =SUMIFS('OP Units'!H:H,'OP Units'!$A:$A,$D12) -> 0 | BA12: =SUMIFS('OP Units'!I:I,'OP Units'!$A:$A,$D12) -> 0 | BB12: =SUMIFS('OP Units'!J:J,'OP Units'!$A:$A,$D12) -> 0 | BC12: =SUMIFS('OP Units'!K:K,'OP Units'!$A:$A,$D12) -> 0 | BD12: =SUMIFS('OP Units'!L:L,'OP Units'!$A:$A,$D12) -> 0 | BE12: =SUMIFS('OP Units'!M:M,'OP Units'!$A:$A,$D12) -> 0 | BF12: =SUMIFS('OP Units'!N:N,'OP Units'!$A:$A,$D12) -> 0 | BG12: =SUMIFS('OP Units'!O:O,'OP Units'!$A:$A,$D12) -> 0 | BH12: =SUMIFS('OP Units'!P:P,'OP Units'!$A:$A,$D12) -> 0 | BJ12: =IFERROR((SUMIFS('OP Units'!E:E,'OP Units'!$A:$A,$D12)-SUMIFS('Forecast Data'!$H:$H,'Forecast Data'!$C:$C,BJ$6,'Forecast Data'!$B:$B,$D12))/SUMIFS('Forecast Data'!$H:$H,'Forecast Data'!$C:$C,BJ$6,'Forecast Data'!$B:$B,$D12),"") -> -1 | BK12: =IFERROR((SUMIFS('OP Units'!F:F,'OP Units'!$A:$A,$D12)-SUMIFS('Forecast Data'!$H:$H,'Forecast Data'!$C:$C,BK$6,'Forecast Data'!$B:$B,$D12))/SUMIFS('Forecast Data'!$H:$H,'Forecast Data'!$C:$C,BK$6,'Forecast Data'!$B:$B,$D12),"") -> -1 | BL12: =IFERROR((SUMIFS('OP Units'!G:G,'OP Units'!$A:$A,$D12)-SUMIFS('Forecast Data'!$H:$H,'Forecast Data'!$C:$C,BL$6,'Forecast Data'!$B:$B,$D12))/SUMIFS('Forecast Data'!$H:$H,'Forecast Data'!$C:$C,BL$6,'Forecast Data'!$B:$B,$D12),"") -> -1 | BM12: =IFERROR((SUMIFS('OP Units'!H:H,'OP Units'!$A:$A,$D12)-SUMIFS('Forecast Data'!$H:$H,'Forecast Data'!$C:$C,BM$6,'Forecast Data'!$B:$B,$D12))/SUMIFS('Forecast Data'!$H:$H,'Forecast Data'!$C:$C,BM$6,'Forecast Data'!$B:$B,$D12),"") -> -1 | BN12: =IFERROR((SUMIFS('OP Units'!I:I,'OP Units'!$A:$A,$D12)-SUMIFS('Forecast Data'!$H:$H,'Forecast Data'!$C:$C,BN$6,'Forecast Data'!$B:$B,$D12))/SUMIFS('Forecast Data'!$H:$H,'Forecast Data'!$C:$C,BN$6,'Forecast Data'!$B:$B,$D12),"") -> -1 | BO12: =IFERROR((SUMIFS('OP Units'!J:J,'OP Units'!$A:$A,$D12)-SUMIFS('Forecast Data'!$H:$H,'Forecast Data'!$C:$C,BO$6,'Forecast Data'!$B:$B,$D12))/SUMIFS('Forecast Data'!$H:$H,'Forecast Data'!$C:$C,BO$6,'Forecast Data'!$B:$B,$D12),"") -> -1 | BP12: =IFERROR((SUMIFS('OP Units'!K:K,'OP Units'!$A:$A,$D12)-SUMIFS('Forecast Data'!$H:$H,'Forecast Data'!$C:$C,BP$6,'Forecast Data'!$B:$B,$D12))/SUMIFS('Forecast Data'!$H:$H,'Forecast Data'!$C:$C,BP$6,'Forecast Data'!$B:$B,$D12),"") -> -1 | BQ12: =IFERROR((SUMIFS('OP Units'!L:L,'OP Units'!$A:$A,$D12)-SUMIFS('Forecast Data'!$H:$H,'Forecast Data'!$C:$C,BQ$6,'Forecast Data'!$B:$B,$D12))/SUMIFS('Forecast Data'!$H:$H,'Forecast Data'!$C:$C,BQ$6,'Forecast Data'!$B:$B,$D12),"") -> -1 | BR12: =IFERROR((SUMIFS('OP Units'!M:M,'OP Units'!$A:$A,$D12)-SUMIFS('Forecast Data'!$H:$H,'Forecast Data'!$C:$C,BR$6,'Forecast Data'!$B:$B,$D12))/SUMIFS('Forecast Data'!$H:$H,'Forecast Data'!$C:$C,BR$6,'Forecast Data'!$B:$B,$D12),"") -> -1 | BS12: =IFERROR((SUMIFS('OP Units'!N:N,'OP Units'!$A:$A,$D12)-SUMIFS('Forecast Data'!$H:$H,'Forecast Data'!$C:$C,BS$6,'Forecast Data'!$B:$B,$D12))/SUMIFS('Forecast Data'!$H:$H,'Forecast Data'!$C:$C,BS$6,'Forecast Data'!$B:$B,$D12),"") -> -1 | BT12: =IFERROR((SUMIFS('OP Units'!O:O,'OP Units'!$A:$A,$D12)-SUMIFS('Forecast Data'!$H:$H,'Forecast Data'!$C:$C,BT$6,'Forecast Data'!$B:$B,$D12))/SUMIFS('Forecast Data'!$H:$H,'Forecast Data'!$C:$C,BT$6,'Forecast Data'!$B:$B,$D12),"") -> -1 | BU12: =IFERROR((SUMIFS('OP Units'!P:P,'OP Units'!$A:$A,$D12)-SUMIFS('Forecast Data'!$H:$H,'Forecast Data'!$C:$C,BU$6,'Forecast Data'!$B:$B,$D12))/SUMIFS('Forecast Data'!$H:$H,'Forecast Data'!$C:$C,BU$6,'Forecast Data'!$B:$B,$D12),"") -> -1 | BW12: =(SUMIFS('Forecast Data'!H:H,'Forecast Data'!B:B,D12,'Forecast Data'!C:C,BK$6)+SUMIFS('Forecast Data'!H:H,'Forecast Data'!B:B,D12,'Forecast Data'!C:C,BL$6)+SUMIFS('Forecast Data'!H:H,'Forecast Data'!B:B,D12,'Forecast Data'!C:C,BM$6)+SUMIFS('Forecast Data'!H:H,'Forecast Data'!B:B,D12,'Forecast Data'!C:C,BN$6)+SUMIFS('Forecast Data'!H:H,'Forecast Data'!B:B,D12,'Forecast Data'!C:C,BO$6)+SUMIFS('Forecast Data'!H:H,'Forecast Data'!B:B,D12,'Forecast Data'!C:C,BP$6)+SUMIFS('Forecast Data'!H:H,'Forecast Data'!B:B,D12,'Forecast Data'!C:C,BQ$6)+SUMIFS('Forecast Data'!H:H,'Forecast Data'!B:B,D12,'Forecast Data'!C:C,BJ$6))/8 -> 164.625 | BX12: =IFERROR((SUM(W12:AD12)-(SUMIFS('Forecast Data'!H:H,'Forecast Data'!B:B,B12,'Forecast Data'!C:C,BJ$6)+SUMIFS('Forecast Data'!H:H,'Forecast Data'!B:B,B12,'Forecast Data'!C:C,BK$6)+SUMIFS('Forecast Data'!H:H,'Forecast Data'!B:B,B12,'Forecast Data'!C:C,BL$6)+SUMIFS('Forecast Data'!H:H,'Forecast Data'!B:B,B12,'Forecast Data'!C:C,BM$6)+SUMIFS('Forecast Data'!H:H,'Forecast Data'!B:B,B12,'Forecast Data'!C:C,BN$6)+SUMIFS('Forecast Data'!H:H,'Forecast Data'!B:B,B12,'Forecast Data'!C:C,BO$6)+SUMIFS('Forecast Data'!H:H,'Forecast Data'!B:B,B12,'Forecast Data'!C:C,BP$6)+SUMIFS('Forecast Data'!H:H,'Forecast Data'!B:B,B12,'Forecast Data'!C:C,BQ$6)))/(SUMIFS('Forecast Data'!H:H,'Forecast Data'!B:B,B12,'Forecast Data'!C:C,BJ$6)+SUMIFS('Forecast Data'!H:H,'Forecast Data'!B:B,B12,'Forecast Data'!C:C,BK$6)+SUMIFS('Forecast Data'!H:H,'Forecast Data'!B:B,B12,'Forecast Data'!C:C,BL$6)+SUMIFS('Forecast Data'!H:H,'Forecast Data'!B:B,B12,'Forecast Data'!C:C,BM$6)+SUMIFS('Forecast Data'!H:H,'Forecast Data'!B:B,B12,'Forecast Data'!C:C,BN$6)+SUMIFS('Forecast Data'!H:H,'Forecast Data'!B:B,B12,'Forecast Data'!C:C,BO$6)+SUMIFS('Forecast Data'!H:H,'Forecast Data'!B:B,B12,'Forecast Data'!C:C,BP$6)+SUMIFS('Forecast Data'!H:H,'Forecast Data'!B:B,B12,'Forecast Data'!C:C,BQ$6)),"") -> -0.76917236 | BY12: =((L12-E12)/($L$4-$E$4))*$M$4 -> -0.0031631687 | BZ12: =((AVERAGE(W12:AD12)-BW12)/(AVERAGE($W$4:$AD$4)-$BW$4))*$BX$4 -> -0.00010412361 | CA12: =(BY12-BZ12)*100 -> -0.30590451 | CB12: =ABS(CA12)/100 -> 0.0030590451 | CD12: =(SUMIFS('Forecast Data'!H:H,'Forecast Data'!B:B,D12,'Forecast Data'!C:C,BK$6)+SUMIFS('Forecast Data'!H:H,'Forecast Data'!B:B,D12,'Forecast Data'!C:C,BL$6)+SUMIFS('Forecast Data'!H:H,'Forecast Data'!B:B,D12,'Forecast Data'!C:C,BM$6)+SUMIFS('Forecast Data'!H:H,'Forecast Data'!B:B,D12,'Forecast Data'!C:C,BJ$6))/4 -> 294.25 | CE12: =IFERROR((SUM(W12:Z12)-(SUMIFS('Forecast Data'!H:H,'Forecast Data'!B:B,D12,'Forecast Data'!C:C,BJ$6)+SUMIFS('Forecast Data'!H:H,'Forecast Data'!B:B,D12,'Forecast Data'!C:C,BK$6)+SUMIFS('Forecast Data'!H:H,'Forecast Data'!B:B,D12,'Forecast Data'!C:C,BL$6)+SUMIFS('Forecast Data'!H:H,'Forecast Data'!B:B,D12,'Forecast Data'!C:C,BM$6)))/(SUMIFS('Forecast Data'!H:H,'Forecast Data'!B:B,D12,'Forecast Data'!C:C,BJ$6)+SUMIFS('Forecast Data'!H:H,'Forecast Data'!B:B,D12,'Forecast Data'!C:C,BK$6)+SUMIFS('Forecast Data'!H:H,'Forecast Data'!B:B,D12,'Forecast Data'!C:C,BL$6)+SUMIFS('Forecast Data'!H:H,'Forecast Data'!B:B,D12,'Forecast Data'!C:C,BM$6)),"") -> -0.87085811 | CF12: =(($L12-$E12)/($L$4-$E$4))*$M$4 -> -0.0031631687 | CG12: =((AVERAGE(W12:Z12)-CD12)/(AVERAGE($W$4:$Z$4)-$CD$4))*$CE$4 -> -0.00021483636 | CH12: =(CF12-CG12)*100 -> -0.29483324
B13: =D13 -> NatureBell | C13: New | D13: NatureBell | E13: =SUMIFS('Fin Data'!F:F,'Fin Data'!A:A,D13) -> 0 | F13: =SUMIFS('Fin Data with 6 week hist'!I:I,'Fin Data with 6 week hist'!$A:$A,$D13) -> 11130 | G13: =SUMIFS('Fin Data with 6 week hist'!J:J,'Fin Data with 6 week hist'!$A:$A,$D13) -> 11034 | H13: =SUMIFS('Fin Data with 6 week hist'!K:K,'Fin Data with 6 week hist'!$A:$A,$D13)+SUMIFS('Unit Cancellations'!D:D,'Unit Cancellations'!$B:$B,$D13) -> 11737 | I13: =SUMIFS('Fin Data with 6 week hist'!L:L,'Fin Data with 6 week hist'!$A:$A,$D13)+SUMIFS('Unit Cancellations'!E:E,'Unit Cancellations'!$B:$B,$D13) -> 11257 | J13: =SUMIFS('Fin Data with 6 week hist'!M:M,'Fin Data with 6 week hist'!$A:$A,$D13)+SUMIFS('Unit Cancellations'!F:F,'Unit Cancellations'!$B:$B,$D13) -> 12597 | K13: =SUMIFS('Fin Data with 6 week hist'!N:N,'Fin Data with 6 week hist'!$A:$A,$D13)+SUMIFS('Unit Cancellations'!G:G,'Unit Cancellations'!$B:$B,$D13) -> 18838 | L13: =SUMIFS('Fin Data'!AN:AN,'Fin Data'!A:A,D13) -> 12766 | M13: =IFERROR(SUMIFS('Fin Data'!AO:AO,'Fin Data'!A:A,D13),"") -> 0 | O13: =AVERAGE(W13:Z13) -> 15408.75 | P13: =CE13 | R13: =AVERAGE(W13:AD13) -> 16928.875 | S13: =BX13 | T13: =AVERAGE(AW13:BD13) -> 3514.75 | U13: =#REF! -> #REF! | W13: =SUMIFS('Forecast Data'!$D:$D,'Forecast Data'!$C:$C,W$6,'Forecast Data'!$B:$B,$D13) -> 15430 | X13: =SUMIFS('Forecast Data'!$D:$D,'Forecast Data'!$C:$C,X$6,'Forecast Data'!$B:$B,$D13) -> 15426 | Y13: =SUMIFS('Forecast Data'!$D:$D,'Forecast Data'!$C:$C,Y$6,'Forecast Data'!$B:$B,$D13) -> 15351 | Z13: =SUMIFS('Forecast Data'!$D:$D,'Forecast Data'!$C:$C,Z$6,'Forecast Data'!$B:$B,$D13) -> 15428 | AA13: =SUMIFS('Forecast Data'!$D:$D,'Forecast Data'!$C:$C,AA$6,'Forecast Data'!$B:$B,$D13) -> 15462 | AB13: =SUMIFS('Forecast Data'!$D:$D,'Forecast Data'!$C:$C,AB$6,'Forecast Data'!$B:$B,$D13) -> 20675 | AC13: =SUMIFS('Forecast Data'!$D:$D,'Forecast Data'!$C:$C,AC$6,'Forecast Data'!$B:$B,$D13) -> 21468 | AD13: =SUMIFS('Forecast Data'!$D:$D,'Forecast Data'!$C:$C,AD$6,'Forecast Data'!$B:$B,$D13) -> 16191 | ... AH13: =SUMIFS('Forecast Data'!$D:$D,'Forecast Data'!$C:$C,AH$6,'Forecast Data'!$B:$B,$D13) -> 15320 | AJ13: =IF(SUMIFS('Forecast Data'!$E:$E,'Forecast Data'!$C:$C,AJ$6,'Forecast Data'!$B:$B,$D13)=0,"",SUMIFS('Forecast Data'!$E:$E,'Forecast Data'!$C:$C,AJ$6,'Forecast Data'!$B:$B,$D13)) | AK13: =IF(SUMIFS('Forecast Data'!$E:$E,'Forecast Data'!$C:$C,AK$6,'Forecast Data'!$B:$B,$D13)=0,"",SUMIFS('Forecast Data'!$E:$E,'Forecast Data'!$C:$C,AK$6,'Forecast Data'!$B:$B,$D13)) | AL13: =IF(SUMIFS('Forecast Data'!$E:$E,'Forecast Data'!$C:$C,AL$6,'Forecast Data'!$B:$B,$D13)=0,"",SUMIFS('Forecast Data'!$E:$E,'Forecast Data'!$C:$C,AL$6,'Forecast Data'!$B:$B,$D13)) | AM13: =IF(SUMIFS('Forecast Data'!$E:$E,'Forecast Data'!$C:$C,AM$6,'Forecast Data'!$B:$B,$D13)=0,"",SUMIFS('Forecast Data'!$E:$E,'Forecast Data'!$C:$C,AM$6,'Forecast Data'!$B:$B,$D13)) | AN13: =IF(SUMIFS('Forecast Data'!$E:$E,'Forecast Data'!$C:$C,AN$6,'Forecast Data'!$B:$B,$D13)=0,"",SUMIFS('Forecast Data'!$E:$E,'Forecast Data'!$C:$C,AN$6,'Forecast Data'!$B:$B,$D13)) | AO13: =IF(SUMIFS('Forecast Data'!$E:$E,'Forecast Data'!$C:$C,AO$6,'Forecast Data'!$B:$B,$D13)=0,"",SUMIFS('Forecast Data'!$E:$E,'Forecast Data'!$C:$C,AO$6,'Forecast Data'!$B:$B,$D13)) | AP13: =IF(SUMIFS('Forecast Data'!$E:$E,'Forecast Data'!$C:$C,AP$6,'Forecast Data'!$B:$B,$D13)=0,"",SUMIFS('Forecast Data'!$E:$E,'Forecast Data'!$C:$C,AP$6,'Forecast Data'!$B:$B,$D13)) | AQ13: =IF(SUMIFS('Forecast Data'!$E:$E,'Forecast Data'!$C:$C,AQ$6,'Forecast Data'!$B:$B,$D13)=0,"",SUMIFS('Forecast Data'!$E:$E,'Forecast Data'!$C:$C,AQ$6,'Forecast Data'!$B:$B,$D13)) | ... AU13: =IF(SUMIFS('Forecast Data'!$E:$E,'Forecast Data'!$C:$C,AU$6,'Forecast Data'!$B:$B,$D13)=0,"",SUMIFS('Forecast Data'!$E:$E,'Forecast Data'!$C:$C,AU$6,'Forecast Data'!$B:$B,$D13)) | AW13: =SUMIFS('OP Units'!E:E,'OP Units'!$A:$A,$D13) -> 2495 | AX13: =SUMIFS('OP Units'!F:F,'OP Units'!$A:$A,$D13) -> 2627 | AY13: =SUMIFS('OP Units'!G:G,'OP Units'!$A:$A,$D13) -> 3521 | AZ13: =SUMIFS('OP Units'!H:H,'OP Units'!$A:$A,$D13) -> 3682 | BA13: =SUMIFS('OP Units'!I:I,'OP Units'!$A:$A,$D13) -> 3739 | BB13: =SUMIFS('OP Units'!J:J,'OP Units'!$A:$A,$D13) -> 3975 | BC13: =SUMIFS('OP Units'!K:K,'OP Units'!$A:$A,$D13) -> 4083 | BD13: =SUMIFS('OP Units'!L:L,'OP Units'!$A:$A,$D13) -> 3996 | BE13: =SUMIFS('OP Units'!M:M,'OP Units'!$A:$A,$D13) -> 4044 | BF13: =SUMIFS('OP Units'!N:N,'OP Units'!$A:$A,$D13) -> 4304 | BG13: =SUMIFS('OP Units'!O:O,'OP Units'!$A:$A,$D13) -> 4506 | BH13: =SUMIFS('OP Units'!P:P,'OP Units'!$A:$A,$D13) -> 4595 | BJ13: =IFERROR((SUMIFS('OP Units'!E:E,'OP Units'!$A:$A,$D13)-SUMIFS('Forecast Data'!$H:$H,'Forecast Data'!$C:$C,BJ$6,'Forecast Data'!$B:$B,$D13))/SUMIFS('Forecast Data'!$H:$H,'Forecast Data'!$C:$C,BJ$6,'Forecast Data'!$B:$B,$D13),"") | BK13: =IFERROR((SUMIFS('OP Units'!F:F,'OP Units'!$A:$A,$D13)-SUMIFS('Forecast Data'!$H:$H,'Forecast Data'!$C:$C,BK$6,'Forecast Data'!$B:$B,$D13))/SUMIFS('Forecast Data'!$H:$H,'Forecast Data'!$C:$C,BK$6,'Forecast Data'!$B:$B,$D13),"") | BL13: =IFERROR((SUMIFS('OP Units'!G:G,'OP Units'!$A:$A,$D13)-SUMIFS('Forecast Data'!$H:$H,'Forecast Data'!$C:$C,BL$6,'Forecast Data'!$B:$B,$D13))/SUMIFS('Forecast Data'!$H:$H,'Forecast Data'!$C:$C,BL$6,'Forecast Data'!$B:$B,$D13),"") | BM13: =IFERROR((SUMIFS('OP Units'!H:H,'OP Units'!$A:$A,$D13)-SUMIFS('Forecast Data'!$H:$H,'Forecast Data'!$C:$C,BM$6,'Forecast Data'!$B:$B,$D13))/SUMIFS('Forecast Data'!$H:$H,'Forecast Data'!$C:$C,BM$6,'Forecast Data'!$B:$B,$D13),"") | BN13: =IFERROR((SUMIFS('OP Units'!I:I,'OP Units'!$A:$A,$D13)-SUMIFS('Forecast Data'!$H:$H,'Forecast Data'!$C:$C,BN$6,'Forecast Data'!$B:$B,$D13))/SUMIFS('Forecast Data'!$H:$H,'Forecast Data'!$C:$C,BN$6,'Forecast Data'!$B:$B,$D13),"") | BO13: =IFERROR((SUMIFS('OP Units'!J:J,'OP Units'!$A:$A,$D13)-SUMIFS('Forecast Data'!$H:$H,'Forecast Data'!$C:$C,BO$6,'Forecast Data'!$B:$B,$D13))/SUMIFS('Forecast Data'!$H:$H,'Forecast Data'!$C:$C,BO$6,'Forecast Data'!$B:$B,$D13),"") | BP13: =IFERROR((SUMIFS('OP Units'!K:K,'OP Units'!$A:$A,$D13)-SUMIFS('Forecast Data'!$H:$H,'Forecast Data'!$C:$C,BP$6,'Forecast Data'!$B:$B,$D13))/SUMIFS('Forecast Data'!$H:$H,'Forecast Data'!$C:$C,BP$6,'Forecast Data'!$B:$B,$D13),"") | BQ13: =IFERROR((SUMIFS('OP Units'!L:L,'OP Units'!$A:$A,$D13)-SUMIFS('Forecast Data'!$H:$H,'Forecast Data'!$C:$C,BQ$6,'Forecast Data'!$B:$B,$D13))/SUMIFS('Forecast Data'!$H:$H,'Forecast Data'!$C:$C,BQ$6,'Forecast Data'!$B:$B,$D13),"") | BR13: =IFERROR((SUMIFS('OP Units'!M:M,'OP Units'!$A:$A,$D13)-SUMIFS('Forecast Data'!$H:$H,'Forecast Data'!$C:$C,BR$6,'Forecast Data'!$B:$B,$D13))/SUMIFS('Forecast Data'!$H:$H,'Forecast Data'!$C:$C,BR$6,'Forecast Data'!$B:$B,$D13),"") | BS13: =IFERROR((SUMIFS('OP Units'!N:N,'OP Units'!$A:$A,$D13)-SUMIFS('Forecast Data'!$H:$H,'Forecast Data'!$C:$C,BS$6,'Forecast Data'!$B:$B,$D13))/SUMIFS('Forecast Data'!$H:$H,'Forecast Data'!$C:$C,BS$6,'Forecast Data'!$B:$B,$D13),"") | BT13: =IFERROR((SUMIFS('OP Units'!O:O,'OP Units'!$A:$A,$D13)-SUMIFS('Forecast Data'!$H:$H,'Forecast Data'!$C:$C,BT$6,'Forecast Data'!$B:$B,$D13))/SUMIFS('Forecast Data'!$H:$H,'Forecast Data'!$C:$C,BT$6,'Forecast Data'!$B:$B,$D13),"") | BU13: =IFERROR((SUMIFS('OP Units'!P:P,'OP Units'!$A:$A,$D13)-SUMIFS('Forecast Data'!$H:$H,'Forecast Data'!$C:$C,BU$6,'Forecast Data'!$B:$B,$D13))/SUMIFS('Forecast Data'!$H:$H,'Forecast Data'!$C:$C,BU$6,'Forecast Data'!$B:$B,$D13),"") | BW13: =(SUMIFS('Forecast Data'!H:H,'Forecast Data'!B:B,D13,'Forecast Data'!C:C,BK$6)+SUMIFS('Forecast Data'!H:H,'Forecast Data'!B:B,D13,'Forecast Data'!C:C,BL$6)+SUMIFS('Forecast Data'!H:H,'Forecast Data'!B:B,D13,'Forecast Data'!C:C,BM$6)+SUMIFS('Forecast Data'!H:H,'Forecast Data'!B:B,D13,'Forecast Data'!C:C,BN$6)+SUMIFS('Forecast Data'!H:H,'Forecast Data'!B:B,D13,'Forecast Data'!C:C,BO$6)+SUMIFS('Forecast Data'!H:H,'Forecast Data'!B:B,D13,'Forecast Data'!C:C,BP$6)+SUMIFS('Forecast Data'!H:H,'Forecast Data'!B:B,D13,'Forecast Data'!C:C,BQ$6)+SUMIFS('Forecast Data'!H:H,'Forecast Data'!B:B,D13,'Forecast Data'!C:C,BJ$6))/8 -> 0 | BX13: =IFERROR((SUM(W13:AD13)-(SUMIFS('Forecast Data'!H:H,'Forecast Data'!B:B,B13,'Forecast Data'!C:C,BJ$6)+SUMIFS('Forecast Data'!H:H,'Forecast Data'!B:B,B13,'Forecast Data'!C:C,BK$6)+SUMIFS('Forecast Data'!H:H,'Forecast Data'!B:B,B13,'Forecast Data'!C:C,BL$6)+SUMIFS('Forecast Data'!H:H,'Forecast Data'!B:B,B13,'Forecast Data'!C:C,BM$6)+SUMIFS('Forecast Data'!H:H,'Forecast Data'!B:B,B13,'Forecast Data'!C:C,BN$6)+SUMIFS('Forecast Data'!H:H,'Forecast Data'!B:B,B13,'Forecast Data'!C:C,BO$6)+SUMIFS('Forecast Data'!H:H,'Forecast Data'!B:B,B13,'Forecast Data'!C:C,BP$6)+SUMIFS('Forecast Data'!H:H,'Forecast Data'!B:B,B13,'Forecast Data'!C:C,BQ$6)))/(SUMIFS('Forecast Data'!H:H,'Forecast Data'!B:B,B13,'Forecast Data'!C:C,BJ$6)+SUMIFS('Forecast Data'!H:H,'Forecast Data'!B:B,B13,'Forecast Data'!C:C,BK$6)+SUMIFS('Forecast Data'!H:H,'Forecast Data'!B:B,B13,'Forecast Data'!C:C,BL$6)+SUMIFS('Forecast Data'!H:H,'Forecast Data'!B:B,B13,'Forecast Data'!C:C,BM$6)+SUMIFS('Forecast Data'!H:H,'Forecast Data'!B:B,B13,'Forecast Data'!C:C,BN$6)+SUMIFS('Forecast Data'!H:H,'Forecast Data'!B:B,B13,'Forecast Data'!C:C,BO$6)+SUMIFS('Forecast Data'!H:H,'Forecast Data'!B:B,B13,'Forecast Data'!C:C,BP$6)+SUMIFS('Forecast Data'!H:H,'Forecast Data'!B:B,B13,'Forecast Data'!C:C,BQ$6)),"") | BY13: =((L13-E13)/($L$4-$E$4))*$M$4 -> 0.010916737 | BZ13: =((AVERAGE(W13:AD13)-BW13)/(AVERAGE($W$4:$AD$4)-$BW$4))*$BX$4 -> 0.013920597 | CA13: =(BY13-BZ13)*100 -> -0.300386 | CB13: =ABS(CA13)/100 -> 0.00300386 | CD13: =(SUMIFS('Forecast Data'!H:H,'Forecast Data'!B:B,D13,'Forecast Data'!C:C,BK$6)+SUMIFS('Forecast Data'!H:H,'Forecast Data'!B:B,D13,'Forecast Data'!C:C,BL$6)+SUMIFS('Forecast Data'!H:H,'Forecast Data'!B:B,D13,'Forecast Data'!C:C,BM$6)+SUMIFS('Forecast Data'!H:H,'Forecast Data'!B:B,D13,'Forecast Data'!C:C,BJ$6))/4 -> 0 | CE13: =IFERROR((SUM(W13:Z13)-(SUMIFS('Forecast Data'!H:H,'Forecast Data'!B:B,B13,'Forecast Data'!C:C,BJ$6)+SUMIFS('Forecast Data'!H:H,'Forecast Data'!B:B,B13,'Forecast Data'!C:C,BK$6)+SUMIFS('Forecast Data'!H:H,'Forecast Data'!B:B,B13,'Forecast Data'!C:C,BL$6)+SUMIFS('Forecast Data'!H:H,'Forecast Data'!B:B,B13,'Forecast Data'!C:C,BM$6)))/(SUMIFS('Forecast Data'!H:H,'Forecast Data'!B:B,B13,'Forecast Data'!C:C,BJ$6)+SUMIFS('Forecast Data'!H:H,'Forecast Data'!B:B,B13,'Forecast Data'!C:C,BK$6)+SUMIFS('Forecast Data'!H:H,'Forecast Data'!B:B,B13,'Forecast Data'!C:C,BL$6)+SUMIFS('Forecast Data'!H:H,'Forecast Data'!B:B,B13,'Forecast Data'!C:C,BM$6)),"") | CF13: =(($L13-$E13)/($L$4-$E$4))*$M$4 -> 0.010916737 | CG13: =((AVERAGE(W13:Z13)-CD13)/(AVERAGE($W$4:$Z$4)-$CD$4))*$CE$4 -> 0.012918477 | CH13: =(CF13-CG13)*100 -> -0.20017395
B14: =D14 -> Atrium - Pure Encapsulations | D14: Atrium - Pure Encapsulations | E14: =SUMIFS('Fin Data'!F:F,'Fin Data'!A:A,D14) -> 232818 | F14: =SUMIFS('Fin Data with 6 week hist'!I:I,'Fin Data with 6 week hist'!$A:$A,$D14) -> 312228 | G14: =SUMIFS('Fin Data with 6 week hist'!J:J,'Fin Data with 6 week hist'!$A:$A,$D14) -> 315311 | H14: =SUMIFS('Fin Data with 6 week hist'!K:K,'Fin Data with 6 week hist'!$A:$A,$D14)+SUMIFS('Unit Cancellations'!D:D,'Unit Cancellations'!$B:$B,$D14) -> 316006 | I14: =SUMIFS('Fin Data with 6 week hist'!L:L,'Fin Data with 6 week hist'!$A:$A,$D14)+SUMIFS('Unit Cancellations'!E:E,'Unit Cancellations'!$B:$B,$D14) -> 315744 | J14: =SUMIFS('Fin Data with 6 week hist'!M:M,'Fin Data with 6 week hist'!$A:$A,$D14)+SUMIFS('Unit Cancellations'!F:F,'Unit Cancellations'!$B:$B,$D14) -> 318979 | K14: =SUMIFS('Fin Data with 6 week hist'!N:N,'Fin Data with 6 week hist'!$A:$A,$D14)+SUMIFS('Unit Cancellations'!G:G,'Unit Cancellations'!$B:$B,$D14) -> 322143 | L14: =SUMIFS('Fin Data'!AN:AN,'Fin Data'!A:A,D14) -> 316735.17 | M14: =IFERROR(SUMIFS('Fin Data'!AO:AO,'Fin Data'!A:A,D14),"") -> 0.36044106 | O14: =AVERAGE(W14:Z14) -> 327414.25 | P14: =CE14 -> 0.37585199 | R14: =AVERAGE(W14:AD14) -> 328940.62 | S14: =BX14 -> 0.35559392 | T14: =AVERAGE(AW14:BD14) -> 304988.12 | U14: =#REF! -> #REF! | W14: =SUMIFS('Forecast Data'!$D:$D,'Forecast Data'!$C:$C,W$6,'Forecast Data'!$B:$B,$D14) -> 322116 | X14: =SUMIFS('Forecast Data'!$D:$D,'Forecast Data'!$C:$C,X$6,'Forecast Data'!$B:$B,$D14) -> 322109 | Y14: =SUMIFS('Forecast Data'!$D:$D,'Forecast Data'!$C:$C,Y$6,'Forecast Data'!$B:$B,$D14) -> 331903 | Z14: =SUMIFS('Forecast Data'!$D:$D,'Forecast Data'!$C:$C,Z$6,'Forecast Data'!$B:$B,$D14) -> 333529 | AA14: =SUMIFS('Forecast Data'!$D:$D,'Forecast Data'!$C:$C,AA$6,'Forecast Data'!$B:$B,$D14) -> 333507 | AB14: =SUMIFS('Forecast Data'!$D:$D,'Forecast Data'!$C:$C,AB$6,'Forecast Data'!$B:$B,$D14) -> 333503 | AC14: =SUMIFS('Forecast Data'!$D:$D,'Forecast Data'!$C:$C,AC$6,'Forecast Data'!$B:$B,$D14) -> 327896 | AD14: =SUMIFS('Forecast Data'!$D:$D,'Forecast Data'!$C:$C,AD$6,'Forecast Data'!$B:$B,$D14) -> 326962 | ... AH14: =SUMIFS('Forecast Data'!$D:$D,'Forecast Data'!$C:$C,AH$6,'Forecast Data'!$B:$B,$D14) -> 322145 | AJ14: =IF(SUMIFS('Forecast Data'!$E:$E,'Forecast Data'!$C:$C,AJ$6,'Forecast Data'!$B:$B,$D14)=0,"",SUMIFS('Forecast Data'!$E:$E,'Forecast Data'!$C:$C,AJ$6,'Forecast Data'!$B:$B,$D14)) -> 0.37 | AK14: =IF(SUMIFS('Forecast Data'!$E:$E,'Forecast Data'!$C:$C,AK$6,'Forecast Data'!$B:$B,$D14)=0,"",SUMIFS('Forecast Data'!$E:$E,'Forecast Data'!$C:$C,AK$6,'Forecast Data'!$B:$B,$D14)) -> 0.35 | AL14: =IF(SUMIFS('Forecast Data'!$E:$E,'Forecast Data'!$C:$C,AL$6,'Forecast Data'!$B:$B,$D14)=0,"",SUMIFS('Forecast Data'!$E:$E,'Forecast Data'!$C:$C,AL$6,'Forecast Data'!$B:$B,$D14)) -> 0.42 | AM14: =IF(SUMIFS('Forecast Data'!$E:$E,'Forecast Data'!$C:$C,AM$6,'Forecast Data'!$B:$B,$D14)=0,"",SUMIFS('Forecast Data'!$E:$E,'Forecast Data'!$C:$C,AM$6,'Forecast Data'!$B:$B,$D14)) -> 0.37 | AN14: =IF(SUMIFS('Forecast Data'!$E:$E,'Forecast Data'!$C:$C,AN$6,'Forecast Data'!$B:$B,$D14)=0,"",SUMIFS('Forecast Data'!$E:$E,'Forecast Data'!$C:$C,AN$6,'Forecast Data'!$B:$B,$D14)) -> 0.34 | AO14: =IF(SUMIFS('Forecast Data'!$E:$E,'Forecast Data'!$C:$C,AO$6,'Forecast Data'!$B:$B,$D14)=0,"",SUMIFS('Forecast Data'!$E:$E,'Forecast Data'!$C:$C,AO$6,'Forecast Data'!$B:$B,$D14)) -> 0.31 | AP14: =IF(SUMIFS('Forecast Data'!$E:$E,'Forecast Data'!$C:$C,AP$6,'Forecast Data'!$B:$B,$D14)=0,"",SUMIFS('Forecast Data'!$E:$E,'Forecast Data'!$C:$C,AP$6,'Forecast Data'!$B:$B,$D14)) -> 0.35 | AQ14: =IF(SUMIFS('Forecast Data'!$E:$E,'Forecast Data'!$C:$C,AQ$6,'Forecast Data'!$B:$B,$D14)=0,"",SUMIFS('Forecast Data'!$E:$E,'Forecast Data'!$C:$C,AQ$6,'Forecast Data'!$B:$B,$D14)) -> 0.34 | ... AU14: =IF(SUMIFS('Forecast Data'!$E:$E,'Forecast Data'!$C:$C,AU$6,'Forecast Data'!$B:$B,$D14)=0,"",SUMIFS('Forecast Data'!$E:$E,'Forecast Data'!$C:$C,AU$6,'Forecast Data'!$B:$B,$D14)) -> 0.32 | AW14: =SUMIFS('OP Units'!E:E,'OP Units'!$A:$A,$D14) -> 294827 | AX14: =SUMIFS('OP Units'!F:F,'OP Units'!$A:$A,$D14) -> 299304 | AY14: =SUMIFS('OP Units'!G:G,'OP Units'!$A:$A,$D14) -> 299586 | AZ14: =SUMIFS('OP Units'!H:H,'OP Units'!$A:$A,$D14) -> 311079 | BA14: =SUMIFS('OP Units'!I:I,'OP Units'!$A:$A,$D14) -> 314145 | BB14: =SUMIFS('OP Units'!J:J,'OP Units'!$A:$A,$D14) -> 317527 | BC14: =SUMIFS('OP Units'!K:K,'OP Units'!$A:$A,$D14) -> 306434 | BD14: =SUMIFS('OP Units'!L:L,'OP Units'!$A:$A,$D14) -> 297003 | BE14: =SUMIFS('OP Units'!M:M,'OP Units'!$A:$A,$D14) -> 295268 | BF14: =SUMIFS('OP Units'!N:N,'OP Units'!$A:$A,$D14) -> 300844 | BG14: =SUMIFS('OP Units'!O:O,'OP Units'!$A:$A,$D14) -> 307929 | BH14: =SUMIFS('OP Units'!P:P,'OP Units'!$A:$A,$D14) -> 302283 | BJ14: =IFERROR((SUMIFS('OP Units'!E:E,'OP Units'!$A:$A,$D14)-SUMIFS('Forecast Data'!$H:$H,'Forecast Data'!$C:$C,BJ$6,'Forecast Data'!$B:$B,$D14))/SUMIFS('Forecast Data'!$H:$H,'Forecast Data'!$C:$C,BJ$6,'Forecast Data'!$B:$B,$D14),"") -> 0.25462569 | BK14: =IFERROR((SUMIFS('OP Units'!F:F,'OP Units'!$A:$A,$D14)-SUMIFS('Forecast Data'!$H:$H,'Forecast Data'!$C:$C,BK$6,'Forecast Data'!$B:$B,$D14))/SUMIFS('Forecast Data'!$H:$H,'Forecast Data'!$C:$C,BK$6,'Forecast Data'!$B:$B,$D14),"") -> 0.25062781 | BL14: =IFERROR((SUMIFS('OP Units'!G:G,'OP Units'!$A:$A,$D14)-SUMIFS('Forecast Data'!$H:$H,'Forecast Data'!$C:$C,BL$6,'Forecast Data'!$B:$B,$D14))/SUMIFS('Forecast Data'!$H:$H,'Forecast Data'!$C:$C,BL$6,'Forecast Data'!$B:$B,$D14),"") -> 0.28070895 | BM14: =IFERROR((SUMIFS('OP Units'!H:H,'OP Units'!$A:$A,$D14)-SUMIFS('Forecast Data'!$H:$H,'Forecast Data'!$C:$C,BM$6,'Forecast Data'!$B:$B,$D14))/SUMIFS('Forecast Data'!$H:$H,'Forecast Data'!$C:$C,BM$6,'Forecast Data'!$B:$B,$D14),"") -> 0.27674009 | BN14: =IFERROR((SUMIFS('OP Units'!I:I,'OP Units'!$A:$A,$D14)-SUMIFS('Forecast Data'!$H:$H,'Forecast Data'!$C:$C,BN$6,'Forecast Data'!$B:$B,$D14))/SUMIFS('Forecast Data'!$H:$H,'Forecast Data'!$C:$C,BN$6,'Forecast Data'!$B:$B,$D14),"") -> 0.26318393 | BO14: =IFERROR((SUMIFS('OP Units'!J:J,'OP Units'!$A:$A,$D14)-SUMIFS('Forecast Data'!$H:$H,'Forecast Data'!$C:$C,BO$6,'Forecast Data'!$B:$B,$D14))/SUMIFS('Forecast Data'!$H:$H,'Forecast Data'!$C:$C,BO$6,'Forecast Data'!$B:$B,$D14),"") -> 0.24982091 | BP14: =IFERROR((SUMIFS('OP Units'!K:K,'OP Units'!$A:$A,$D14)-SUMIFS('Forecast Data'!$H:$H,'Forecast Data'!$C:$C,BP$6,'Forecast Data'!$B:$B,$D14))/SUMIFS('Forecast Data'!$H:$H,'Forecast Data'!$C:$C,BP$6,'Forecast Data'!$B:$B,$D14),"") -> 0.26427098 | BQ14: =IFERROR((SUMIFS('OP Units'!L:L,'OP Units'!$A:$A,$D14)-SUMIFS('Forecast Data'!$H:$H,'Forecast Data'!$C:$C,BQ$6,'Forecast Data'!$B:$B,$D14))/SUMIFS('Forecast Data'!$H:$H,'Forecast Data'!$C:$C,BQ$6,'Forecast Data'!$B:$B,$D14),"") -> 0.2161538 | BR14: =IFERROR((SUMIFS('OP Units'!M:M,'OP Units'!$A:$A,$D14)-SUMIFS('Forecast Data'!$H:$H,'Forecast Data'!$C:$C,BR$6,'Forecast Data'!$B:$B,$D14))/SUMIFS('Forecast Data'!$H:$H,'Forecast Data'!$C:$C,BR$6,'Forecast Data'!$B:$B,$D14),"") -> 0.1775159 | BS14: =IFERROR((SUMIFS('OP Units'!N:N,'OP Units'!$A:$A,$D14)-SUMIFS('Forecast Data'!$H:$H,'Forecast Data'!$C:$C,BS$6,'Forecast Data'!$B:$B,$D14))/SUMIFS('Forecast Data'!$H:$H,'Forecast Data'!$C:$C,BS$6,'Forecast Data'!$B:$B,$D14),"") -> 0.19258076 | BT14: =IFERROR((SUMIFS('OP Units'!O:O,'OP Units'!$A:$A,$D14)-SUMIFS('Forecast Data'!$H:$H,'Forecast Data'!$C:$C,BT$6,'Forecast Data'!$B:$B,$D14))/SUMIFS('Forecast Data'!$H:$H,'Forecast Data'!$C:$C,BT$6,'Forecast Data'!$B:$B,$D14),"") -> 0.24356468 | BU14: =IFERROR((SUMIFS('OP Units'!P:P,'OP Units'!$A:$A,$D14)-SUMIFS('Forecast Data'!$H:$H,'Forecast Data'!$C:$C,BU$6,'Forecast Data'!$B:$B,$D14))/SUMIFS('Forecast Data'!$H:$H,'Forecast Data'!$C:$C,BU$6,'Forecast Data'!$B:$B,$D14),"") -> 0.2415004 | BW14: =(SUMIFS('Forecast Data'!H:H,'Forecast Data'!B:B,D14,'Forecast Data'!C:C,BK$6)+SUMIFS('Forecast Data'!H:H,'Forecast Data'!B:B,D14,'Forecast Data'!C:C,BL$6)+SUMIFS('Forecast Data'!H:H,'Forecast Data'!B:B,D14,'Forecast Data'!C:C,BM$6)+SUMIFS('Forecast Data'!H:H,'Forecast Data'!B:B,D14,'Forecast Data'!C:C,BN$6)+SUMIFS('Forecast Data'!H:H,'Forecast Data'!B:B,D14,'Forecast Data'!C:C,BO$6)+SUMIFS('Forecast Data'!H:H,'Forecast Data'!B:B,D14,'Forecast Data'!C:C,BP$6)+SUMIFS('Forecast Data'!H:H,'Forecast Data'!B:B,D14,'Forecast Data'!C:C,BQ$6)+SUMIFS('Forecast Data'!H:H,'Forecast Data'!B:B,D14,'Forecast Data'!C:C,BJ$6))/8 -> 242654.25 | BX14: =IFERROR((SUM(W14:AD14)-(SUMIFS('Forecast Data'!H:H,'Forecast Data'!B:B,B14,'Forecast Data'!C:C,BJ$6)+SUMIFS('Forecast Data'!H:H,'Forecast Data'!B:B,B14,'Forecast Data'!C:C,BK$6)+SUMIFS('Forecast Data'!H:H,'Forecast Data'!B:B,B14,'Forecast Data'!C:C,BL$6)+SUMIFS('Forecast Data'!H:H,'Forecast Data'!B:B,B14,'Forecast Data'!C:C,BM$6)+SUMIFS('Forecast Data'!H:H,'Forecast Data'!B:B,B14,'Forecast Data'!C:C,BN$6)+SUMIFS('Forecast Data'!H:H,'Forecast Data'!B:B,B14,'Forecast Data'!C:C,BO$6)+SUMIFS('Forecast Data'!H:H,'Forecast Data'!B:B,B14,'Forecast Data'!C:C,BP$6)+SUMIFS('Forecast Data'!H:H,'Forecast Data'!B:B,B14,'Forecast Data'!C:C,BQ$6)))/(SUMIFS('Forecast Data'!H:H,'Forecast Data'!B:B,B14,'Forecast Data'!C:C,BJ$6)+SUMIFS('Forecast Data'!H:H,'Forecast Data'!B:B,B14,'Forecast Data'!C:C,BK$6)+SUMIFS('Forecast Data'!H:H,'Forecast Data'!B:B,B14,'Forecast Data'!C:C,BL$6)+SUMIFS('Forecast Data'!H:H,'Forecast Data'!B:B,B14,'Forecast Data'!C:C,BM$6)+SUMIFS('Forecast Data'!H:H,'Forecast Data'!B:B,B14,'Forecast Data'!C:C,BN$6)+SUMIFS('Forecast Data'!H:H,'Forecast Data'!B:B,B14,'Forecast Data'!C:C,BO$6)+SUMIFS('Forecast Data'!H:H,'Forecast Data'!B:B,B14,'Forecast Data'!C:C,BP$6)+SUMIFS('Forecast Data'!H:H,'Forecast Data'!B:B,B14,'Forecast Data'!C:C,BQ$6)),"") -> 0.35559392 | BY14: =((L14-E14)/($L$4-$E$4))*$M$4 -> 0.071761059 | BZ14: =((AVERAGE(W14:AD14)-BW14)/(AVERAGE($W$4:$AD$4)-$BW$4))*$BX$4 -> 0.070953202 | CA14: =(BY14-BZ14)*100 -> 0.080785663 | CB14: =ABS(CA14)/100 -> 0.00080785663 | CD14: =(SUMIFS('Forecast Data'!H:H,'Forecast Data'!B:B,D14,'Forecast Data'!C:C,BK$6)+SUMIFS('Forecast Data'!H:H,'Forecast Data'!B:B,D14,'Forecast Data'!C:C,BL$6)+SUMIFS('Forecast Data'!H:H,'Forecast Data'!B:B,D14,'Forecast Data'!C:C,BM$6)+SUMIFS('Forecast Data'!H:H,'Forecast Data'!B:B,D14,'Forecast Data'!C:C,BJ$6))/4 -> 237972 | CE14: =IFERROR((SUM(W14:Z14)-(SUMIFS('Forecast Data'!H:H,'Forecast Data'!B:B,D14,'Forecast Data'!C:C,BJ$6)+SUMIFS('Forecast Data'!H:H,'Forecast Data'!B:B,D14,'Forecast Data'!C:C,BK$6)+SUMIFS('Forecast Data'!H:H,'Forecast Data'!B:B,D14,'Forecast Data'!C:C,BL$6)+SUMIFS('Forecast Data'!H:H,'Forecast Data'!B:B,D14,'Forecast Data'!C:C,BM$6)))/(SUMIFS('Forecast Data'!H:H,'Forecast Data'!B:B,D14,'Forecast Data'!C:C,BJ$6)+SUMIFS('Forecast Data'!H:H,'Forecast Data'!B:B,D14,'Forecast Data'!C:C,BK$6)+SUMIFS('Forecast Data'!H:H,'Forecast Data'!B:B,D14,'Forecast Data'!C:C,BL$6)+SUMIFS('Forecast Data'!H:H,'Forecast Data'!B:B,D14,'Forecast Data'!C:C,BM$6)),"") -> 0.37585199 | CF14: =(($L14-$E14)/($L$4-$E$4))*$M$4 -> 0.071761059 | CG14: =((AVERAGE(W14:Z14)-CD14)/(AVERAGE($W$4:$Z$4)-$CD$4))*$CE$4 -> 0.074987111 | CH14: =(CF14-CG14)*100 -> -0.32260524
B15: =D15 -> Integrative Therapeutics | D15: Integrative Therapeutics | E15: =SUMIFS('Fin Data'!F:F,'Fin Data'!A:A,D15) -> 37912 | F15: =SUMIFS('Fin Data with 6 week hist'!I:I,'Fin Data with 6 week hist'!$A:$A,$D15) -> 44017 | G15: =SUMIFS('Fin Data with 6 week hist'!J:J,'Fin Data with 6 week hist'!$A:$A,$D15) -> 42224 | H15: =SUMIFS('Fin Data with 6 week hist'!K:K,'Fin Data with 6 week hist'!$A:$A,$D15)+SUMIFS('Unit Cancellations'!D:D,'Unit Cancellations'!$B:$B,$D15) -> 42904 | I15: =SUMIFS('Fin Data with 6 week hist'!L:L,'Fin Data with 6 week hist'!$A:$A,$D15)+SUMIFS('Unit Cancellations'!E:E,'Unit Cancellations'!$B:$B,$D15) -> 42337 | J15: =SUMIFS('Fin Data with 6 week hist'!M:M,'Fin Data with 6 week hist'!$A:$A,$D15)+SUMIFS('Unit Cancellations'!F:F,'Unit Cancellations'!$B:$B,$D15) -> 40207 | K15: =SUMIFS('Fin Data with 6 week hist'!N:N,'Fin Data with 6 week hist'!$A:$A,$D15)+SUMIFS('Unit Cancellations'!G:G,'Unit Cancellations'!$B:$B,$D15) -> 43778 | L15: =SUMIFS('Fin Data'!AN:AN,'Fin Data'!A:A,D15) -> 42577.5 | M15: =IFERROR(SUMIFS('Fin Data'!AO:AO,'Fin Data'!A:A,D15),"") -> 0.1230613 | O15: =AVERAGE(W15:Z15) -> 45148.75 | P15: =CE15 -> 0.20005449 | R15: =AVERAGE(W15:AD15) -> 45198.625 | S15: =BX15 -> 0.18740251 | T15: =AVERAGE(AW15:BD15) -> 41823.125 | U15: =#REF! -> #REF! | W15: =SUMIFS('Forecast Data'!$D:$D,'Forecast Data'!$C:$C,W$6,'Forecast Data'!$B:$B,$D15) -> 45100 | X15: =SUMIFS('Forecast Data'!$D:$D,'Forecast Data'!$C:$C,X$6,'Forecast Data'!$B:$B,$D15) -> 45098 | Y15: =SUMIFS('Forecast Data'!$D:$D,'Forecast Data'!$C:$C,Y$6,'Forecast Data'!$B:$B,$D15) -> 45158 | Z15: =SUMIFS('Forecast Data'!$D:$D,'Forecast Data'!$C:$C,Z$6,'Forecast Data'!$B:$B,$D15) -> 45239 | AA15: =SUMIFS('Forecast Data'!$D:$D,'Forecast Data'!$C:$C,AA$6,'Forecast Data'!$B:$B,$D15) -> 45210 | AB15: =SUMIFS('Forecast Data'!$D:$D,'Forecast Data'!$C:$C,AB$6,'Forecast Data'!$B:$B,$D15) -> 45219 | AC15: =SUMIFS('Forecast Data'!$D:$D,'Forecast Data'!$C:$C,AC$6,'Forecast Data'!$B:$B,$D15) -> 45283 | AD15: =SUMIFS('Forecast Data'!$D:$D,'Forecast Data'!$C:$C,AD$6,'Forecast Data'!$B:$B,$D15) -> 45282 | ... AH15: =SUMIFS('Forecast Data'!$D:$D,'Forecast Data'!$C:$C,AH$6,'Forecast Data'!$B:$B,$D15) -> 45541 | AJ15: =IF(SUMIFS('Forecast Data'!$E:$E,'Forecast Data'!$C:$C,AJ$6,'Forecast Data'!$B:$B,$D15)=0,"",SUMIFS('Forecast Data'!$E:$E,'Forecast Data'!$C:$C,AJ$6,'Forecast Data'!$B:$B,$D15)) -> 0.2 | AK15: =IF(SUMIFS('Forecast Data'!$E:$E,'Forecast Data'!$C:$C,AK$6,'Forecast Data'!$B:$B,$D15)=0,"",SUMIFS('Forecast Data'!$E:$E,'Forecast Data'!$C:$C,AK$6,'Forecast Data'!$B:$B,$D15)) -> 0.2 | AL15: =IF(SUMIFS('Forecast Data'!$E:$E,'Forecast Data'!$C:$C,AL$6,'Forecast Data'!$B:$B,$D15)=0,"",SUMIFS('Forecast Data'!$E:$E,'Forecast Data'!$C:$C,AL$6,'Forecast Data'!$B:$B,$D15)) -> 0.24 | AM15: =IF(SUMIFS('Forecast Data'!$E:$E,'Forecast Data'!$C:$C,AM$6,'Forecast Data'!$B:$B,$D15)=0,"",SUMIFS('Forecast Data'!$E:$E,'Forecast Data'!$C:$C,AM$6,'Forecast Data'!$B:$B,$D15)) -> 0.17 | AN15: =IF(SUMIFS('Forecast Data'!$E:$E,'Forecast Data'!$C:$C,AN$6,'Forecast Data'!$B:$B,$D15)=0,"",SUMIFS('Forecast Data'!$E:$E,'Forecast Data'!$C:$C,AN$6,'Forecast Data'!$B:$B,$D15)) -> 0.16 | AO15: =IF(SUMIFS('Forecast Data'!$E:$E,'Forecast Data'!$C:$C,AO$6,'Forecast Data'!$B:$B,$D15)=0,"",SUMIFS('Forecast Data'!$E:$E,'Forecast Data'!$C:$C,AO$6,'Forecast Data'!$B:$B,$D15)) -> 0.17 | AP15: =IF(SUMIFS('Forecast Data'!$E:$E,'Forecast Data'!$C:$C,AP$6,'Forecast Data'!$B:$B,$D15)=0,"",SUMIFS('Forecast Data'!$E:$E,'Forecast Data'!$C:$C,AP$6,'Forecast Data'!$B:$B,$D15)) -> 0.21 | AQ15: =IF(SUMIFS('Forecast Data'!$E:$E,'Forecast Data'!$C:$C,AQ$6,'Forecast Data'!$B:$B,$D15)=0,"",SUMIFS('Forecast Data'!$E:$E,'Forecast Data'!$C:$C,AQ$6,'Forecast Data'!$B:$B,$D15)) -> 0.16 | ... AU15: =IF(SUMIFS('Forecast Data'!$E:$E,'Forecast Data'!$C:$C,AU$6,'Forecast Data'!$B:$B,$D15)=0,"",SUMIFS('Forecast Data'!$E:$E,'Forecast Data'!$C:$C,AU$6,'Forecast Data'!$B:$B,$D15)) -> 0.2 | AW15: =SUMIFS('OP Units'!E:E,'OP Units'!$A:$A,$D15) -> 38288 | AX15: =SUMIFS('OP Units'!F:F,'OP Units'!$A:$A,$D15) -> 40656 | AY15: =SUMIFS('OP Units'!G:G,'OP Units'!$A:$A,$D15) -> 43395 | AZ15: =SUMIFS('OP Units'!H:H,'OP Units'!$A:$A,$D15) -> 45676 | BA15: =SUMIFS('OP Units'!I:I,'OP Units'!$A:$A,$D15) -> 43857 | BB15: =SUMIFS('OP Units'!J:J,'OP Units'!$A:$A,$D15) -> 42998 | BC15: =SUMIFS('OP Units'!K:K,'OP Units'!$A:$A,$D15) -> 40366 | BD15: =SUMIFS('OP Units'!L:L,'OP Units'!$A:$A,$D15) -> 39349 | BE15: =SUMIFS('OP Units'!M:M,'OP Units'!$A:$A,$D15) -> 39024 | BF15: =SUMIFS('OP Units'!N:N,'OP Units'!$A:$A,$D15) -> 40065 | BG15: =SUMIFS('OP Units'!O:O,'OP Units'!$A:$A,$D15) -> 40691 | BH15: =SUMIFS('OP Units'!P:P,'OP Units'!$A:$A,$D15) -> 39699 | BJ15: =IFERROR((SUMIFS('OP Units'!E:E,'OP Units'!$A:$A,$D15)-SUMIFS('Forecast Data'!$H:$H,'Forecast Data'!$C:$C,BJ$6,'Forecast Data'!$B:$B,$D15))/SUMIFS('Forecast Data'!$H:$H,'Forecast Data'!$C:$C,BJ$6,'Forecast Data'!$B:$B,$D15),"") -> 0.015569879 | BK15: =IFERROR((SUMIFS('OP Units'!F:F,'OP Units'!$A:$A,$D15)-SUMIFS('Forecast Data'!$H:$H,'Forecast Data'!$C:$C,BK$6,'Forecast Data'!$B:$B,$D15))/SUMIFS('Forecast Data'!$H:$H,'Forecast Data'!$C:$C,BK$6,'Forecast Data'!$B:$B,$D15),"") -> 0.077579581 | BL15: =IFERROR((SUMIFS('OP Units'!G:G,'OP Units'!$A:$A,$D15)-SUMIFS('Forecast Data'!$H:$H,'Forecast Data'!$C:$C,BL$6,'Forecast Data'!$B:$B,$D15))/SUMIFS('Forecast Data'!$H:$H,'Forecast Data'!$C:$C,BL$6,'Forecast Data'!$B:$B,$D15),"") -> 0.19427015 | BM15: =IFERROR((SUMIFS('OP Units'!H:H,'OP Units'!$A:$A,$D15)-SUMIFS('Forecast Data'!$H:$H,'Forecast Data'!$C:$C,BM$6,'Forecast Data'!$B:$B,$D15))/SUMIFS('Forecast Data'!$H:$H,'Forecast Data'!$C:$C,BM$6,'Forecast Data'!$B:$B,$D15),"") -> 0.17955737 | BN15: =IFERROR((SUMIFS('OP Units'!I:I,'OP Units'!$A:$A,$D15)-SUMIFS('Forecast Data'!$H:$H,'Forecast Data'!$C:$C,BN$6,'Forecast Data'!$B:$B,$D15))/SUMIFS('Forecast Data'!$H:$H,'Forecast Data'!$C:$C,BN$6,'Forecast Data'!$B:$B,$D15),"") -> 0.12789322 | BO15: =IFERROR((SUMIFS('OP Units'!J:J,'OP Units'!$A:$A,$D15)-SUMIFS('Forecast Data'!$H:$H,'Forecast Data'!$C:$C,BO$6,'Forecast Data'!$B:$B,$D15))/SUMIFS('Forecast Data'!$H:$H,'Forecast Data'!$C:$C,BO$6,'Forecast Data'!$B:$B,$D15),"") -> 0.10871023 | BP15: =IFERROR((SUMIFS('OP Units'!K:K,'OP Units'!$A:$A,$D15)-SUMIFS('Forecast Data'!$H:$H,'Forecast Data'!$C:$C,BP$6,'Forecast Data'!$B:$B,$D15))/SUMIFS('Forecast Data'!$H:$H,'Forecast Data'!$C:$C,BP$6,'Forecast Data'!$B:$B,$D15),"") -> 0.08132869 | BQ15: =IFERROR((SUMIFS('OP Units'!L:L,'OP Units'!$A:$A,$D15)-SUMIFS('Forecast Data'!$H:$H,'Forecast Data'!$C:$C,BQ$6,'Forecast Data'!$B:$B,$D15))/SUMIFS('Forecast Data'!$H:$H,'Forecast Data'!$C:$C,BQ$6,'Forecast Data'!$B:$B,$D15),"") -> 0.0080182396 | BR15: =IFERROR((SUMIFS('OP Units'!M:M,'OP Units'!$A:$A,$D15)-SUMIFS('Forecast Data'!$H:$H,'Forecast Data'!$C:$C,BR$6,'Forecast Data'!$B:$B,$D15))/SUMIFS('Forecast Data'!$H:$H,'Forecast Data'!$C:$C,BR$6,'Forecast Data'!$B:$B,$D15),"") -> 0.0017455591 | BS15: =IFERROR((SUMIFS('OP Units'!N:N,'OP Units'!$A:$A,$D15)-SUMIFS('Forecast Data'!$H:$H,'Forecast Data'!$C:$C,BS$6,'Forecast Data'!$B:$B,$D15))/SUMIFS('Forecast Data'!$H:$H,'Forecast Data'!$C:$C,BS$6,'Forecast Data'!$B:$B,$D15),"") -> 0.045865093 | BT15: =IFERROR((SUMIFS('OP Units'!O:O,'OP Units'!$A:$A,$D15)-SUMIFS('Forecast Data'!$H:$H,'Forecast Data'!$C:$C,BT$6,'Forecast Data'!$B:$B,$D15))/SUMIFS('Forecast Data'!$H:$H,'Forecast Data'!$C:$C,BT$6,'Forecast Data'!$B:$B,$D15),"") -> 0.090297688 | BU15: =IFERROR((SUMIFS('OP Units'!P:P,'OP Units'!$A:$A,$D15)-SUMIFS('Forecast Data'!$H:$H,'Forecast Data'!$C:$C,BU$6,'Forecast Data'!$B:$B,$D15))/SUMIFS('Forecast Data'!$H:$H,'Forecast Data'!$C:$C,BU$6,'Forecast Data'!$B:$B,$D15),"") -> 0.049266552 | BW15: =(SUMIFS('Forecast Data'!H:H,'Forecast Data'!B:B,D15,'Forecast Data'!C:C,BK$6)+SUMIFS('Forecast Data'!H:H,'Forecast Data'!B:B,D15,'Forecast Data'!C:C,BL$6)+SUMIFS('Forecast Data'!H:H,'Forecast Data'!B:B,D15,'Forecast Data'!C:C,BM$6)+SUMIFS('Forecast Data'!H:H,'Forecast Data'!B:B,D15,'Forecast Data'!C:C,BN$6)+SUMIFS('Forecast Data'!H:H,'Forecast Data'!B:B,D15,'Forecast Data'!C:C,BO$6)+SUMIFS('Forecast Data'!H:H,'Forecast Data'!B:B,D15,'Forecast Data'!C:C,BP$6)+SUMIFS('Forecast Data'!H:H,'Forecast Data'!B:B,D15,'Forecast Data'!C:C,BQ$6)+SUMIFS('Forecast Data'!H:H,'Forecast Data'!B:B,D15,'Forecast Data'!C:C,BJ$6))/8 -> 38065.125 | BX15: =IFERROR((SUM(W15:AD15)-(SUMIFS('Forecast Data'!H:H,'Forecast Data'!B:B,B15,'Forecast Data'!C:C,BJ$6)+SUMIFS('Forecast Data'!H:H,'Forecast Data'!B:B,B15,'Forecast Data'!C:C,BK$6)+SUMIFS('Forecast Data'!H:H,'Forecast Data'!B:B,B15,'Forecast Data'!C:C,BL$6)+SUMIFS('Forecast Data'!H:H,'Forecast Data'!B:B,B15,'Forecast Data'!C:C,BM$6)+SUMIFS('Forecast Data'!H:H,'Forecast Data'!B:B,B15,'Forecast Data'!C:C,BN$6)+SUMIFS('Forecast Data'!H:H,'Forecast Data'!B:B,B15,'Forecast Data'!C:C,BO$6)+SUMIFS('Forecast Data'!H:H,'Forecast Data'!B:B,B15,'Forecast Data'!C:C,BP$6)+SUMIFS('Forecast Data'!H:H,'Forecast Data'!B:B,B15,'Forecast Data'!C:C,BQ$6)))/(SUMIFS('Forecast Data'!H:H,'Forecast Data'!B:B,B15,'Forecast Data'!C:C,BJ$6)+SUMIFS('Forecast Data'!H:H,'Forecast Data'!B:B,B15,'Forecast Data'!C:C,BK$6)+SUMIFS('Forecast Data'!H:H,'Forecast Data'!B:B,B15,'Forecast Data'!C:C,BL$6)+SUMIFS('Forecast Data'!H:H,'Forecast Data'!B:B,B15,'Forecast Data'!C:C,BM$6)+SUMIFS('Forecast Data'!H:H,'Forecast Data'!B:B,B15,'Forecast Data'!C:C,BN$6)+SUMIFS('Forecast Data'!H:H,'Forecast Data'!B:B,B15,'Forecast Data'!C:C,BO$6)+SUMIFS('Forecast Data'!H:H,'Forecast Data'!B:B,B15,'Forecast Data'!C:C,BP$6)+SUMIFS('Forecast Data'!H:H,'Forecast Data'!B:B,B15,'Forecast Data'!C:C,BQ$6)),"") -> 0.18740251 | BY15: =((L15-E15)/($L$4-$E$4))*$M$4 -> 0.003989663 | BZ15: =((AVERAGE(W15:AD15)-BW15)/(AVERAGE($W$4:$AD$4)-$BW$4))*$BX$4 -> 0.0058658701 | CA15: =(BY15-BZ15)*100 -> -0.1876207 | CB15: =ABS(CA15)/100 -> 0.001876207 | CD15: =(SUMIFS('Forecast Data'!H:H,'Forecast Data'!B:B,D15,'Forecast Data'!C:C,BK$6)+SUMIFS('Forecast Data'!H:H,'Forecast Data'!B:B,D15,'Forecast Data'!C:C,BL$6)+SUMIFS('Forecast Data'!H:H,'Forecast Data'!B:B,D15,'Forecast Data'!C:C,BM$6)+SUMIFS('Forecast Data'!H:H,'Forecast Data'!B:B,D15,'Forecast Data'!C:C,BJ$6))/4 -> 37622.25 | CE15: =IFERROR((SUM(W15:Z15)-(SUMIFS('Forecast Data'!H:H,'Forecast Data'!B:B,D15,'Forecast Data'!C:C,BJ$6)+SUMIFS('Forecast Data'!H:H,'Forecast Data'!B:B,D15,'Forecast Data'!C:C,BK$6)+SUMIFS('Forecast Data'!H:H,'Forecast Data'!B:B,D15,'Forecast Data'!C:C,BL$6)+SUMIFS('Forecast Data'!H:H,'Forecast Data'!B:B,D15,'Forecast Data'!C:C,BM$6)))/(SUMIFS('Forecast Data'!H:H,'Forecast Data'!B:B,D15,'Forecast Data'!C:C,BJ$6)+SUMIFS('Forecast Data'!H:H,'Forecast Data'!B:B,D15,'Forecast Data'!C:C,BK$6)+SUMIFS('Forecast Data'!H:H,'Forecast Data'!B:B,D15,'Forecast Data'!C:C,BL$6)+SUMIFS('Forecast Data'!H:H,'Forecast Data'!B:B,D15,'Forecast Data'!C:C,BM$6)),"") -> 0.20005449 | CF15: =(($L15-$E15)/($L$4-$E$4))*$M$4 -> 0.003989663 | CG15: =((AVERAGE(W15:Z15)-CD15)/(AVERAGE($W$4:$Z$4)-$CD$4))*$CE$4 -> 0.0063101106 | CH15: =(CF15-CG15)*100 -> -0.23204476
D16: Garanimals | E16: =SUMIFS('Fin Data'!F:F,'Fin Data'!A:A,D16) -> 0 | F16: =SUMIFS('Fin Data with 6 week hist'!I:I,'Fin Data with 6 week hist'!$A:$A,$D16) -> 356 | G16: =SUMIFS('Fin Data with 6 week hist'!J:J,'Fin Data with 6 week hist'!$A:$A,$D16) -> 1096 | H16: =SUMIFS('Fin Data with 6 week hist'!K:K,'Fin Data with 6 week hist'!$A:$A,$D16)+SUMIFS('Unit Cancellations'!D:D,'Unit Cancellations'!$B:$B,$D16) -> 1114 | I16: =SUMIFS('Fin Data with 6 week hist'!L:L,'Fin Data with 6 week hist'!$A:$A,$D16)+SUMIFS('Unit Cancellations'!E:E,'Unit Cancellations'!$B:$B,$D16) -> 1883 | J16: =SUMIFS('Fin Data with 6 week hist'!M:M,'Fin Data with 6 week hist'!$A:$A,$D16)+SUMIFS('Unit Cancellations'!F:F,'Unit Cancellations'!$B:$B,$D16) -> 2534 | K16: =SUMIFS('Fin Data with 6 week hist'!N:N,'Fin Data with 6 week hist'!$A:$A,$D16)+SUMIFS('Unit Cancellations'!G:G,'Unit Cancellations'!$B:$B,$D16) -> 3266 | L16: =SUMIFS('Fin Data'!AN:AN,'Fin Data'!A:A,D16) -> 1708 | M16: =IFERROR(SUMIFS('Fin Data'!AO:AO,'Fin Data'!A:A,D16),"") -> 0 | O16: =AVERAGE(W16:Z16) -> 4758.75 | P16: =CE16 | R16: =AVERAGE(W16:AD16) -> 7313.25 | S16: =BX16 | T16: =AVERAGE(AW16:BD16) -> 3687.375 | U16: =#REF! -> #REF! | W16: =SUMIFS('Forecast Data'!$D:$D,'Forecast Data'!$C:$C,W$6,'Forecast Data'!$B:$B,$D16) -> 3546 | X16: =SUMIFS('Forecast Data'!$D:$D,'Forecast Data'!$C:$C,X$6,'Forecast Data'!$B:$B,$D16) -> 4255 | Y16: =SUMIFS('Forecast Data'!$D:$D,'Forecast Data'!$C:$C,Y$6,'Forecast Data'!$B:$B,$D16) -> 5106 | Z16: =SUMIFS('Forecast Data'!$D:$D,'Forecast Data'!$C:$C,Z$6,'Forecast Data'!$B:$B,$D16) -> 6128 | AA16: =SUMIFS('Forecast Data'!$D:$D,'Forecast Data'!$C:$C,AA$6,'Forecast Data'!$B:$B,$D16) -> 7353 | AB16: =SUMIFS('Forecast Data'!$D:$D,'Forecast Data'!$C:$C,AB$6,'Forecast Data'!$B:$B,$D16) -> 8824 | AC16: =SUMIFS('Forecast Data'!$D:$D,'Forecast Data'!$C:$C,AC$6,'Forecast Data'!$B:$B,$D16) -> 10588 | AD16: =SUMIFS('Forecast Data'!$D:$D,'Forecast Data'!$C:$C,AD$6,'Forecast Data'!$B:$B,$D16) -> 12706 | ... AH16: =SUMIFS('Forecast Data'!$D:$D,'Forecast Data'!$C:$C,AH$6,'Forecast Data'!$B:$B,$D16) -> 26347 | AJ16: =IF(SUMIFS('Forecast Data'!$E:$E,'Forecast Data'!$C:$C,AJ$6,'Forecast Data'!$B:$B,$D16)=0,"",SUMIFS('Forecast Data'!$E:$E,'Forecast Data'!$C:$C,AJ$6,'Forecast Data'!$B:$B,$D16)) | AK16: =IF(SUMIFS('Forecast Data'!$E:$E,'Forecast Data'!$C:$C,AK$6,'Forecast Data'!$B:$B,$D16)=0,"",SUMIFS('Forecast Data'!$E:$E,'Forecast Data'!$C:$C,AK$6,'Forecast Data'!$B:$B,$D16)) | AL16: =IF(SUMIFS('Forecast Data'!$E:$E,'Forecast Data'!$C:$C,AL$6,'Forecast Data'!$B:$B,$D16)=0,"",SUMIFS('Forecast Data'!$E:$E,'Forecast Data'!$C:$C,AL$6,'Forecast Data'!$B:$B,$D16)) | AM16: =IF(SUMIFS('Forecast Data'!$E:$E,'Forecast Data'!$C:$C,AM$6,'Forecast Data'!$B:$B,$D16)=0,"",SUMIFS('Forecast Data'!$E:$E,'Forecast Data'!$C:$C,AM$6,'Forecast Data'!$B:$B,$D16)) | AN16: =IF(SUMIFS('Forecast Data'!$E:$E,'Forecast Data'!$C:$C,AN$6,'Forecast Data'!$B:$B,$D16)=0,"",SUMIFS('Forecast Data'!$E:$E,'Forecast Data'!$C:$C,AN$6,'Forecast Data'!$B:$B,$D16)) | AO16: =IF(SUMIFS('Forecast Data'!$E:$E,'Forecast Data'!$C:$C,AO$6,'Forecast Data'!$B:$B,$D16)=0,"",SUMIFS('Forecast Data'!$E:$E,'Forecast Data'!$C:$C,AO$6,'Forecast Data'!$B:$B,$D16)) | AP16: =IF(SUMIFS('Forecast Data'!$E:$E,'Forecast Data'!$C:$C,AP$6,'Forecast Data'!$B:$B,$D16)=0,"",SUMIFS('Forecast Data'!$E:$E,'Forecast Data'!$C:$C,AP$6,'Forecast Data'!$B:$B,$D16)) | AQ16: =IF(SUMIFS('Forecast Data'!$E:$E,'Forecast Data'!$C:$C,AQ$6,'Forecast Data'!$B:$B,$D16)=0,"",SUMIFS('Forecast Data'!$E:$E,'Forecast Data'!$C:$C,AQ$6,'Forecast Data'!$B:$B,$D16)) | ... AU16: =IF(SUMIFS('Forecast Data'!$E:$E,'Forecast Data'!$C:$C,AU$6,'Forecast Data'!$B:$B,$D16)=0,"",SUMIFS('Forecast Data'!$E:$E,'Forecast Data'!$C:$C,AU$6,'Forecast Data'!$B:$B,$D16)) | AW16: =SUMIFS('OP Units'!E:E,'OP Units'!$A:$A,$D16) -> 2751 | AX16: =SUMIFS('OP Units'!F:F,'OP Units'!$A:$A,$D16) -> 2896 | AY16: =SUMIFS('OP Units'!G:G,'OP Units'!$A:$A,$D16) -> 3729 | AZ16: =SUMIFS('OP Units'!H:H,'OP Units'!$A:$A,$D16) -> 3899 | BA16: =SUMIFS('OP Units'!I:I,'OP Units'!$A:$A,$D16) -> 3960 | BB16: =SUMIFS('OP Units'!J:J,'OP Units'!$A:$A,$D16) -> 4209 | BC16: =SUMIFS('OP Units'!K:K,'OP Units'!$A:$A,$D16) -> 4071 | BD16: =SUMIFS('OP Units'!L:L,'OP Units'!$A:$A,$D16) -> 3984 | BE16: =SUMIFS('OP Units'!M:M,'OP Units'!$A:$A,$D16) -> 4032 | BF16: =SUMIFS('OP Units'!N:N,'OP Units'!$A:$A,$D16) -> 4291 | BG16: =SUMIFS('OP Units'!O:O,'OP Units'!$A:$A,$D16) -> 4547 | BH16: =SUMIFS('OP Units'!P:P,'OP Units'!$A:$A,$D16) -> 4679 | BJ16: =IFERROR((SUMIFS('OP Units'!E:E,'OP Units'!$A:$A,$D16)-SUMIFS('Forecast Data'!$H:$H,'Forecast Data'!$C:$C,BJ$6,'Forecast Data'!$B:$B,$D16))/SUMIFS('Forecast Data'!$H:$H,'Forecast Data'!$C:$C,BJ$6,'Forecast Data'!$B:$B,$D16),"") | BK16: =IFERROR((SUMIFS('OP Units'!F:F,'OP Units'!$A:$A,$D16)-SUMIFS('Forecast Data'!$H:$H,'Forecast Data'!$C:$C,BK$6,'Forecast Data'!$B:$B,$D16))/SUMIFS('Forecast Data'!$H:$H,'Forecast Data'!$C:$C,BK$6,'Forecast Data'!$B:$B,$D16),"") | BL16: =IFERROR((SUMIFS('OP Units'!G:G,'OP Units'!$A:$A,$D16)-SUMIFS('Forecast Data'!$H:$H,'Forecast Data'!$C:$C,BL$6,'Forecast Data'!$B:$B,$D16))/SUMIFS('Forecast Data'!$H:$H,'Forecast Data'!$C:$C,BL$6,'Forecast Data'!$B:$B,$D16),"") | BM16: =IFERROR((SUMIFS('OP Units'!H:H,'OP Units'!$A:$A,$D16)-SUMIFS('Forecast Data'!$H:$H,'Forecast Data'!$C:$C,BM$6,'Forecast Data'!$B:$B,$D16))/SUMIFS('Forecast Data'!$H:$H,'Forecast Data'!$C:$C,BM$6,'Forecast Data'!$B:$B,$D16),"") | BN16: =IFERROR((SUMIFS('OP Units'!I:I,'OP Units'!$A:$A,$D16)-SUMIFS('Forecast Data'!$H:$H,'Forecast Data'!$C:$C,BN$6,'Forecast Data'!$B:$B,$D16))/SUMIFS('Forecast Data'!$H:$H,'Forecast Data'!$C:$C,BN$6,'Forecast Data'!$B:$B,$D16),"") | BO16: =IFERROR((SUMIFS('OP Units'!J:J,'OP Units'!$A:$A,$D16)-SUMIFS('Forecast Data'!$H:$H,'Forecast Data'!$C:$C,BO$6,'Forecast Data'!$B:$B,$D16))/SUMIFS('Forecast Data'!$H:$H,'Forecast Data'!$C:$C,BO$6,'Forecast Data'!$B:$B,$D16),"") | BP16: =IFERROR((SUMIFS('OP Units'!K:K,'OP Units'!$A:$A,$D16)-SUMIFS('Forecast Data'!$H:$H,'Forecast Data'!$C:$C,BP$6,'Forecast Data'!$B:$B,$D16))/SUMIFS('Forecast Data'!$H:$H,'Forecast Data'!$C:$C,BP$6,'Forecast Data'!$B:$B,$D16),"") | BQ16: =IFERROR((SUMIFS('OP Units'!L:L,'OP Units'!$A:$A,$D16)-SUMIFS('Forecast Data'!$H:$H,'Forecast Data'!$C:$C,BQ$6,'Forecast Data'!$B:$B,$D16))/SUMIFS('Forecast Data'!$H:$H,'Forecast Data'!$C:$C,BQ$6,'Forecast Data'!$B:$B,$D16),"") | BR16: =IFERROR((SUMIFS('OP Units'!M:M,'OP Units'!$A:$A,$D16)-SUMIFS('Forecast Data'!$H:$H,'Forecast Data'!$C:$C,BR$6,'Forecast Data'!$B:$B,$D16))/SUMIFS('Forecast Data'!$H:$H,'Forecast Data'!$C:$C,BR$6,'Forecast Data'!$B:$B,$D16),"") | BS16: =IFERROR((SUMIFS('OP Units'!N:N,'OP Units'!$A:$A,$D16)-SUMIFS('Forecast Data'!$H:$H,'Forecast Data'!$C:$C,BS$6,'Forecast Data'!$B:$B,$D16))/SUMIFS('Forecast Data'!$H:$H,'Forecast Data'!$C:$C,BS$6,'Forecast Data'!$B:$B,$D16),"") | BT16: =IFERROR((SUMIFS('OP Units'!O:O,'OP Units'!$A:$A,$D16)-SUMIFS('Forecast Data'!$H:$H,'Forecast Data'!$C:$C,BT$6,'Forecast Data'!$B:$B,$D16))/SUMIFS('Forecast Data'!$H:$H,'Forecast Data'!$C:$C,BT$6,'Forecast Data'!$B:$B,$D16),"") | BU16: =IFERROR((SUMIFS('OP Units'!P:P,'OP Units'!$A:$A,$D16)-SUMIFS('Forecast Data'!$H:$H,'Forecast Data'!$C:$C,BU$6,'Forecast Data'!$B:$B,$D16))/SUMIFS('Forecast Data'!$H:$H,'Forecast Data'!$C:$C,BU$6,'Forecast Data'!$B:$B,$D16),"") | BW16: =(SUMIFS('Forecast Data'!H:H,'Forecast Data'!B:B,D16,'Forecast Data'!C:C,BK$6)+SUMIFS('Forecast Data'!H:H,'Forecast Data'!B:B,D16,'Forecast Data'!C:C,BL$6)+SUMIFS('Forecast Data'!H:H,'Forecast Data'!B:B,D16,'Forecast Data'!C:C,BM$6)+SUMIFS('Forecast Data'!H:H,'Forecast Data'!B:B,D16,'Forecast Data'!C:C,BN$6)+SUMIFS('Forecast Data'!H:H,'Forecast Data'!B:B,D16,'Forecast Data'!C:C,BO$6)+SUMIFS('Forecast Data'!H:H,'Forecast Data'!B:B,D16,'Forecast Data'!C:C,BP$6)+SUMIFS('Forecast Data'!H:H,'Forecast Data'!B:B,D16,'Forecast Data'!C:C,BQ$6)+SUMIFS('Forecast Data'!H:H,'Forecast Data'!B:B,D16,'Forecast Data'!C:C,BJ$6))/8 -> 0 | BX16: =IFERROR((SUM(W16:AD16)-(SUMIFS('Forecast Data'!H:H,'Forecast Data'!B:B,B16,'Forecast Data'!C:C,BJ$6)+SUMIFS('Forecast Data'!H:H,'Forecast Data'!B:B,B16,'Forecast Data'!C:C,BK$6)+SUMIFS('Forecast Data'!H:H,'Forecast Data'!B:B,B16,'Forecast Data'!C:C,BL$6)+SUMIFS('Forecast Data'!H:H,'Forecast Data'!B:B,B16,'Forecast Data'!C:C,BM$6)+SUMIFS('Forecast Data'!H:H,'Forecast Data'!B:B,B16,'Forecast Data'!C:C,BN$6)+SUMIFS('Forecast Data'!H:H,'Forecast Data'!B:B,B16,'Forecast Data'!C:C,BO$6)+SUMIFS('Forecast Data'!H:H,'Forecast Data'!B:B,B16,'Forecast Data'!C:C,BP$6)+SUMIFS('Forecast Data'!H:H,'Forecast Data'!B:B,B16,'Forecast Data'!C:C,BQ$6)))/(SUMIFS('Forecast Data'!H:H,'Forecast Data'!B:B,B16,'Forecast Data'!C:C,BJ$6)+SUMIFS('Forecast Data'!H:H,'Forecast Data'!B:B,B16,'Forecast Data'!C:C,BK$6)+SUMIFS('Forecast Data'!H:H,'Forecast Data'!B:B,B16,'Forecast Data'!C:C,BL$6)+SUMIFS('Forecast Data'!H:H,'Forecast Data'!B:B,B16,'Forecast Data'!C:C,BM$6)+SUMIFS('Forecast Data'!H:H,'Forecast Data'!B:B,B16,'Forecast Data'!C:C,BN$6)+SUMIFS('Forecast Data'!H:H,'Forecast Data'!B:B,B16,'Forecast Data'!C:C,BO$6)+SUMIFS('Forecast Data'!H:H,'Forecast Data'!B:B,B16,'Forecast Data'!C:C,BP$6)+SUMIFS('Forecast Data'!H:H,'Forecast Data'!B:B,B16,'Forecast Data'!C:C,BQ$6)),"") | BY16: =((L16-E16)/($L$4-$E$4))*$M$4 -> 0.0014605818 | BZ16: =((AVERAGE(W16:AD16)-BW16)/(AVERAGE($W$4:$AD$4)-$BW$4))*$BX$4 -> 0.0060136783 | CA16: =(BY16-BZ16)*100 -> -0.45530965 | CB16: =ABS(CA16)/100 -> 0.0045530965 | CD16: =(SUMIFS('Forecast Data'!H:H,'Forecast Data'!B:B,D16,'Forecast Data'!C:C,BK$6)+SUMIFS('Forecast Data'!H:H,'Forecast Data'!B:B,D16,'Forecast Data'!C:C,BL$6)+SUMIFS('Forecast Data'!H:H,'Forecast Data'!B:B,D16,'Forecast Data'!C:C,BM$6)+SUMIFS('Forecast Data'!H:H,'Forecast Data'!B:B,D16,'Forecast Data'!C:C,BJ$6))/4 -> 0 | CE16: =IFERROR((SUM(W16:Z16)-(SUMIFS('Forecast Data'!H:H,'Forecast Data'!B:B,D16,'Forecast Data'!C:C,BJ$6)+SUMIFS('Forecast Data'!H:H,'Forecast Data'!B:B,D16,'Forecast Data'!C:C,BK$6)+SUMIFS('Forecast Data'!H:H,'Forecast Data'!B:B,D16,'Forecast Data'!C:C,BL$6)+SUMIFS('Forecast Data'!H:H,'Forecast Data'!B:B,D16,'Forecast Data'!C:C,BM$6)))/(SUMIFS('Forecast Data'!H:H,'Forecast Data'!B:B,D16,'Forecast Data'!C:C,BJ$6)+SUMIFS('Forecast Data'!H:H,'Forecast Data'!B:B,D16,'Forecast Data'!C:C,BK$6)+SUMIFS('Forecast Data'!H:H,'Forecast Data'!B:B,D16,'Forecast Data'!C:C,BL$6)+SUMIFS('Forecast Data'!H:H,'Forecast Data'!B:B,D16,'Forecast Data'!C:C,BM$6)),"") | CF16: =(($L16-$E16)/($L$4-$E$4))*$M$4 -> 0.0014605818 | CG16: =((AVERAGE(W16:Z16)-CD16)/(AVERAGE($W$4:$Z$4)-$CD$4))*$CE$4 -> 0.0039896684 | CH16: =(CF16-CG16)*100 -> -0.25290865
B17: =D17 -> Yogi | D17: Yogi | E17: =SUMIFS('Fin Data'!F:F,'Fin Data'!A:A,D17) -> 22589 | F17: =SUMIFS('Fin Data with 6 week hist'!I:I,'Fin Data with 6 week hist'!$A:$A,$D17) -> 20530 | G17: =SUMIFS('Fin Data with 6 week hist'!J:J,'Fin Data with 6 week hist'!$A:$A,$D17) -> 21556 | H17: =SUMIFS('Fin Data with 6 week hist'!K:K,'Fin Data with 6 week hist'!$A:$A,$D17)+SUMIFS('Unit Cancellations'!D:D,'Unit Cancellations'!$B:$B,$D17) -> 22046 | I17: =SUMIFS('Fin Data with 6 week hist'!L:L,'Fin Data with 6 week hist'!$A:$A,$D17)+SUMIFS('Unit Cancellations'!E:E,'Unit Cancellations'!$B:$B,$D17) -> 21929 | J17: =SUMIFS('Fin Data with 6 week hist'!M:M,'Fin Data with 6 week hist'!$A:$A,$D17)+SUMIFS('Unit Cancellations'!F:F,'Unit Cancellations'!$B:$B,$D17) -> 19917 | K17: =SUMIFS('Fin Data with 6 week hist'!N:N,'Fin Data with 6 week hist'!$A:$A,$D17)+SUMIFS('Unit Cancellations'!G:G,'Unit Cancellations'!$B:$B,$D17) -> 19438 | L17: =SUMIFS('Fin Data'!AN:AN,'Fin Data'!A:A,D17) -> 20902.667 | M17: =IFERROR(SUMIFS('Fin Data'!AO:AO,'Fin Data'!A:A,D17),"") -> -0.074652855 | O17: =AVERAGE(W17:Z17) -> 21051 | P17: =CE17 -> 0.061078418 | R17: =AVERAGE(W17:AD17) -> 20111.5 | S17: =BX17 -> 0.033744539 | T17: =AVERAGE(AW17:BD17) -> 24665.875 | U17: =#REF! -> #REF! | W17: =SUMIFS('Forecast Data'!$D:$D,'Forecast Data'!$C:$C,W$6,'Forecast Data'!$B:$B,$D17) -> 22244 | X17: =SUMIFS('Forecast Data'!$D:$D,'Forecast Data'!$C:$C,X$6,'Forecast Data'!$B:$B,$D17) -> 21111 | Y17: =SUMIFS('Forecast Data'!$D:$D,'Forecast Data'!$C:$C,Y$6,'Forecast Data'!$B:$B,$D17) -> 20466 | Z17: =SUMIFS('Forecast Data'!$D:$D,'Forecast Data'!$C:$C,Z$6,'Forecast Data'!$B:$B,$D17) -> 20383 | AA17: =SUMIFS('Forecast Data'!$D:$D,'Forecast Data'!$C:$C,AA$6,'Forecast Data'!$B:$B,$D17) -> 20243 | AB17: =SUMIFS('Forecast Data'!$D:$D,'Forecast Data'!$C:$C,AB$6,'Forecast Data'!$B:$B,$D17) -> 19547 | AC17: =SUMIFS('Forecast Data'!$D:$D,'Forecast Data'!$C:$C,AC$6,'Forecast Data'!$B:$B,$D17) -> 18529 | AD17: =SUMIFS('Forecast Data'!$D:$D,'Forecast Data'!$C:$C,AD$6,'Forecast Data'!$B:$B,$D17) -> 18369 | ... AH17: =SUMIFS('Forecast Data'!$D:$D,'Forecast Data'!$C:$C,AH$6,'Forecast Data'!$B:$B,$D17) -> 16710 | AJ17: =IF(SUMIFS('Forecast Data'!$E:$E,'Forecast Data'!$C:$C,AJ$6,'Forecast Data'!$B:$B,$D17)=0,"",SUMIFS('Forecast Data'!$E:$E,'Forecast Data'!$C:$C,AJ$6,'Forecast Data'!$B:$B,$D17)) -> 0.11 | AK17: =IF(SUMIFS('Forecast Data'!$E:$E,'Forecast Data'!$C:$C,AK$6,'Forecast Data'!$B:$B,$D17)=0,"",SUMIFS('Forecast Data'!$E:$E,'Forecast Data'!$C:$C,AK$6,'Forecast Data'!$B:$B,$D17)) -> 0.04 | AL17: =IF(SUMIFS('Forecast Data'!$E:$E,'Forecast Data'!$C:$C,AL$6,'Forecast Data'!$B:$B,$D17)=0,"",SUMIFS('Forecast Data'!$E:$E,'Forecast Data'!$C:$C,AL$6,'Forecast Data'!$B:$B,$D17)) -> 0.04 | AM17: =IF(SUMIFS('Forecast Data'!$E:$E,'Forecast Data'!$C:$C,AM$6,'Forecast Data'!$B:$B,$D17)=0,"",SUMIFS('Forecast Data'!$E:$E,'Forecast Data'!$C:$C,AM$6,'Forecast Data'!$B:$B,$D17)) -> 0.06 | AN17: =IF(SUMIFS('Forecast Data'!$E:$E,'Forecast Data'!$C:$C,AN$6,'Forecast Data'!$B:$B,$D17)=0,"",SUMIFS('Forecast Data'!$E:$E,'Forecast Data'!$C:$C,AN$6,'Forecast Data'!$B:$B,$D17)) -> 0.06 | AO17: =IF(SUMIFS('Forecast Data'!$E:$E,'Forecast Data'!$C:$C,AO$6,'Forecast Data'!$B:$B,$D17)=0,"",SUMIFS('Forecast Data'!$E:$E,'Forecast Data'!$C:$C,AO$6,'Forecast Data'!$B:$B,$D17)) -> -0.01 | AP17: =IF(SUMIFS('Forecast Data'!$E:$E,'Forecast Data'!$C:$C,AP$6,'Forecast Data'!$B:$B,$D17)=0,"",SUMIFS('Forecast Data'!$E:$E,'Forecast Data'!$C:$C,AP$6,'Forecast Data'!$B:$B,$D17)) -> -0.06 | AQ17: =IF(SUMIFS('Forecast Data'!$E:$E,'Forecast Data'!$C:$C,AQ$6,'Forecast Data'!$B:$B,$D17)=0,"",SUMIFS('Forecast Data'!$E:$E,'Forecast Data'!$C:$C,AQ$6,'Forecast Data'!$B:$B,$D17)) -> 0.04 | ... AU17: =IF(SUMIFS('Forecast Data'!$E:$E,'Forecast Data'!$C:$C,AU$6,'Forecast Data'!$B:$B,$D17)=0,"",SUMIFS('Forecast Data'!$E:$E,'Forecast Data'!$C:$C,AU$6,'Forecast Data'!$B:$B,$D17)) -> 0.05 | AW17: =SUMIFS('OP Units'!E:E,'OP Units'!$A:$A,$D17) -> 26818 | AX17: =SUMIFS('OP Units'!F:F,'OP Units'!$A:$A,$D17) -> 25068 | AY17: =SUMIFS('OP Units'!G:G,'OP Units'!$A:$A,$D17) -> 25851 | AZ17: =SUMIFS('OP Units'!H:H,'OP Units'!$A:$A,$D17) -> 25451 | BA17: =SUMIFS('OP Units'!I:I,'OP Units'!$A:$A,$D17) -> 25383 | BB17: =SUMIFS('OP Units'!J:J,'OP Units'!$A:$A,$D17) -> 23695 | BC17: =SUMIFS('OP Units'!K:K,'OP Units'!$A:$A,$D17) -> 23541 | BD17: =SUMIFS('OP Units'!L:L,'OP Units'!$A:$A,$D17) -> 21520 | BE17: =SUMIFS('OP Units'!M:M,'OP Units'!$A:$A,$D17) -> 21947 | BF17: =SUMIFS('OP Units'!N:N,'OP Units'!$A:$A,$D17) -> 20923 | BG17: =SUMIFS('OP Units'!O:O,'OP Units'!$A:$A,$D17) -> 20915 | BH17: =SUMIFS('OP Units'!P:P,'OP Units'!$A:$A,$D17) -> 20207 | BJ17: =IFERROR((SUMIFS('OP Units'!E:E,'OP Units'!$A:$A,$D17)-SUMIFS('Forecast Data'!$H:$H,'Forecast Data'!$C:$C,BJ$6,'Forecast Data'!$B:$B,$D17))/SUMIFS('Forecast Data'!$H:$H,'Forecast Data'!$C:$C,BJ$6,'Forecast Data'!$B:$B,$D17),"") -> 0.33495943 | BK17: =IFERROR((SUMIFS('OP Units'!F:F,'OP Units'!$A:$A,$D17)-SUMIFS('Forecast Data'!$H:$H,'Forecast Data'!$C:$C,BK$6,'Forecast Data'!$B:$B,$D17))/SUMIFS('Forecast Data'!$H:$H,'Forecast Data'!$C:$C,BK$6,'Forecast Data'!$B:$B,$D17),"") -> 0.23743706 | BL17: =IFERROR((SUMIFS('OP Units'!G:G,'OP Units'!$A:$A,$D17)-SUMIFS('Forecast Data'!$H:$H,'Forecast Data'!$C:$C,BL$6,'Forecast Data'!$B:$B,$D17))/SUMIFS('Forecast Data'!$H:$H,'Forecast Data'!$C:$C,BL$6,'Forecast Data'!$B:$B,$D17),"") -> 0.31096912 | BM17: =IFERROR((SUMIFS('OP Units'!H:H,'OP Units'!$A:$A,$D17)-SUMIFS('Forecast Data'!$H:$H,'Forecast Data'!$C:$C,BM$6,'Forecast Data'!$B:$B,$D17))/SUMIFS('Forecast Data'!$H:$H,'Forecast Data'!$C:$C,BM$6,'Forecast Data'!$B:$B,$D17),"") -> 0.31931989 | BN17: =IFERROR((SUMIFS('OP Units'!I:I,'OP Units'!$A:$A,$D17)-SUMIFS('Forecast Data'!$H:$H,'Forecast Data'!$C:$C,BN$6,'Forecast Data'!$B:$B,$D17))/SUMIFS('Forecast Data'!$H:$H,'Forecast Data'!$C:$C,BN$6,'Forecast Data'!$B:$B,$D17),"") -> 0.32382393 | BO17: =IFERROR((SUMIFS('OP Units'!J:J,'OP Units'!$A:$A,$D17)-SUMIFS('Forecast Data'!$H:$H,'Forecast Data'!$C:$C,BO$6,'Forecast Data'!$B:$B,$D17))/SUMIFS('Forecast Data'!$H:$H,'Forecast Data'!$C:$C,BO$6,'Forecast Data'!$B:$B,$D17),"") -> 0.19829068 | BP17: =IFERROR((SUMIFS('OP Units'!K:K,'OP Units'!$A:$A,$D17)-SUMIFS('Forecast Data'!$H:$H,'Forecast Data'!$C:$C,BP$6,'Forecast Data'!$B:$B,$D17))/SUMIFS('Forecast Data'!$H:$H,'Forecast Data'!$C:$C,BP$6,'Forecast Data'!$B:$B,$D17),"") -> 0.19722321 | BQ17: =IFERROR((SUMIFS('OP Units'!L:L,'OP Units'!$A:$A,$D17)-SUMIFS('Forecast Data'!$H:$H,'Forecast Data'!$C:$C,BQ$6,'Forecast Data'!$B:$B,$D17))/SUMIFS('Forecast Data'!$H:$H,'Forecast Data'!$C:$C,BQ$6,'Forecast Data'!$B:$B,$D17),"") -> 0.21774559 | BR17: =IFERROR((SUMIFS('OP Units'!M:M,'OP Units'!$A:$A,$D17)-SUMIFS('Forecast Data'!$H:$H,'Forecast Data'!$C:$C,BR$6,'Forecast Data'!$B:$B,$D17))/SUMIFS('Forecast Data'!$H:$H,'Forecast Data'!$C:$C,BR$6,'Forecast Data'!$B:$B,$D17),"") -> 0.28766721 | BS17: =IFERROR((SUMIFS('OP Units'!N:N,'OP Units'!$A:$A,$D17)-SUMIFS('Forecast Data'!$H:$H,'Forecast Data'!$C:$C,BS$6,'Forecast Data'!$B:$B,$D17))/SUMIFS('Forecast Data'!$H:$H,'Forecast Data'!$C:$C,BS$6,'Forecast Data'!$B:$B,$D17),"") -> 0.23797408 | BT17: =IFERROR((SUMIFS('OP Units'!O:O,'OP Units'!$A:$A,$D17)-SUMIFS('Forecast Data'!$H:$H,'Forecast Data'!$C:$C,BT$6,'Forecast Data'!$B:$B,$D17))/SUMIFS('Forecast Data'!$H:$H,'Forecast Data'!$C:$C,BT$6,'Forecast Data'!$B:$B,$D17),"") -> 0.27227934 | BU17: =IFERROR((SUMIFS('OP Units'!P:P,'OP Units'!$A:$A,$D17)-SUMIFS('Forecast Data'!$H:$H,'Forecast Data'!$C:$C,BU$6,'Forecast Data'!$B:$B,$D17))/SUMIFS('Forecast Data'!$H:$H,'Forecast Data'!$C:$C,BU$6,'Forecast Data'!$B:$B,$D17),"") -> 0.26737331 | BW17: =(SUMIFS('Forecast Data'!H:H,'Forecast Data'!B:B,D17,'Forecast Data'!C:C,BK$6)+SUMIFS('Forecast Data'!H:H,'Forecast Data'!B:B,D17,'Forecast Data'!C:C,BL$6)+SUMIFS('Forecast Data'!H:H,'Forecast Data'!B:B,D17,'Forecast Data'!C:C,BM$6)+SUMIFS('Forecast Data'!H:H,'Forecast Data'!B:B,D17,'Forecast Data'!C:C,BN$6)+SUMIFS('Forecast Data'!H:H,'Forecast Data'!B:B,D17,'Forecast Data'!C:C,BO$6)+SUMIFS('Forecast Data'!H:H,'Forecast Data'!B:B,D17,'Forecast Data'!C:C,BP$6)+SUMIFS('Forecast Data'!H:H,'Forecast Data'!B:B,D17,'Forecast Data'!C:C,BQ$6)+SUMIFS('Forecast Data'!H:H,'Forecast Data'!B:B,D17,'Forecast Data'!C:C,BJ$6))/8 -> 19455 | BX17: =IFERROR((SUM(W17:AD17)-(SUMIFS('Forecast Data'!H:H,'Forecast Data'!B:B,B17,'Forecast Data'!C:C,BJ$6)+SUMIFS('Forecast Data'!H:H,'Forecast Data'!B:B,B17,'Forecast Data'!C:C,BK$6)+SUMIFS('Forecast Data'!H:H,'Forecast Data'!B:B,B17,'Forecast Data'!C:C,BL$6)+SUMIFS('Forecast Data'!H:H,'Forecast Data'!B:B,B17,'Forecast Data'!C:C,BM$6)+SUMIFS('Forecast Data'!H:H,'Forecast Data'!B:B,B17,'Forecast Data'!C:C,BN$6)+SUMIFS('Forecast Data'!H:H,'Forecast Data'!B:B,B17,'Forecast Data'!C:C,BO$6)+SUMIFS('Forecast Data'!H:H,'Forecast Data'!B:B,B17,'Forecast Data'!C:C,BP$6)+SUMIFS('Forecast Data'!H:H,'Forecast Data'!B:B,B17,'Forecast Data'!C:C,BQ$6)))/(SUMIFS('Forecast Data'!H:H,'Forecast Data'!B:B,B17,'Forecast Data'!C:C,BJ$6)+SUMIFS('Forecast Data'!H:H,'Forecast Data'!B:B,B17,'Forecast Data'!C:C,BK$6)+SUMIFS('Forecast Data'!H:H,'Forecast Data'!B:B,B17,'Forecast Data'!C:C,BL$6)+SUMIFS('Forecast Data'!H:H,'Forecast Data'!B:B,B17,'Forecast Data'!C:C,BM$6)+SUMIFS('Forecast Data'!H:H,'Forecast Data'!B:B,B17,'Forecast Data'!C:C,BN$6)+SUMIFS('Forecast Data'!H:H,'Forecast Data'!B:B,B17,'Forecast Data'!C:C,BO$6)+SUMIFS('Forecast Data'!H:H,'Forecast Data'!B:B,B17,'Forecast Data'!C:C,BP$6)+SUMIFS('Forecast Data'!H:H,'Forecast Data'!B:B,B17,'Forecast Data'!C:C,BQ$6)),"") -> 0.033744539 | BY17: =((L17-E17)/($L$4-$E$4))*$M$4 -> -0.0014420538 | BZ17: =((AVERAGE(W17:AD17)-BW17)/(AVERAGE($W$4:$AD$4)-$BW$4))*$BX$4 -> 0.00053983931 | CA17: =(BY17-BZ17)*100 -> -0.19818931 | CB17: =ABS(CA17)/100 -> 0.0019818931 | CD17: =(SUMIFS('Forecast Data'!H:H,'Forecast Data'!B:B,D17,'Forecast Data'!C:C,BK$6)+SUMIFS('Forecast Data'!H:H,'Forecast Data'!B:B,D17,'Forecast Data'!C:C,BL$6)+SUMIFS('Forecast Data'!H:H,'Forecast Data'!B:B,D17,'Forecast Data'!C:C,BM$6)+SUMIFS('Forecast Data'!H:H,'Forecast Data'!B:B,D17,'Forecast Data'!C:C,BJ$6))/4 -> 19839.25 | CE17: =IFERROR((SUM(W17:Z17)-(SUMIFS('Forecast Data'!H:H,'Forecast Data'!B:B,D17,'Forecast Data'!C:C,BJ$6)+SUMIFS('Forecast Data'!H:H,'Forecast Data'!B:B,D17,'Forecast Data'!C:C,BK$6)+SUMIFS('Forecast Data'!H:H,'Forecast Data'!B:B,D17,'Forecast Data'!C:C,BL$6)+SUMIFS('Forecast Data'!H:H,'Forecast Data'!B:B,D17,'Forecast Data'!C:C,BM$6)))/(SUMIFS('Forecast Data'!H:H,'Forecast Data'!B:B,D17,'Forecast Data'!C:C,BJ$6)+SUMIFS('Forecast Data'!H:H,'Forecast Data'!B:B,D17,'Forecast Data'!C:C,BK$6)+SUMIFS('Forecast Data'!H:H,'Forecast Data'!B:B,D17,'Forecast Data'!C:C,BL$6)+SUMIFS('Forecast Data'!H:H,'Forecast Data'!B:B,D17,'Forecast Data'!C:C,BM$6)),"") -> 0.061078418 | CF17: =(($L17-$E17)/($L$4-$E$4))*$M$4 -> -0.0014420538 | CG17: =((AVERAGE(W17:Z17)-CD17)/(AVERAGE($W$4:$Z$4)-$CD$4))*$CE$4 -> 0.001015914 | CH17: =(CF17-CG17)*100 -> -0.24579677
D18: Xymogen | E18: =SUMIFS('Fin Data'!F:F,'Fin Data'!A:A,D18) -> 0 | F18: =SUMIFS('Fin Data with 6 week hist'!I:I,'Fin Data with 6 week hist'!$A:$A,$D18) -> 3778 | G18: =SUMIFS('Fin Data with 6 week hist'!J:J,'Fin Data with 6 week hist'!$A:$A,$D18) -> 4064 | H18: =SUMIFS('Fin Data with 6 week hist'!K:K,'Fin Data with 6 week hist'!$A:$A,$D18)+SUMIFS('Unit Cancellations'!D:D,'Unit Cancellations'!$B:$B,$D18) -> 4166 | I18: =SUMIFS('Fin Data with 6 week hist'!L:L,'Fin Data with 6 week hist'!$A:$A,$D18)+SUMIFS('Unit Cancellations'!E:E,'Unit Cancellations'!$B:$B,$D18) -> 4494 | J18: =SUMIFS('Fin Data with 6 week hist'!M:M,'Fin Data with 6 week hist'!$A:$A,$D18)+SUMIFS('Unit Cancellations'!F:F,'Unit Cancellations'!$B:$B,$D18) -> 4967 | K18: =SUMIFS('Fin Data with 6 week hist'!N:N,'Fin Data with 6 week hist'!$A:$A,$D18)+SUMIFS('Unit Cancellations'!G:G,'Unit Cancellations'!$B:$B,$D18) -> 4140 | L18: =SUMIFS('Fin Data'!AN:AN,'Fin Data'!A:A,D18) -> 4268 | M18: =IFERROR(SUMIFS('Fin Data'!AO:AO,'Fin Data'!A:A,D18),"") -> 0 | O18: =AVERAGE(W18:Z18) -> 7287.75 | P18: =CE18 | R18: =AVERAGE(W18:AD18) -> 8207.125 | S18: =BX18 | T18: =AVERAGE(AW18:BD18) -> 5286.5 | U18: =#REF! -> #REF! | W18: =SUMIFS('Forecast Data'!$D:$D,'Forecast Data'!$C:$C,W$6,'Forecast Data'!$B:$B,$D18) -> 6896 | X18: =SUMIFS('Forecast Data'!$D:$D,'Forecast Data'!$C:$C,X$6,'Forecast Data'!$B:$B,$D18) -> 7239 | Y18: =SUMIFS('Forecast Data'!$D:$D,'Forecast Data'!$C:$C,Y$6,'Forecast Data'!$B:$B,$D18) -> 7418 | Z18: =SUMIFS('Forecast Data'!$D:$D,'Forecast Data'!$C:$C,Z$6,'Forecast Data'!$B:$B,$D18) -> 7598 | AA18: =SUMIFS('Forecast Data'!$D:$D,'Forecast Data'!$C:$C,AA$6,'Forecast Data'!$B:$B,$D18) -> 8002 | AB18: =SUMIFS('Forecast Data'!$D:$D,'Forecast Data'!$C:$C,AB$6,'Forecast Data'!$B:$B,$D18) -> 8825 | AC18: =SUMIFS('Forecast Data'!$D:$D,'Forecast Data'!$C:$C,AC$6,'Forecast Data'!$B:$B,$D18) -> 9703 | AD18: =SUMIFS('Forecast Data'!$D:$D,'Forecast Data'!$C:$C,AD$6,'Forecast Data'!$B:$B,$D18) -> 9976 | ... AH18: =SUMIFS('Forecast Data'!$D:$D,'Forecast Data'!$C:$C,AH$6,'Forecast Data'!$B:$B,$D18) -> 10486 | AJ18: =IF(SUMIFS('Forecast Data'!$E:$E,'Forecast Data'!$C:$C,AJ$6,'Forecast Data'!$B:$B,$D18)=0,"",SUMIFS('Forecast Data'!$E:$E,'Forecast Data'!$C:$C,AJ$6,'Forecast Data'!$B:$B,$D18)) | AK18: =IF(SUMIFS('Forecast Data'!$E:$E,'Forecast Data'!$C:$C,AK$6,'Forecast Data'!$B:$B,$D18)=0,"",SUMIFS('Forecast Data'!$E:$E,'Forecast Data'!$C:$C,AK$6,'Forecast Data'!$B:$B,$D18)) | AL18: =IF(SUMIFS('Forecast Data'!$E:$E,'Forecast Data'!$C:$C,AL$6,'Forecast Data'!$B:$B,$D18)=0,"",SUMIFS('Forecast Data'!$E:$E,'Forecast Data'!$C:$C,AL$6,'Forecast Data'!$B:$B,$D18)) | AM18: =IF(SUMIFS('Forecast Data'!$E:$E,'Forecast Data'!$C:$C,AM$6,'Forecast Data'!$B:$B,$D18)=0,"",SUMIFS('Forecast Data'!$E:$E,'Forecast Data'!$C:$C,AM$6,'Forecast Data'!$B:$B,$D18)) | AN18: =IF(SUMIFS('Forecast Data'!$E:$E,'Forecast Data'!$C:$C,AN$6,'Forecast Data'!$B:$B,$D18)=0,"",SUMIFS('Forecast Data'!$E:$E,'Forecast Data'!$C:$C,AN$6,'Forecast Data'!$B:$B,$D18)) | AO18: =IF(SUMIFS('Forecast Data'!$E:$E,'Forecast Data'!$C:$C,AO$6,'Forecast Data'!$B:$B,$D18)=0,"",SUMIFS('Forecast Data'!$E:$E,'Forecast Data'!$C:$C,AO$6,'Forecast Data'!$B:$B,$D18)) | AP18: =IF(SUMIFS('Forecast Data'!$E:$E,'Forecast Data'!$C:$C,AP$6,'Forecast Data'!$B:$B,$D18)=0,"",SUMIFS('Forecast Data'!$E:$E,'Forecast Data'!$C:$C,AP$6,'Forecast Data'!$B:$B,$D18)) | AQ18: =IF(SUMIFS('Forecast Data'!$E:$E,'Forecast Data'!$C:$C,AQ$6,'Forecast Data'!$B:$B,$D18)=0,"",SUMIFS('Forecast Data'!$E:$E,'Forecast Data'!$C:$C,AQ$6,'Forecast Data'!$B:$B,$D18)) | ... AU18: =IF(SUMIFS('Forecast Data'!$E:$E,'Forecast Data'!$C:$C,AU$6,'Forecast Data'!$B:$B,$D18)=0,"",SUMIFS('Forecast Data'!$E:$E,'Forecast Data'!$C:$C,AU$6,'Forecast Data'!$B:$B,$D18)) | AW18: =SUMIFS('OP Units'!E:E,'OP Units'!$A:$A,$D18) -> 4216 | AX18: =SUMIFS('OP Units'!F:F,'OP Units'!$A:$A,$D18) -> 4439 | AY18: =SUMIFS('OP Units'!G:G,'OP Units'!$A:$A,$D18) -> 5327 | AZ18: =SUMIFS('OP Units'!H:H,'OP Units'!$A:$A,$D18) -> 5570 | BA18: =SUMIFS('OP Units'!I:I,'OP Units'!$A:$A,$D18) -> 5656 | BB18: =SUMIFS('OP Units'!J:J,'OP Units'!$A:$A,$D18) -> 6013 | BC18: =SUMIFS('OP Units'!K:K,'OP Units'!$A:$A,$D18) -> 5595 | BD18: =SUMIFS('OP Units'!L:L,'OP Units'!$A:$A,$D18) -> 5476 | BE18: =SUMIFS('OP Units'!M:M,'OP Units'!$A:$A,$D18) -> 5542 | BF18: =SUMIFS('OP Units'!N:N,'OP Units'!$A:$A,$D18) -> 5898 | BG18: =SUMIFS('OP Units'!O:O,'OP Units'!$A:$A,$D18) -> 6166 | BH18: =SUMIFS('OP Units'!P:P,'OP Units'!$A:$A,$D18) -> 6279 | BJ18: =IFERROR((SUMIFS('OP Units'!E:E,'OP Units'!$A:$A,$D18)-SUMIFS('Forecast Data'!$H:$H,'Forecast Data'!$C:$C,BJ$6,'Forecast Data'!$B:$B,$D18))/SUMIFS('Forecast Data'!$H:$H,'Forecast Data'!$C:$C,BJ$6,'Forecast Data'!$B:$B,$D18),"") | BK18: =IFERROR((SUMIFS('OP Units'!F:F,'OP Units'!$A:$A,$D18)-SUMIFS('Forecast Data'!$H:$H,'Forecast Data'!$C:$C,BK$6,'Forecast Data'!$B:$B,$D18))/SUMIFS('Forecast Data'!$H:$H,'Forecast Data'!$C:$C,BK$6,'Forecast Data'!$B:$B,$D18),"") | BL18: =IFERROR((SUMIFS('OP Units'!G:G,'OP Units'!$A:$A,$D18)-SUMIFS('Forecast Data'!$H:$H,'Forecast Data'!$C:$C,BL$6,'Forecast Data'!$B:$B,$D18))/SUMIFS('Forecast Data'!$H:$H,'Forecast Data'!$C:$C,BL$6,'Forecast Data'!$B:$B,$D18),"") | BM18: =IFERROR((SUMIFS('OP Units'!H:H,'OP Units'!$A:$A,$D18)-SUMIFS('Forecast Data'!$H:$H,'Forecast Data'!$C:$C,BM$6,'Forecast Data'!$B:$B,$D18))/SUMIFS('Forecast Data'!$H:$H,'Forecast Data'!$C:$C,BM$6,'Forecast Data'!$B:$B,$D18),"") | BN18: =IFERROR((SUMIFS('OP Units'!I:I,'OP Units'!$A:$A,$D18)-SUMIFS('Forecast Data'!$H:$H,'Forecast Data'!$C:$C,BN$6,'Forecast Data'!$B:$B,$D18))/SUMIFS('Forecast Data'!$H:$H,'Forecast Data'!$C:$C,BN$6,'Forecast Data'!$B:$B,$D18),"") | BO18: =IFERROR((SUMIFS('OP Units'!J:J,'OP Units'!$A:$A,$D18)-SUMIFS('Forecast Data'!$H:$H,'Forecast Data'!$C:$C,BO$6,'Forecast Data'!$B:$B,$D18))/SUMIFS('Forecast Data'!$H:$H,'Forecast Data'!$C:$C,BO$6,'Forecast Data'!$B:$B,$D18),"") | BP18: =IFERROR((SUMIFS('OP Units'!K:K,'OP Units'!$A:$A,$D18)-SUMIFS('Forecast Data'!$H:$H,'Forecast Data'!$C:$C,BP$6,'Forecast Data'!$B:$B,$D18))/SUMIFS('Forecast Data'!$H:$H,'Forecast Data'!$C:$C,BP$6,'Forecast Data'!$B:$B,$D18),"") | BQ18: =IFERROR((SUMIFS('OP Units'!L:L,'OP Units'!$A:$A,$D18)-SUMIFS('Forecast Data'!$H:$H,'Forecast Data'!$C:$C,BQ$6,'Forecast Data'!$B:$B,$D18))/SUMIFS('Forecast Data'!$H:$H,'Forecast Data'!$C:$C,BQ$6,'Forecast Data'!$B:$B,$D18),"") | BR18: =IFERROR((SUMIFS('OP Units'!M:M,'OP Units'!$A:$A,$D18)-SUMIFS('Forecast Data'!$H:$H,'Forecast Data'!$C:$C,BR$6,'Forecast Data'!$B:$B,$D18))/SUMIFS('Forecast Data'!$H:$H,'Forecast Data'!$C:$C,BR$6,'Forecast Data'!$B:$B,$D18),"") | BS18: =IFERROR((SUMIFS('OP Units'!N:N,'OP Units'!$A:$A,$D18)-SUMIFS('Forecast Data'!$H:$H,'Forecast Data'!$C:$C,BS$6,'Forecast Data'!$B:$B,$D18))/SUMIFS('Forecast Data'!$H:$H,'Forecast Data'!$C:$C,BS$6,'Forecast Data'!$B:$B,$D18),"") | BT18: =IFERROR((SUMIFS('OP Units'!O:O,'OP Units'!$A:$A,$D18)-SUMIFS('Forecast Data'!$H:$H,'Forecast Data'!$C:$C,BT$6,'Forecast Data'!$B:$B,$D18))/SUMIFS('Forecast Data'!$H:$H,'Forecast Data'!$C:$C,BT$6,'Forecast Data'!$B:$B,$D18),"") | BU18: =IFERROR((SUMIFS('OP Units'!P:P,'OP Units'!$A:$A,$D18)-SUMIFS('Forecast Data'!$H:$H,'Forecast Data'!$C:$C,BU$6,'Forecast Data'!$B:$B,$D18))/SUMIFS('Forecast Data'!$H:$H,'Forecast Data'!$C:$C,BU$6,'Forecast Data'!$B:$B,$D18),"") | BW18: =(SUMIFS('Forecast Data'!H:H,'Forecast Data'!B:B,D18,'Forecast Data'!C:C,BK$6)+SUMIFS('Forecast Data'!H:H,'Forecast Data'!B:B,D18,'Forecast Data'!C:C,BL$6)+SUMIFS('Forecast Data'!H:H,'Forecast Data'!B:B,D18,'Forecast Data'!C:C,BM$6)+SUMIFS('Forecast Data'!H:H,'Forecast Data'!B:B,D18,'Forecast Data'!C:C,BN$6)+SUMIFS('Forecast Data'!H:H,'Forecast Data'!B:B,D18,'Forecast Data'!C:C,BO$6)+SUMIFS('Forecast Data'!H:H,'Forecast Data'!B:B,D18,'Forecast Data'!C:C,BP$6)+SUMIFS('Forecast Data'!H:H,'Forecast Data'!B:B,D18,'Forecast Data'!C:C,BQ$6)+SUMIFS('Forecast Data'!H:H,'Forecast Data'!B:B,D18,'Forecast Data'!C:C,BJ$6))/8 -> 0 | BX18: =IFERROR((SUM(W18:AD18)-(SUMIFS('Forecast Data'!H:H,'Forecast Data'!B:B,B18,'Forecast Data'!C:C,BJ$6)+SUMIFS('Forecast Data'!H:H,'Forecast Data'!B:B,B18,'Forecast Data'!C:C,BK$6)+SUMIFS('Forecast Data'!H:H,'Forecast Data'!B:B,B18,'Forecast Data'!C:C,BL$6)+SUMIFS('Forecast Data'!H:H,'Forecast Data'!B:B,B18,'Forecast Data'!C:C,BM$6)+SUMIFS('Forecast Data'!H:H,'Forecast Data'!B:B,B18,'Forecast Data'!C:C,BN$6)+SUMIFS('Forecast Data'!H:H,'Forecast Data'!B:B,B18,'Forecast Data'!C:C,BO$6)+SUMIFS('Forecast Data'!H:H,'Forecast Data'!B:B,B18,'Forecast Data'!C:C,BP$6)+SUMIFS('Forecast Data'!H:H,'Forecast Data'!B:B,B18,'Forecast Data'!C:C,BQ$6)))/(SUMIFS('Forecast Data'!H:H,'Forecast Data'!B:B,B18,'Forecast Data'!C:C,BJ$6)+SUMIFS('Forecast Data'!H:H,'Forecast Data'!B:B,B18,'Forecast Data'!C:C,BK$6)+SUMIFS('Forecast Data'!H:H,'Forecast Data'!B:B,B18,'Forecast Data'!C:C,BL$6)+SUMIFS('Forecast Data'!H:H,'Forecast Data'!B:B,B18,'Forecast Data'!C:C,BM$6)+SUMIFS('Forecast Data'!H:H,'Forecast Data'!B:B,B18,'Forecast Data'!C:C,BN$6)+SUMIFS('Forecast Data'!H:H,'Forecast Data'!B:B,B18,'Forecast Data'!C:C,BO$6)+SUMIFS('Forecast Data'!H:H,'Forecast Data'!B:B,B18,'Forecast Data'!C:C,BP$6)+SUMIFS('Forecast Data'!H:H,'Forecast Data'!B:B,B18,'Forecast Data'!C:C,BQ$6)),"") | BY18: =((L18-E18)/($L$4-$E$4))*$M$4 -> 0.0036497443 | BZ18: =((AVERAGE(W18:AD18)-BW18)/(AVERAGE($W$4:$AD$4)-$BW$4))*$BX$4 -> 0.0067487109 | CA18: =(BY18-BZ18)*100 -> -0.30989666 | CB18: =ABS(CA18)/100 -> 0.0030989666 | CD18: =(SUMIFS('Forecast Data'!H:H,'Forecast Data'!B:B,D18,'Forecast Data'!C:C,BK$6)+SUMIFS('Forecast Data'!H:H,'Forecast Data'!B:B,D18,'Forecast Data'!C:C,BL$6)+SUMIFS('Forecast Data'!H:H,'Forecast Data'!B:B,D18,'Forecast Data'!C:C,BM$6)+SUMIFS('Forecast Data'!H:H,'Forecast Data'!B:B,D18,'Forecast Data'!C:C,BJ$6))/4 -> 0 | CE18: =IFERROR((SUM(W18:Z18)-(SUMIFS('Forecast Data'!H:H,'Forecast Data'!B:B,D18,'Forecast Data'!C:C,BJ$6)+SUMIFS('Forecast Data'!H:H,'Forecast Data'!B:B,D18,'Forecast Data'!C:C,BK$6)+SUMIFS('Forecast Data'!H:H,'Forecast Data'!B:B,D18,'Forecast Data'!C:C,BL$6)+SUMIFS('Forecast Data'!H:H,'Forecast Data'!B:B,D18,'Forecast Data'!C:C,BM$6)))/(SUMIFS('Forecast Data'!H:H,'Forecast Data'!B:B,D18,'Forecast Data'!C:C,BJ$6)+SUMIFS('Forecast Data'!H:H,'Forecast Data'!B:B,D18,'Forecast Data'!C:C,BK$6)+SUMIFS('Forecast Data'!H:H,'Forecast Data'!B:B,D18,'Forecast Data'!C:C,BL$6)+SUMIFS('Forecast Data'!H:H,'Forecast Data'!B:B,D18,'Forecast Data'!C:C,BM$6)),"") | CF18: =(($L18-$E18)/($L$4-$E$4))*$M$4 -> 0.0036497443 | CG18: =((AVERAGE(W18:Z18)-CD18)/(AVERAGE($W$4:$Z$4)-$CD$4))*$CE$4 -> 0.006109946 | CH18: =(CF18-CG18)*100 -> -0.24602017
B19: =D19 -> Philips Norelco | D19: Philips Norelco | E19: =SUMIFS('Fin Data'!F:F,'Fin Data'!A:A,D19) -> 3236 | F19: =SUMIFS('Fin Data with 6 week hist'!I:I,'Fin Data with 6 week hist'!$A:$A,$D19) -> 1721 | G19: =SUMIFS('Fin Data with 6 week hist'!J:J,'Fin Data with 6 week hist'!$A:$A,$D19) -> 1513 | H19: =SUMIFS('Fin Data with 6 week hist'!K:K,'Fin Data with 6 week hist'!$A:$A,$D19)+SUMIFS('Unit Cancellations'!D:D,'Unit Cancellations'!$B:$B,$D19) -> 1232 | I19: =SUMIFS('Fin Data with 6 week hist'!L:L,'Fin Data with 6 week hist'!$A:$A,$D19)+SUMIFS('Unit Cancellations'!E:E,'Unit Cancellations'!$B:$B,$D19) -> 1339 | J19: =SUMIFS('Fin Data with 6 week hist'!M:M,'Fin Data with 6 week hist'!$A:$A,$D19)+SUMIFS('Unit Cancellations'!F:F,'Unit Cancellations'!$B:$B,$D19) -> 1420 | K19: =SUMIFS('Fin Data with 6 week hist'!N:N,'Fin Data with 6 week hist'!$A:$A,$D19)+SUMIFS('Unit Cancellations'!G:G,'Unit Cancellations'!$B:$B,$D19) -> 3297 | L19: =SUMIFS('Fin Data'!AN:AN,'Fin Data'!A:A,D19) -> 1754 | M19: =IFERROR(SUMIFS('Fin Data'!AO:AO,'Fin Data'!A:A,D19),"") -> -0.45797281 | O19: =AVERAGE(W19:Z19) -> 3492.25 | P19: =CE19 -> 1.1094835 | R19: =AVERAGE(W19:AD19) -> 3489.625 | S19: =BX19 -> 0.75832966 | T19: =AVERAGE(AW19:BD19) -> 0 | U19: =#REF! -> #REF! | W19: =SUMIFS('Forecast Data'!$D:$D,'Forecast Data'!$C:$C,W$6,'Forecast Data'!$B:$B,$D19) -> 3505 | X19: =SUMIFS('Forecast Data'!$D:$D,'Forecast Data'!$C:$C,X$6,'Forecast Data'!$B:$B,$D19) -> 3490 | Y19: =SUMIFS('Forecast Data'!$D:$D,'Forecast Data'!$C:$C,Y$6,'Forecast Data'!$B:$B,$D19) -> 3487 | Z19: =SUMIFS('Forecast Data'!$D:$D,'Forecast Data'!$C:$C,Z$6,'Forecast Data'!$B:$B,$D19) -> 3487 | AA19: =SUMIFS('Forecast Data'!$D:$D,'Forecast Data'!$C:$C,AA$6,'Forecast Data'!$B:$B,$D19) -> 3487 | AB19: =SUMIFS('Forecast Data'!$D:$D,'Forecast Data'!$C:$C,AB$6,'Forecast Data'!$B:$B,$D19) -> 3487 | AC19: =SUMIFS('Forecast Data'!$D:$D,'Forecast Data'!$C:$C,AC$6,'Forecast Data'!$B:$B,$D19) -> 3487 | AD19: =SUMIFS('Forecast Data'!$D:$D,'Forecast Data'!$C:$C,AD$6,'Forecast Data'!$B:$B,$D19) -> 3487 | ... AH19: =SUMIFS('Forecast Data'!$D:$D,'Forecast Data'!$C:$C,AH$6,'Forecast Data'!$B:$B,$D19) -> 3489 | AJ19: =IF(SUMIFS('Forecast Data'!$E:$E,'Forecast Data'!$C:$C,AJ$6,'Forecast Data'!$B:$B,$D19)=0,"",SUMIFS('Forecast Data'!$E:$E,'Forecast Data'!$C:$C,AJ$6,'Forecast Data'!$B:$B,$D19)) -> 0.7 | AK19: =IF(SUMIFS('Forecast Data'!$E:$E,'Forecast Data'!$C:$C,AK$6,'Forecast Data'!$B:$B,$D19)=0,"",SUMIFS('Forecast Data'!$E:$E,'Forecast Data'!$C:$C,AK$6,'Forecast Data'!$B:$B,$D19)) -> 0.9 | AL19: =IF(SUMIFS('Forecast Data'!$E:$E,'Forecast Data'!$C:$C,AL$6,'Forecast Data'!$B:$B,$D19)=0,"",SUMIFS('Forecast Data'!$E:$E,'Forecast Data'!$C:$C,AL$6,'Forecast Data'!$B:$B,$D19)) -> 2.14 | AM19: =IF(SUMIFS('Forecast Data'!$E:$E,'Forecast Data'!$C:$C,AM$6,'Forecast Data'!$B:$B,$D19)=0,"",SUMIFS('Forecast Data'!$E:$E,'Forecast Data'!$C:$C,AM$6,'Forecast Data'!$B:$B,$D19)) -> 1.16 | AN19: =IF(SUMIFS('Forecast Data'!$E:$E,'Forecast Data'!$C:$C,AN$6,'Forecast Data'!$B:$B,$D19)=0,"",SUMIFS('Forecast Data'!$E:$E,'Forecast Data'!$C:$C,AN$6,'Forecast Data'!$B:$B,$D19)) -> 0.86 | AO19: =IF(SUMIFS('Forecast Data'!$E:$E,'Forecast Data'!$C:$C,AO$6,'Forecast Data'!$B:$B,$D19)=0,"",SUMIFS('Forecast Data'!$E:$E,'Forecast Data'!$C:$C,AO$6,'Forecast Data'!$B:$B,$D19)) -> 0.28 | AP19: =IF(SUMIFS('Forecast Data'!$E:$E,'Forecast Data'!$C:$C,AP$6,'Forecast Data'!$B:$B,$D19)=0,"",SUMIFS('Forecast Data'!$E:$E,'Forecast Data'!$C:$C,AP$6,'Forecast Data'!$B:$B,$D19)) -> 0.53 | AQ19: =IF(SUMIFS('Forecast Data'!$E:$E,'Forecast Data'!$C:$C,AQ$6,'Forecast Data'!$B:$B,$D19)=0,"",SUMIFS('Forecast Data'!$E:$E,'Forecast Data'!$C:$C,AQ$6,'Forecast Data'!$B:$B,$D19)) -> 0.47 | ... AU19: =IF(SUMIFS('Forecast Data'!$E:$E,'Forecast Data'!$C:$C,AU$6,'Forecast Data'!$B:$B,$D19)=0,"",SUMIFS('Forecast Data'!$E:$E,'Forecast Data'!$C:$C,AU$6,'Forecast Data'!$B:$B,$D19)) -> 0.91 | AW19: =SUMIFS('OP Units'!E:E,'OP Units'!$A:$A,$D19) -> 0 | AX19: =SUMIFS('OP Units'!F:F,'OP Units'!$A:$A,$D19) -> 0 | AY19: =SUMIFS('OP Units'!G:G,'OP Units'!$A:$A,$D19) -> 0 | AZ19: =SUMIFS('OP Units'!H:H,'OP Units'!$A:$A,$D19) -> 0 | BA19: =SUMIFS('OP Units'!I:I,'OP Units'!$A:$A,$D19) -> 0 | BB19: =SUMIFS('OP Units'!J:J,'OP Units'!$A:$A,$D19) -> 0 | BC19: =SUMIFS('OP Units'!K:K,'OP Units'!$A:$A,$D19) -> 0 | BD19: =SUMIFS('OP Units'!L:L,'OP Units'!$A:$A,$D19) -> 0 | BE19: =SUMIFS('OP Units'!M:M,'OP Units'!$A:$A,$D19) -> 0 | BF19: =SUMIFS('OP Units'!N:N,'OP Units'!$A:$A,$D19) -> 0 | BG19: =SUMIFS('OP Units'!O:O,'OP Units'!$A:$A,$D19) -> 0 | BH19: =SUMIFS('OP Units'!P:P,'OP Units'!$A:$A,$D19) -> 0 | BJ19: =IFERROR((SUMIFS('OP Units'!E:E,'OP Units'!$A:$A,$D19)-SUMIFS('Forecast Data'!$H:$H,'Forecast Data'!$C:$C,BJ$6,'Forecast Data'!$B:$B,$D19))/SUMIFS('Forecast Data'!$H:$H,'Forecast Data'!$C:$C,BJ$6,'Forecast Data'!$B:$B,$D19),"") -> -1 | BK19: =IFERROR((SUMIFS('OP Units'!F:F,'OP Units'!$A:$A,$D19)-SUMIFS('Forecast Data'!$H:$H,'Forecast Data'!$C:$C,BK$6,'Forecast Data'!$B:$B,$D19))/SUMIFS('Forecast Data'!$H:$H,'Forecast Data'!$C:$C,BK$6,'Forecast Data'!$B:$B,$D19),"") -> -1 | BL19: =IFERROR((SUMIFS('OP Units'!G:G,'OP Units'!$A:$A,$D19)-SUMIFS('Forecast Data'!$H:$H,'Forecast Data'!$C:$C,BL$6,'Forecast Data'!$B:$B,$D19))/SUMIFS('Forecast Data'!$H:$H,'Forecast Data'!$C:$C,BL$6,'Forecast Data'!$B:$B,$D19),"") -> -1 | BM19: =IFERROR((SUMIFS('OP Units'!H:H,'OP Units'!$A:$A,$D19)-SUMIFS('Forecast Data'!$H:$H,'Forecast Data'!$C:$C,BM$6,'Forecast Data'!$B:$B,$D19))/SUMIFS('Forecast Data'!$H:$H,'Forecast Data'!$C:$C,BM$6,'Forecast Data'!$B:$B,$D19),"") -> -1 | BN19: =IFERROR((SUMIFS('OP Units'!I:I,'OP Units'!$A:$A,$D19)-SUMIFS('Forecast Data'!$H:$H,'Forecast Data'!$C:$C,BN$6,'Forecast Data'!$B:$B,$D19))/SUMIFS('Forecast Data'!$H:$H,'Forecast Data'!$C:$C,BN$6,'Forecast Data'!$B:$B,$D19),"") -> -1 | BO19: =IFERROR((SUMIFS('OP Units'!J:J,'OP Units'!$A:$A,$D19)-SUMIFS('Forecast Data'!$H:$H,'Forecast Data'!$C:$C,BO$6,'Forecast Data'!$B:$B,$D19))/SUMIFS('Forecast Data'!$H:$H,'Forecast Data'!$C:$C,BO$6,'Forecast Data'!$B:$B,$D19),"") -> -1 | BP19: =IFERROR((SUMIFS('OP Units'!K:K,'OP Units'!$A:$A,$D19)-SUMIFS('Forecast Data'!$H:$H,'Forecast Data'!$C:$C,BP$6,'Forecast Data'!$B:$B,$D19))/SUMIFS('Forecast Data'!$H:$H,'Forecast Data'!$C:$C,BP$6,'Forecast Data'!$B:$B,$D19),"") -> -1 | BQ19: =IFERROR((SUMIFS('OP Units'!L:L,'OP Units'!$A:$A,$D19)-SUMIFS('Forecast Data'!$H:$H,'Forecast Data'!$C:$C,BQ$6,'Forecast Data'!$B:$B,$D19))/SUMIFS('Forecast Data'!$H:$H,'Forecast Data'!$C:$C,BQ$6,'Forecast Data'!$B:$B,$D19),"") -> -1 | BR19: =IFERROR((SUMIFS('OP Units'!M:M,'OP Units'!$A:$A,$D19)-SUMIFS('Forecast Data'!$H:$H,'Forecast Data'!$C:$C,BR$6,'Forecast Data'!$B:$B,$D19))/SUMIFS('Forecast Data'!$H:$H,'Forecast Data'!$C:$C,BR$6,'Forecast Data'!$B:$B,$D19),"") -> -1 | BS19: =IFERROR((SUMIFS('OP Units'!N:N,'OP Units'!$A:$A,$D19)-SUMIFS('Forecast Data'!$H:$H,'Forecast Data'!$C:$C,BS$6,'Forecast Data'!$B:$B,$D19))/SUMIFS('Forecast Data'!$H:$H,'Forecast Data'!$C:$C,BS$6,'Forecast Data'!$B:$B,$D19),"") -> -1 | BT19: =IFERROR((SUMIFS('OP Units'!O:O,'OP Units'!$A:$A,$D19)-SUMIFS('Forecast Data'!$H:$H,'Forecast Data'!$C:$C,BT$6,'Forecast Data'!$B:$B,$D19))/SUMIFS('Forecast Data'!$H:$H,'Forecast Data'!$C:$C,BT$6,'Forecast Data'!$B:$B,$D19),"") -> -1 | BU19: =IFERROR((SUMIFS('OP Units'!P:P,'OP Units'!$A:$A,$D19)-SUMIFS('Forecast Data'!$H:$H,'Forecast Data'!$C:$C,BU$6,'Forecast Data'!$B:$B,$D19))/SUMIFS('Forecast Data'!$H:$H,'Forecast Data'!$C:$C,BU$6,'Forecast Data'!$B:$B,$D19),"") -> -1 | BW19: =(SUMIFS('Forecast Data'!H:H,'Forecast Data'!B:B,D19,'Forecast Data'!C:C,BK$6)+SUMIFS('Forecast Data'!H:H,'Forecast Data'!B:B,D19,'Forecast Data'!C:C,BL$6)+SUMIFS('Forecast Data'!H:H,'Forecast Data'!B:B,D19,'Forecast Data'!C:C,BM$6)+SUMIFS('Forecast Data'!H:H,'Forecast Data'!B:B,D19,'Forecast Data'!C:C,BN$6)+SUMIFS('Forecast Data'!H:H,'Forecast Data'!B:B,D19,'Forecast Data'!C:C,BO$6)+SUMIFS('Forecast Data'!H:H,'Forecast Data'!B:B,D19,'Forecast Data'!C:C,BP$6)+SUMIFS('Forecast Data'!H:H,'Forecast Data'!B:B,D19,'Forecast Data'!C:C,BQ$6)+SUMIFS('Forecast Data'!H:H,'Forecast Data'!B:B,D19,'Forecast Data'!C:C,BJ$6))/8 -> 1984.625 | BX19: =IFERROR((SUM(W19:AD19)-(SUMIFS('Forecast Data'!H:H,'Forecast Data'!B:B,B19,'Forecast Data'!C:C,BJ$6)+SUMIFS('Forecast Data'!H:H,'Forecast Data'!B:B,B19,'Forecast Data'!C:C,BK$6)+SUMIFS('Forecast Data'!H:H,'Forecast Data'!B:B,B19,'Forecast Data'!C:C,BL$6)+SUMIFS('Forecast Data'!H:H,'Forecast Data'!B:B,B19,'Forecast Data'!C:C,BM$6)+SUMIFS('Forecast Data'!H:H,'Forecast Data'!B:B,B19,'Forecast Data'!C:C,BN$6)+SUMIFS('Forecast Data'!H:H,'Forecast Data'!B:B,B19,'Forecast Data'!C:C,BO$6)+SUMIFS('Forecast Data'!H:H,'Forecast Data'!B:B,B19,'Forecast Data'!C:C,BP$6)+SUMIFS('Forecast Data'!H:H,'Forecast Data'!B:B,B19,'Forecast Data'!C:C,BQ$6)))/(SUMIFS('Forecast Data'!H:H,'Forecast Data'!B:B,B19,'Forecast Data'!C:C,BJ$6)+SUMIFS('Forecast Data'!H:H,'Forecast Data'!B:B,B19,'Forecast Data'!C:C,BK$6)+SUMIFS('Forecast Data'!H:H,'Forecast Data'!B:B,B19,'Forecast Data'!C:C,BL$6)+SUMIFS('Forecast Data'!H:H,'Forecast Data'!B:B,B19,'Forecast Data'!C:C,BM$6)+SUMIFS('Forecast Data'!H:H,'Forecast Data'!B:B,B19,'Forecast Data'!C:C,BN$6)+SUMIFS('Forecast Data'!H:H,'Forecast Data'!B:B,B19,'Forecast Data'!C:C,BO$6)+SUMIFS('Forecast Data'!H:H,'Forecast Data'!B:B,B19,'Forecast Data'!C:C,BP$6)+SUMIFS('Forecast Data'!H:H,'Forecast Data'!B:B,B19,'Forecast Data'!C:C,BQ$6)),"") -> 0.75832966 | BY19: =((L19-E19)/($L$4-$E$4))*$M$4 -> -0.0012673198 | BZ19: =((AVERAGE(W19:AD19)-BW19)/(AVERAGE($W$4:$AD$4)-$BW$4))*$BX$4 -> 0.00123756 | CA19: =(BY19-BZ19)*100 -> -0.25048799 | CB19: =ABS(CA19)/100 -> 0.0025048799 | CD19: =(SUMIFS('Forecast Data'!H:H,'Forecast Data'!B:B,D19,'Forecast Data'!C:C,BK$6)+SUMIFS('Forecast Data'!H:H,'Forecast Data'!B:B,D19,'Forecast Data'!C:C,BL$6)+SUMIFS('Forecast Data'!H:H,'Forecast Data'!B:B,D19,'Forecast Data'!C:C,BM$6)+SUMIFS('Forecast Data'!H:H,'Forecast Data'!B:B,D19,'Forecast Data'!C:C,BJ$6))/4 -> 1655.5 | CE19: =IFERROR((SUM(W19:Z19)-(SUMIFS('Forecast Data'!H:H,'Forecast Data'!B:B,D19,'Forecast Data'!C:C,BJ$6)+SUMIFS('Forecast Data'!H:H,'Forecast Data'!B:B,D19,'Forecast Data'!C:C,BK$6)+SUMIFS('Forecast Data'!H:H,'Forecast Data'!B:B,D19,'Forecast Data'!C:C,BL$6)+SUMIFS('Forecast Data'!H:H,'Forecast Data'!B:B,D19,'Forecast Data'!C:C,BM$6)))/(SUMIFS('Forecast Data'!H:H,'Forecast Data'!B:B,D19,'Forecast Data'!C:C,BJ$6)+SUMIFS('Forecast Data'!H:H,'Forecast Data'!B:B,D19,'Forecast Data'!C:C,BK$6)+SUMIFS('Forecast Data'!H:H,'Forecast Data'!B:B,D19,'Forecast Data'!C:C,BL$6)+SUMIFS('Forecast Data'!H:H,'Forecast Data'!B:B,D19,'Forecast Data'!C:C,BM$6)),"") -> 1.1094835 | CF19: =(($L19-$E19)/($L$4-$E$4))*$M$4 -> -0.0012673198 | CG19: =((AVERAGE(W19:Z19)-CD19)/(AVERAGE($W$4:$Z$4)-$CD$4))*$CE$4 -> 0.0015399051 | CH19: =(CF19-CG19)*100 -> -0.28072249
B20: =D20 -> Sorel | D20: Sorel | E20: =SUMIFS('Fin Data'!F:F,'Fin Data'!A:A,D20) -> 3101 | F20: =SUMIFS('Fin Data with 6 week hist'!I:I,'Fin Data with 6 week hist'!$A:$A,$D20) -> 1426 | G20: =SUMIFS('Fin Data with 6 week hist'!J:J,'Fin Data with 6 week hist'!$A:$A,$D20) -> 1244 | H20: =SUMIFS('Fin Data with 6 week hist'!K:K,'Fin Data with 6 week hist'!$A:$A,$D20)+SUMIFS('Unit Cancellations'!D:D,'Unit Cancellations'!$B:$B,$D20) -> 1350 | I20: =SUMIFS('Fin Data with 6 week hist'!L:L,'Fin Data with 6 week hist'!$A:$A,$D20)+SUMIFS('Unit Cancellations'!E:E,'Unit Cancellations'!$B:$B,$D20) -> 680 | J20: =SUMIFS('Fin Data with 6 week hist'!M:M,'Fin Data with 6 week hist'!$A:$A,$D20)+SUMIFS('Unit Cancellations'!F:F,'Unit Cancellations'!$B:$B,$D20) -> 569 | K20: =SUMIFS('Fin Data with 6 week hist'!N:N,'Fin Data with 6 week hist'!$A:$A,$D20)+SUMIFS('Unit Cancellations'!G:G,'Unit Cancellations'!$B:$B,$D20) -> 407 | L20: =SUMIFS('Fin Data'!AN:AN,'Fin Data'!A:A,D20) -> 946 | M20: =IFERROR(SUMIFS('Fin Data'!AO:AO,'Fin Data'!A:A,D20),"") -> -0.69493712 | O20: =AVERAGE(W20:Z20) -> 1572.25 | P20: =CE20 -> 0.20363636 | R20: =AVERAGE(W20:AD20) -> 1573.125 | S20: =BX20 -> 0.40160374 | T20: =AVERAGE(AW20:BD20) -> 0 | U20: =#REF! -> #REF! | W20: =SUMIFS('Forecast Data'!$D:$D,'Forecast Data'!$C:$C,W$6,'Forecast Data'!$B:$B,$D20) -> 1572 | X20: =SUMIFS('Forecast Data'!$D:$D,'Forecast Data'!$C:$C,X$6,'Forecast Data'!$B:$B,$D20) -> 1572 | Y20: =SUMIFS('Forecast Data'!$D:$D,'Forecast Data'!$C:$C,Y$6,'Forecast Data'!$B:$B,$D20) -> 1571 | Z20: =SUMIFS('Forecast Data'!$D:$D,'Forecast Data'!$C:$C,Z$6,'Forecast Data'!$B:$B,$D20) -> 1574 | AA20: =SUMIFS('Forecast Data'!$D:$D,'Forecast Data'!$C:$C,AA$6,'Forecast Data'!$B:$B,$D20) -> 1575 | AB20: =SUMIFS('Forecast Data'!$D:$D,'Forecast Data'!$C:$C,AB$6,'Forecast Data'!$B:$B,$D20) -> 1572 | AC20: =SUMIFS('Forecast Data'!$D:$D,'Forecast Data'!$C:$C,AC$6,'Forecast Data'!$B:$B,$D20) -> 1577 | AD20: =SUMIFS('Forecast Data'!$D:$D,'Forecast Data'!$C:$C,AD$6,'Forecast Data'!$B:$B,$D20) -> 1572 | ... AH20: =SUMIFS('Forecast Data'!$D:$D,'Forecast Data'!$C:$C,AH$6,'Forecast Data'!$B:$B,$D20) -> 1572 | AJ20: =IF(SUMIFS('Forecast Data'!$E:$E,'Forecast Data'!$C:$C,AJ$6,'Forecast Data'!$B:$B,$D20)=0,"",SUMIFS('Forecast Data'!$E:$E,'Forecast Data'!$C:$C,AJ$6,'Forecast Data'!$B:$B,$D20)) -> 0.01 | AK20: =IF(SUMIFS('Forecast Data'!$E:$E,'Forecast Data'!$C:$C,AK$6,'Forecast Data'!$B:$B,$D20)=0,"",SUMIFS('Forecast Data'!$E:$E,'Forecast Data'!$C:$C,AK$6,'Forecast Data'!$B:$B,$D20)) -> 0.1 | AL20: =IF(SUMIFS('Forecast Data'!$E:$E,'Forecast Data'!$C:$C,AL$6,'Forecast Data'!$B:$B,$D20)=0,"",SUMIFS('Forecast Data'!$E:$E,'Forecast Data'!$C:$C,AL$6,'Forecast Data'!$B:$B,$D20)) -> 0.3 | AM20: =IF(SUMIFS('Forecast Data'!$E:$E,'Forecast Data'!$C:$C,AM$6,'Forecast Data'!$B:$B,$D20)=0,"",SUMIFS('Forecast Data'!$E:$E,'Forecast Data'!$C:$C,AM$6,'Forecast Data'!$B:$B,$D20)) -> 0.53 | AN20: =IF(SUMIFS('Forecast Data'!$E:$E,'Forecast Data'!$C:$C,AN$6,'Forecast Data'!$B:$B,$D20)=0,"",SUMIFS('Forecast Data'!$E:$E,'Forecast Data'!$C:$C,AN$6,'Forecast Data'!$B:$B,$D20)) -> 0.66 | AO20: =IF(SUMIFS('Forecast Data'!$E:$E,'Forecast Data'!$C:$C,AO$6,'Forecast Data'!$B:$B,$D20)=0,"",SUMIFS('Forecast Data'!$E:$E,'Forecast Data'!$C:$C,AO$6,'Forecast Data'!$B:$B,$D20)) -> 0.68 | AP20: =IF(SUMIFS('Forecast Data'!$E:$E,'Forecast Data'!$C:$C,AP$6,'Forecast Data'!$B:$B,$D20)=0,"",SUMIFS('Forecast Data'!$E:$E,'Forecast Data'!$C:$C,AP$6,'Forecast Data'!$B:$B,$D20)) -> 0.62 | AQ20: =IF(SUMIFS('Forecast Data'!$E:$E,'Forecast Data'!$C:$C,AQ$6,'Forecast Data'!$B:$B,$D20)=0,"",SUMIFS('Forecast Data'!$E:$E,'Forecast Data'!$C:$C,AQ$6,'Forecast Data'!$B:$B,$D20)) -> 0.75 | ... AU20: =IF(SUMIFS('Forecast Data'!$E:$E,'Forecast Data'!$C:$C,AU$6,'Forecast Data'!$B:$B,$D20)=0,"",SUMIFS('Forecast Data'!$E:$E,'Forecast Data'!$C:$C,AU$6,'Forecast Data'!$B:$B,$D20)) -> 1.35 | AW20: =SUMIFS('OP Units'!E:E,'OP Units'!$A:$A,$D20) -> 0 | AX20: =SUMIFS('OP Units'!F:F,'OP Units'!$A:$A,$D20) -> 0 | AY20: =SUMIFS('OP Units'!G:G,'OP Units'!$A:$A,$D20) -> 0 | AZ20: =SUMIFS('OP Units'!H:H,'OP Units'!$A:$A,$D20) -> 0 | BA20: =SUMIFS('OP Units'!I:I,'OP Units'!$A:$A,$D20) -> 0 | BB20: =SUMIFS('OP Units'!J:J,'OP Units'!$A:$A,$D20) -> 0 | BC20: =SUMIFS('OP Units'!K:K,'OP Units'!$A:$A,$D20) -> 0 | BD20: =SUMIFS('OP Units'!L:L,'OP Units'!$A:$A,$D20) -> 0 | BE20: =SUMIFS('OP Units'!M:M,'OP Units'!$A:$A,$D20) -> 0 | BF20: =SUMIFS('OP Units'!N:N,'OP Units'!$A:$A,$D20) -> 0 | BG20: =SUMIFS('OP Units'!O:O,'OP Units'!$A:$A,$D20) -> 0 | BH20: =SUMIFS('OP Units'!P:P,'OP Units'!$A:$A,$D20) -> 0 | BJ20: =IFERROR((SUMIFS('OP Units'!E:E,'OP Units'!$A:$A,$D20)-SUMIFS('Forecast Data'!$H:$H,'Forecast Data'!$C:$C,BJ$6,'Forecast Data'!$B:$B,$D20))/SUMIFS('Forecast Data'!$H:$H,'Forecast Data'!$C:$C,BJ$6,'Forecast Data'!$B:$B,$D20),"") -> -1 | BK20: =IFERROR((SUMIFS('OP Units'!F:F,'OP Units'!$A:$A,$D20)-SUMIFS('Forecast Data'!$H:$H,'Forecast Data'!$C:$C,BK$6,'Forecast Data'!$B:$B,$D20))/SUMIFS('Forecast Data'!$H:$H,'Forecast Data'!$C:$C,BK$6,'Forecast Data'!$B:$B,$D20),"") -> -1 | BL20: =IFERROR((SUMIFS('OP Units'!G:G,'OP Units'!$A:$A,$D20)-SUMIFS('Forecast Data'!$H:$H,'Forecast Data'!$C:$C,BL$6,'Forecast Data'!$B:$B,$D20))/SUMIFS('Forecast Data'!$H:$H,'Forecast Data'!$C:$C,BL$6,'Forecast Data'!$B:$B,$D20),"") -> -1 | BM20: =IFERROR((SUMIFS('OP Units'!H:H,'OP Units'!$A:$A,$D20)-SUMIFS('Forecast Data'!$H:$H,'Forecast Data'!$C:$C,BM$6,'Forecast Data'!$B:$B,$D20))/SUMIFS('Forecast Data'!$H:$H,'Forecast Data'!$C:$C,BM$6,'Forecast Data'!$B:$B,$D20),"") -> -1 | BN20: =IFERROR((SUMIFS('OP Units'!I:I,'OP Units'!$A:$A,$D20)-SUMIFS('Forecast Data'!$H:$H,'Forecast Data'!$C:$C,BN$6,'Forecast Data'!$B:$B,$D20))/SUMIFS('Forecast Data'!$H:$H,'Forecast Data'!$C:$C,BN$6,'Forecast Data'!$B:$B,$D20),"") -> -1 | BO20: =IFERROR((SUMIFS('OP Units'!J:J,'OP Units'!$A:$A,$D20)-SUMIFS('Forecast Data'!$H:$H,'Forecast Data'!$C:$C,BO$6,'Forecast Data'!$B:$B,$D20))/SUMIFS('Forecast Data'!$H:$H,'Forecast Data'!$C:$C,BO$6,'Forecast Data'!$B:$B,$D20),"") -> -1 | BP20: =IFERROR((SUMIFS('OP Units'!K:K,'OP Units'!$A:$A,$D20)-SUMIFS('Forecast Data'!$H:$H,'Forecast Data'!$C:$C,BP$6,'Forecast Data'!$B:$B,$D20))/SUMIFS('Forecast Data'!$H:$H,'Forecast Data'!$C:$C,BP$6,'Forecast Data'!$B:$B,$D20),"") -> -1 | BQ20: =IFERROR((SUMIFS('OP Units'!L:L,'OP Units'!$A:$A,$D20)-SUMIFS('Forecast Data'!$H:$H,'Forecast Data'!$C:$C,BQ$6,'Forecast Data'!$B:$B,$D20))/SUMIFS('Forecast Data'!$H:$H,'Forecast Data'!$C:$C,BQ$6,'Forecast Data'!$B:$B,$D20),"") -> -1 | BR20: =IFERROR((SUMIFS('OP Units'!M:M,'OP Units'!$A:$A,$D20)-SUMIFS('Forecast Data'!$H:$H,'Forecast Data'!$C:$C,BR$6,'Forecast Data'!$B:$B,$D20))/SUMIFS('Forecast Data'!$H:$H,'Forecast Data'!$C:$C,BR$6,'Forecast Data'!$B:$B,$D20),"") -> -1 | BS20: =IFERROR((SUMIFS('OP Units'!N:N,'OP Units'!$A:$A,$D20)-SUMIFS('Forecast Data'!$H:$H,'Forecast Data'!$C:$C,BS$6,'Forecast Data'!$B:$B,$D20))/SUMIFS('Forecast Data'!$H:$H,'Forecast Data'!$C:$C,BS$6,'Forecast Data'!$B:$B,$D20),"") -> -1 | BT20: =IFERROR((SUMIFS('OP Units'!O:O,'OP Units'!$A:$A,$D20)-SUMIFS('Forecast Data'!$H:$H,'Forecast Data'!$C:$C,BT$6,'Forecast Data'!$B:$B,$D20))/SUMIFS('Forecast Data'!$H:$H,'Forecast Data'!$C:$C,BT$6,'Forecast Data'!$B:$B,$D20),"") -> -1 | BU20: =IFERROR((SUMIFS('OP Units'!P:P,'OP Units'!$A:$A,$D20)-SUMIFS('Forecast Data'!$H:$H,'Forecast Data'!$C:$C,BU$6,'Forecast Data'!$B:$B,$D20))/SUMIFS('Forecast Data'!$H:$H,'Forecast Data'!$C:$C,BU$6,'Forecast Data'!$B:$B,$D20),"") -> -1 | BW20: =(SUMIFS('Forecast Data'!H:H,'Forecast Data'!B:B,D20,'Forecast Data'!C:C,BK$6)+SUMIFS('Forecast Data'!H:H,'Forecast Data'!B:B,D20,'Forecast Data'!C:C,BL$6)+SUMIFS('Forecast Data'!H:H,'Forecast Data'!B:B,D20,'Forecast Data'!C:C,BM$6)+SUMIFS('Forecast Data'!H:H,'Forecast Data'!B:B,D20,'Forecast Data'!C:C,BN$6)+SUMIFS('Forecast Data'!H:H,'Forecast Data'!B:B,D20,'Forecast Data'!C:C,BO$6)+SUMIFS('Forecast Data'!H:H,'Forecast Data'!B:B,D20,'Forecast Data'!C:C,BP$6)+SUMIFS('Forecast Data'!H:H,'Forecast Data'!B:B,D20,'Forecast Data'!C:C,BQ$6)+SUMIFS('Forecast Data'!H:H,'Forecast Data'!B:B,D20,'Forecast Data'!C:C,BJ$6))/8 -> 1122.375 | BX20: =IFERROR((SUM(W20:AD20)-(SUMIFS('Forecast Data'!H:H,'Forecast Data'!B:B,B20,'Forecast Data'!C:C,BJ$6)+SUMIFS('Forecast Data'!H:H,'Forecast Data'!B:B,B20,'Forecast Data'!C:C,BK$6)+SUMIFS('Forecast Data'!H:H,'Forecast Data'!B:B,B20,'Forecast Data'!C:C,BL$6)+SUMIFS('Forecast Data'!H:H,'Forecast Data'!B:B,B20,'Forecast Data'!C:C,BM$6)+SUMIFS('Forecast Data'!H:H,'Forecast Data'!B:B,B20,'Forecast Data'!C:C,BN$6)+SUMIFS('Forecast Data'!H:H,'Forecast Data'!B:B,B20,'Forecast Data'!C:C,BO$6)+SUMIFS('Forecast Data'!H:H,'Forecast Data'!B:B,B20,'Forecast Data'!C:C,BP$6)+SUMIFS('Forecast Data'!H:H,'Forecast Data'!B:B,B20,'Forecast Data'!C:C,BQ$6)))/(SUMIFS('Forecast Data'!H:H,'Forecast Data'!B:B,B20,'Forecast Data'!C:C,BJ$6)+SUMIFS('Forecast Data'!H:H,'Forecast Data'!B:B,B20,'Forecast Data'!C:C,BK$6)+SUMIFS('Forecast Data'!H:H,'Forecast Data'!B:B,B20,'Forecast Data'!C:C,BL$6)+SUMIFS('Forecast Data'!H:H,'Forecast Data'!B:B,B20,'Forecast Data'!C:C,BM$6)+SUMIFS('Forecast Data'!H:H,'Forecast Data'!B:B,B20,'Forecast Data'!C:C,BN$6)+SUMIFS('Forecast Data'!H:H,'Forecast Data'!B:B,B20,'Forecast Data'!C:C,BO$6)+SUMIFS('Forecast Data'!H:H,'Forecast Data'!B:B,B20,'Forecast Data'!C:C,BP$6)+SUMIFS('Forecast Data'!H:H,'Forecast Data'!B:B,B20,'Forecast Data'!C:C,BQ$6)),"") -> 0.40160374 | BY20: =((L20-E20)/($L$4-$E$4))*$M$4 -> -0.0018428301 | BZ20: =((AVERAGE(W20:AD20)-BW20)/(AVERAGE($W$4:$AD$4)-$BW$4))*$BX$4 -> 0.00037065129 | CA20: =(BY20-BZ20)*100 -> -0.22134814 | CB20: =ABS(CA20)/100 -> 0.0022134814 | CD20: =(SUMIFS('Forecast Data'!H:H,'Forecast Data'!B:B,D20,'Forecast Data'!C:C,BK$6)+SUMIFS('Forecast Data'!H:H,'Forecast Data'!B:B,D20,'Forecast Data'!C:C,BL$6)+SUMIFS('Forecast Data'!H:H,'Forecast Data'!B:B,D20,'Forecast Data'!C:C,BM$6)+SUMIFS('Forecast Data'!H:H,'Forecast Data'!B:B,D20,'Forecast Data'!C:C,BJ$6))/4 -> 1306.25 | CE20: =IFERROR((SUM(W20:Z20)-(SUMIFS('Forecast Data'!H:H,'Forecast Data'!B:B,D20,'Forecast Data'!C:C,BJ$6)+SUMIFS('Forecast Data'!H:H,'Forecast Data'!B:B,D20,'Forecast Data'!C:C,BK$6)+SUMIFS('Forecast Data'!H:H,'Forecast Data'!B:B,D20,'Forecast Data'!C:C,BL$6)+SUMIFS('Forecast Data'!H:H,'Forecast Data'!B:B,D20,'Forecast Data'!C:C,BM$6)))/(SUMIFS('Forecast Data'!H:H,'Forecast Data'!B:B,D20,'Forecast Data'!C:C,BJ$6)+SUMIFS('Forecast Data'!H:H,'Forecast Data'!B:B,D20,'Forecast Data'!C:C,BK$6)+SUMIFS('Forecast Data'!H:H,'Forecast Data'!B:B,D20,'Forecast Data'!C:C,BL$6)+SUMIFS('Forecast Data'!H:H,'Forecast Data'!B:B,D20,'Forecast Data'!C:C,BM$6)),"") -> 0.20363636 | CF20: =(($L20-$E20)/($L$4-$E$4))*$M$4 -> -0.0018428301 | CG20: =((AVERAGE(W20:Z20)-CD20)/(AVERAGE($W$4:$Z$4)-$CD$4))*$CE$4 -> 0.00022301062 | CH20: =(CF20-CG20)*100 -> -0.20658407
D21: GNC | E21: =SUMIFS('Fin Data'!F:F,'Fin Data'!A:A,D21) -> 0 | F21: =SUMIFS('Fin Data with 6 week hist'!I:I,'Fin Data with 6 week hist'!$A:$A,$D21) -> 22008 | G21: =SUMIFS('Fin Data with 6 week hist'!J:J,'Fin Data with 6 week hist'!$A:$A,$D21) -> 23475 | H21: =SUMIFS('Fin Data with 6 week hist'!K:K,'Fin Data with 6 week hist'!$A:$A,$D21)+SUMIFS('Unit Cancellations'!D:D,'Unit Cancellations'!$B:$B,$D21) -> 24670 | I21: =SUMIFS('Fin Data with 6 week hist'!L:L,'Fin Data with 6 week hist'!$A:$A,$D21)+SUMIFS('Unit Cancellations'!E:E,'Unit Cancellations'!$B:$B,$D21) -> 26861 | J21: =SUMIFS('Fin Data with 6 week hist'!M:M,'Fin Data with 6 week hist'!$A:$A,$D21)+SUMIFS('Unit Cancellations'!F:F,'Unit Cancellations'!$B:$B,$D21) -> 27147 | K21: =SUMIFS('Fin Data with 6 week hist'!N:N,'Fin Data with 6 week hist'!$A:$A,$D21)+SUMIFS('Unit Cancellations'!G:G,'Unit Cancellations'!$B:$B,$D21) -> 27931 | L21: =SUMIFS('Fin Data'!AN:AN,'Fin Data'!A:A,D21) -> 25349 | M21: =IFERROR(SUMIFS('Fin Data'!AO:AO,'Fin Data'!A:A,D21),"") -> 0 | O21: =AVERAGE(W21:Z21) -> 26501.75 | P21: =CE21 | R21: =AVERAGE(W21:AD21) -> 25898.625 | S21: =BX21 | T21: =AVERAGE(AW21:BD21) -> 0 | U21: =#REF! -> #REF! | W21: =SUMIFS('Forecast Data'!$D:$D,'Forecast Data'!$C:$C,W$6,'Forecast Data'!$B:$B,$D21) -> 27141 | X21: =SUMIFS('Forecast Data'!$D:$D,'Forecast Data'!$C:$C,X$6,'Forecast Data'!$B:$B,$D21) -> 26708 | Y21: =SUMIFS('Forecast Data'!$D:$D,'Forecast Data'!$C:$C,Y$6,'Forecast Data'!$B:$B,$D21) -> 26559 | Z21: =SUMIFS('Forecast Data'!$D:$D,'Forecast Data'!$C:$C,Z$6,'Forecast Data'!$B:$B,$D21) -> 25599 | AA21: =SUMIFS('Forecast Data'!$D:$D,'Forecast Data'!$C:$C,AA$6,'Forecast Data'!$B:$B,$D21) -> 25311 | AB21: =SUMIFS('Forecast Data'!$D:$D,'Forecast Data'!$C:$C,AB$6,'Forecast Data'!$B:$B,$D21) -> 25328 | AC21: =SUMIFS('Forecast Data'!$D:$D,'Forecast Data'!$C:$C,AC$6,'Forecast Data'!$B:$B,$D21) -> 25289 | AD21: =SUMIFS('Forecast Data'!$D:$D,'Forecast Data'!$C:$C,AD$6,'Forecast Data'!$B:$B,$D21) -> 25254 | ... AH21: =SUMIFS('Forecast Data'!$D:$D,'Forecast Data'!$C:$C,AH$6,'Forecast Data'!$B:$B,$D21) -> 25184 | AJ21: =IF(SUMIFS('Forecast Data'!$E:$E,'Forecast Data'!$C:$C,AJ$6,'Forecast Data'!$B:$B,$D21)=0,"",SUMIFS('Forecast Data'!$E:$E,'Forecast Data'!$C:$C,AJ$6,'Forecast Data'!$B:$B,$D21)) | AK21: =IF(SUMIFS('Forecast Data'!$E:$E,'Forecast Data'!$C:$C,AK$6,'Forecast Data'!$B:$B,$D21)=0,"",SUMIFS('Forecast Data'!$E:$E,'Forecast Data'!$C:$C,AK$6,'Forecast Data'!$B:$B,$D21)) | AL21: =IF(SUMIFS('Forecast Data'!$E:$E,'Forecast Data'!$C:$C,AL$6,'Forecast Data'!$B:$B,$D21)=0,"",SUMIFS('Forecast Data'!$E:$E,'Forecast Data'!$C:$C,AL$6,'Forecast Data'!$B:$B,$D21)) | AM21: =IF(SUMIFS('Forecast Data'!$E:$E,'Forecast Data'!$C:$C,AM$6,'Forecast Data'!$B:$B,$D21)=0,"",SUMIFS('Forecast Data'!$E:$E,'Forecast Data'!$C:$C,AM$6,'Forecast Data'!$B:$B,$D21)) | AN21: =IF(SUMIFS('Forecast Data'!$E:$E,'Forecast Data'!$C:$C,AN$6,'Forecast Data'!$B:$B,$D21)=0,"",SUMIFS('Forecast Data'!$E:$E,'Forecast Data'!$C:$C,AN$6,'Forecast Data'!$B:$B,$D21)) | AO21: =IF(SUMIFS('Forecast Data'!$E:$E,'Forecast Data'!$C:$C,AO$6,'Forecast Data'!$B:$B,$D21)=0,"",SUMIFS('Forecast Data'!$E:$E,'Forecast Data'!$C:$C,AO$6,'Forecast Data'!$B:$B,$D21)) | AP21: =IF(SUMIFS('Forecast Data'!$E:$E,'Forecast Data'!$C:$C,AP$6,'Forecast Data'!$B:$B,$D21)=0,"",SUMIFS('Forecast Data'!$E:$E,'Forecast Data'!$C:$C,AP$6,'Forecast Data'!$B:$B,$D21)) | AQ21: =IF(SUMIFS('Forecast Data'!$E:$E,'Forecast Data'!$C:$C,AQ$6,'Forecast Data'!$B:$B,$D21)=0,"",SUMIFS('Forecast Data'!$E:$E,'Forecast Data'!$C:$C,AQ$6,'Forecast Data'!$B:$B,$D21)) | ... AU21: =IF(SUMIFS('Forecast Data'!$E:$E,'Forecast Data'!$C:$C,AU$6,'Forecast Data'!$B:$B,$D21)=0,"",SUMIFS('Forecast Data'!$E:$E,'Forecast Data'!$C:$C,AU$6,'Forecast Data'!$B:$B,$D21)) | AW21: =SUMIFS('OP Units'!E:E,'OP Units'!$A:$A,$D21) -> 0 | AX21: =SUMIFS('OP Units'!F:F,'OP Units'!$A:$A,$D21) -> 0 | AY21: =SUMIFS('OP Units'!G:G,'OP Units'!$A:$A,$D21) -> 0 | AZ21: =SUMIFS('OP Units'!H:H,'OP Units'!$A:$A,$D21) -> 0 | BA21: =SUMIFS('OP Units'!I:I,'OP Units'!$A:$A,$D21) -> 0 | BB21: =SUMIFS('OP Units'!J:J,'OP Units'!$A:$A,$D21) -> 0 | BC21: =SUMIFS('OP Units'!K:K,'OP Units'!$A:$A,$D21) -> 0 | BD21: =SUMIFS('OP Units'!L:L,'OP Units'!$A:$A,$D21) -> 0 | BE21: =SUMIFS('OP Units'!M:M,'OP Units'!$A:$A,$D21) -> 0 | BF21: =SUMIFS('OP Units'!N:N,'OP Units'!$A:$A,$D21) -> 0 | BG21: =SUMIFS('OP Units'!O:O,'OP Units'!$A:$A,$D21) -> 0 | BH21: =SUMIFS('OP Units'!P:P,'OP Units'!$A:$A,$D21) -> 0 | BJ21: =IFERROR((SUMIFS('OP Units'!E:E,'OP Units'!$A:$A,$D21)-SUMIFS('Forecast Data'!$H:$H,'Forecast Data'!$C:$C,BJ$6,'Forecast Data'!$B:$B,$D21))/SUMIFS('Forecast Data'!$H:$H,'Forecast Data'!$C:$C,BJ$6,'Forecast Data'!$B:$B,$D21),"") | BK21: =IFERROR((SUMIFS('OP Units'!F:F,'OP Units'!$A:$A,$D21)-SUMIFS('Forecast Data'!$H:$H,'Forecast Data'!$C:$C,BK$6,'Forecast Data'!$B:$B,$D21))/SUMIFS('Forecast Data'!$H:$H,'Forecast Data'!$C:$C,BK$6,'Forecast Data'!$B:$B,$D21),"") | BL21: =IFERROR((SUMIFS('OP Units'!G:G,'OP Units'!$A:$A,$D21)-SUMIFS('Forecast Data'!$H:$H,'Forecast Data'!$C:$C,BL$6,'Forecast Data'!$B:$B,$D21))/SUMIFS('Forecast Data'!$H:$H,'Forecast Data'!$C:$C,BL$6,'Forecast Data'!$B:$B,$D21),"") | BM21: =IFERROR((SUMIFS('OP Units'!H:H,'OP Units'!$A:$A,$D21)-SUMIFS('Forecast Data'!$H:$H,'Forecast Data'!$C:$C,BM$6,'Forecast Data'!$B:$B,$D21))/SUMIFS('Forecast Data'!$H:$H,'Forecast Data'!$C:$C,BM$6,'Forecast Data'!$B:$B,$D21),"") | BN21: =IFERROR((SUMIFS('OP Units'!I:I,'OP Units'!$A:$A,$D21)-SUMIFS('Forecast Data'!$H:$H,'Forecast Data'!$C:$C,BN$6,'Forecast Data'!$B:$B,$D21))/SUMIFS('Forecast Data'!$H:$H,'Forecast Data'!$C:$C,BN$6,'Forecast Data'!$B:$B,$D21),"") | BO21: =IFERROR((SUMIFS('OP Units'!J:J,'OP Units'!$A:$A,$D21)-SUMIFS('Forecast Data'!$H:$H,'Forecast Data'!$C:$C,BO$6,'Forecast Data'!$B:$B,$D21))/SUMIFS('Forecast Data'!$H:$H,'Forecast Data'!$C:$C,BO$6,'Forecast Data'!$B:$B,$D21),"") | BP21: =IFERROR((SUMIFS('OP Units'!K:K,'OP Units'!$A:$A,$D21)-SUMIFS('Forecast Data'!$H:$H,'Forecast Data'!$C:$C,BP$6,'Forecast Data'!$B:$B,$D21))/SUMIFS('Forecast Data'!$H:$H,'Forecast Data'!$C:$C,BP$6,'Forecast Data'!$B:$B,$D21),"") | BQ21: =IFERROR((SUMIFS('OP Units'!L:L,'OP Units'!$A:$A,$D21)-SUMIFS('Forecast Data'!$H:$H,'Forecast Data'!$C:$C,BQ$6,'Forecast Data'!$B:$B,$D21))/SUMIFS('Forecast Data'!$H:$H,'Forecast Data'!$C:$C,BQ$6,'Forecast Data'!$B:$B,$D21),"") | BR21: =IFERROR((SUMIFS('OP Units'!M:M,'OP Units'!$A:$A,$D21)-SUMIFS('Forecast Data'!$H:$H,'Forecast Data'!$C:$C,BR$6,'Forecast Data'!$B:$B,$D21))/SUMIFS('Forecast Data'!$H:$H,'Forecast Data'!$C:$C,BR$6,'Forecast Data'!$B:$B,$D21),"") | BS21: =IFERROR((SUMIFS('OP Units'!N:N,'OP Units'!$A:$A,$D21)-SUMIFS('Forecast Data'!$H:$H,'Forecast Data'!$C:$C,BS$6,'Forecast Data'!$B:$B,$D21))/SUMIFS('Forecast Data'!$H:$H,'Forecast Data'!$C:$C,BS$6,'Forecast Data'!$B:$B,$D21),"") | BT21: =IFERROR((SUMIFS('OP Units'!O:O,'OP Units'!$A:$A,$D21)-SUMIFS('Forecast Data'!$H:$H,'Forecast Data'!$C:$C,BT$6,'Forecast Data'!$B:$B,$D21))/SUMIFS('Forecast Data'!$H:$H,'Forecast Data'!$C:$C,BT$6,'Forecast Data'!$B:$B,$D21),"") | BU21: =IFERROR((SUMIFS('OP Units'!P:P,'OP Units'!$A:$A,$D21)-SUMIFS('Forecast Data'!$H:$H,'Forecast Data'!$C:$C,BU$6,'Forecast Data'!$B:$B,$D21))/SUMIFS('Forecast Data'!$H:$H,'Forecast Data'!$C:$C,BU$6,'Forecast Data'!$B:$B,$D21),"") | BW21: =(SUMIFS('Forecast Data'!H:H,'Forecast Data'!B:B,D21,'Forecast Data'!C:C,BK$6)+SUMIFS('Forecast Data'!H:H,'Forecast Data'!B:B,D21,'Forecast Data'!C:C,BL$6)+SUMIFS('Forecast Data'!H:H,'Forecast Data'!B:B,D21,'Forecast Data'!C:C,BM$6)+SUMIFS('Forecast Data'!H:H,'Forecast Data'!B:B,D21,'Forecast Data'!C:C,BN$6)+SUMIFS('Forecast Data'!H:H,'Forecast Data'!B:B,D21,'Forecast Data'!C:C,BO$6)+SUMIFS('Forecast Data'!H:H,'Forecast Data'!B:B,D21,'Forecast Data'!C:C,BP$6)+SUMIFS('Forecast Data'!H:H,'Forecast Data'!B:B,D21,'Forecast Data'!C:C,BQ$6)+SUMIFS('Forecast Data'!H:H,'Forecast Data'!B:B,D21,'Forecast Data'!C:C,BJ$6))/8 -> 0 | BX21: =IFERROR((SUM(W21:AD21)-(SUMIFS('Forecast Data'!H:H,'Forecast Data'!B:B,B21,'Forecast Data'!C:C,BJ$6)+SUMIFS('Forecast Data'!H:H,'Forecast Data'!B:B,B21,'Forecast Data'!C:C,BK$6)+SUMIFS('Forecast Data'!H:H,'Forecast Data'!B:B,B21,'Forecast Data'!C:C,BL$6)+SUMIFS('Forecast Data'!H:H,'Forecast Data'!B:B,B21,'Forecast Data'!C:C,BM$6)+SUMIFS('Forecast Data'!H:H,'Forecast Data'!B:B,B21,'Forecast Data'!C:C,BN$6)+SUMIFS('Forecast Data'!H:H,'Forecast Data'!B:B,B21,'Forecast Data'!C:C,BO$6)+SUMIFS('Forecast Data'!H:H,'Forecast Data'!B:B,B21,'Forecast Data'!C:C,BP$6)+SUMIFS('Forecast Data'!H:H,'Forecast Data'!B:B,B21,'Forecast Data'!C:C,BQ$6)))/(SUMIFS('Forecast Data'!H:H,'Forecast Data'!B:B,B21,'Forecast Data'!C:C,BJ$6)+SUMIFS('Forecast Data'!H:H,'Forecast Data'!B:B,B21,'Forecast Data'!C:C,BK$6)+SUMIFS('Forecast Data'!H:H,'Forecast Data'!B:B,B21,'Forecast Data'!C:C,BL$6)+SUMIFS('Forecast Data'!H:H,'Forecast Data'!B:B,B21,'Forecast Data'!C:C,BM$6)+SUMIFS('Forecast Data'!H:H,'Forecast Data'!B:B,B21,'Forecast Data'!C:C,BN$6)+SUMIFS('Forecast Data'!H:H,'Forecast Data'!B:B,B21,'Forecast Data'!C:C,BO$6)+SUMIFS('Forecast Data'!H:H,'Forecast Data'!B:B,B21,'Forecast Data'!C:C,BP$6)+SUMIFS('Forecast Data'!H:H,'Forecast Data'!B:B,B21,'Forecast Data'!C:C,BQ$6)),"") | BY21: =((L21-E21)/($L$4-$E$4))*$M$4 -> 0.021676984 | BZ21: =((AVERAGE(W21:AD21)-BW21)/(AVERAGE($W$4:$AD$4)-$BW$4))*$BX$4 -> 0.021296414 | CA21: =(BY21-BZ21)*100 -> 0.038056988 | CB21: =ABS(CA21)/100 -> 0.00038056988 | CD21: =(SUMIFS('Forecast Data'!H:H,'Forecast Data'!B:B,D21,'Forecast Data'!C:C,BK$6)+SUMIFS('Forecast Data'!H:H,'Forecast Data'!B:B,D21,'Forecast Data'!C:C,BL$6)+SUMIFS('Forecast Data'!H:H,'Forecast Data'!B:B,D21,'Forecast Data'!C:C,BM$6)+SUMIFS('Forecast Data'!H:H,'Forecast Data'!B:B,D21,'Forecast Data'!C:C,BJ$6))/4 -> 0 | CE21: =IFERROR((SUM(W21:Z21)-(SUMIFS('Forecast Data'!H:H,'Forecast Data'!B:B,D21,'Forecast Data'!C:C,BJ$6)+SUMIFS('Forecast Data'!H:H,'Forecast Data'!B:B,D21,'Forecast Data'!C:C,BK$6)+SUMIFS('Forecast Data'!H:H,'Forecast Data'!B:B,D21,'Forecast Data'!C:C,BL$6)+SUMIFS('Forecast Data'!H:H,'Forecast Data'!B:B,D21,'Forecast Data'!C:C,BM$6)))/(SUMIFS('Forecast Data'!H:H,'Forecast Data'!B:B,D21,'Forecast Data'!C:C,BJ$6)+SUMIFS('Forecast Data'!H:H,'Forecast Data'!B:B,D21,'Forecast Data'!C:C,BK$6)+SUMIFS('Forecast Data'!H:H,'Forecast Data'!B:B,D21,'Forecast Data'!C:C,BL$6)+SUMIFS('Forecast Data'!H:H,'Forecast Data'!B:B,D21,'Forecast Data'!C:C,BM$6)),"") | CF21: =(($L21-$E21)/($L$4-$E$4))*$M$4 -> 0.021676984 | CG21: =((AVERAGE(W21:Z21)-CD21)/(AVERAGE($W$4:$Z$4)-$CD$4))*$CE$4 -> 0.02221869 | CH21: =(CF21-CG21)*100 -> -0.054170654
B22: =D22 -> Wisdom Panel | C22: Holiday | D22: Wisdom Panel | E22: =SUMIFS('Fin Data'!F:F,'Fin Data'!A:A,D22) -> 2360 | F22: =SUMIFS('Fin Data with 6 week hist'!I:I,'Fin Data with 6 week hist'!$A:$A,$D22) -> 2474 | G22: =SUMIFS('Fin Data with 6 week hist'!J:J,'Fin Data with 6 week hist'!$A:$A,$D22) -> 2105 | H22: =SUMIFS('Fin Data with 6 week hist'!K:K,'Fin Data with 6 week hist'!$A:$A,$D22)+SUMIFS('Unit Cancellations'!D:D,'Unit Cancellations'!$B:$B,$D22) -> 2219 | I22: =SUMIFS('Fin Data with 6 week hist'!L:L,'Fin Data with 6 week hist'!$A:$A,$D22)+SUMIFS('Unit Cancellations'!E:E,'Unit Cancellations'!$B:$B,$D22) -> 2702 | J22: =SUMIFS('Fin Data with 6 week hist'!M:M,'Fin Data with 6 week hist'!$A:$A,$D22)+SUMIFS('Unit Cancellations'!F:F,'Unit Cancellations'!$B:$B,$D22) -> 2710 | K22: =SUMIFS('Fin Data with 6 week hist'!N:N,'Fin Data with 6 week hist'!$A:$A,$D22)+SUMIFS('Unit Cancellations'!G:G,'Unit Cancellations'!$B:$B,$D22) -> 3310 | L22: =SUMIFS('Fin Data'!AN:AN,'Fin Data'!A:A,D22) -> 2586.5 | M22: =IFERROR(SUMIFS('Fin Data'!AO:AO,'Fin Data'!A:A,D22),"") -> 0.095974576 | O22: =AVERAGE(W22:Z22) -> 3344 | P22: =CE22 -> 2.8403675 | R22: =AVERAGE(W22:AD22) -> 3685.375 | S22: =BX22 -> 1.3154795 | T22: =AVERAGE(AW22:BD22) -> 2465.25 | U22: =#REF! -> #REF! | W22: =SUMIFS('Forecast Data'!$D:$D,'Forecast Data'!$C:$C,W$6,'Forecast Data'!$B:$B,$D22) -> 5521 | X22: =SUMIFS('Forecast Data'!$D:$D,'Forecast Data'!$C:$C,X$6,'Forecast Data'!$B:$B,$D22) -> 3016 | Y22: =SUMIFS('Forecast Data'!$D:$D,'Forecast Data'!$C:$C,Y$6,'Forecast Data'!$B:$B,$D22) -> 2349 | Z22: =SUMIFS('Forecast Data'!$D:$D,'Forecast Data'!$C:$C,Z$6,'Forecast Data'!$B:$B,$D22) -> 2490 | AA22: =SUMIFS('Forecast Data'!$D:$D,'Forecast Data'!$C:$C,AA$6,'Forecast Data'!$B:$B,$D22) -> 2861 | AB22: =SUMIFS('Forecast Data'!$D:$D,'Forecast Data'!$C:$C,AB$6,'Forecast Data'!$B:$B,$D22) -> 3740 | AC22: =SUMIFS('Forecast Data'!$D:$D,'Forecast Data'!$C:$C,AC$6,'Forecast Data'!$B:$B,$D22) -> 4786 | AD22: =SUMIFS('Forecast Data'!$D:$D,'Forecast Data'!$C:$C,AD$6,'Forecast Data'!$B:$B,$D22) -> 4720 | ... AH22: =SUMIFS('Forecast Data'!$D:$D,'Forecast Data'!$C:$C,AH$6,'Forecast Data'!$B:$B,$D22) -> 4279 | AJ22: =IF(SUMIFS('Forecast Data'!$E:$E,'Forecast Data'!$C:$C,AJ$6,'Forecast Data'!$B:$B,$D22)=0,"",SUMIFS('Forecast Data'!$E:$E,'Forecast Data'!$C:$C,AJ$6,'Forecast Data'!$B:$B,$D22)) -> 10.2 | AK22: =IF(SUMIFS('Forecast Data'!$E:$E,'Forecast Data'!$C:$C,AK$6,'Forecast Data'!$B:$B,$D22)=0,"",SUMIFS('Forecast Data'!$E:$E,'Forecast Data'!$C:$C,AK$6,'Forecast Data'!$B:$B,$D22)) -> 3.46 | AL22: =IF(SUMIFS('Forecast Data'!$E:$E,'Forecast Data'!$C:$C,AL$6,'Forecast Data'!$B:$B,$D22)=0,"",SUMIFS('Forecast Data'!$E:$E,'Forecast Data'!$C:$C,AL$6,'Forecast Data'!$B:$B,$D22)) -> 1.67 | AM22: =IF(SUMIFS('Forecast Data'!$E:$E,'Forecast Data'!$C:$C,AM$6,'Forecast Data'!$B:$B,$D22)=0,"",SUMIFS('Forecast Data'!$E:$E,'Forecast Data'!$C:$C,AM$6,'Forecast Data'!$B:$B,$D22)) -> 0.74 | AN22: =IF(SUMIFS('Forecast Data'!$E:$E,'Forecast Data'!$C:$C,AN$6,'Forecast Data'!$B:$B,$D22)=0,"",SUMIFS('Forecast Data'!$E:$E,'Forecast Data'!$C:$C,AN$6,'Forecast Data'!$B:$B,$D22)) -> 0.68 | AO22: =IF(SUMIFS('Forecast Data'!$E:$E,'Forecast Data'!$C:$C,AO$6,'Forecast Data'!$B:$B,$D22)=0,"",SUMIFS('Forecast Data'!$E:$E,'Forecast Data'!$C:$C,AO$6,'Forecast Data'!$B:$B,$D22)) -> 0.58 | AP22: =IF(SUMIFS('Forecast Data'!$E:$E,'Forecast Data'!$C:$C,AP$6,'Forecast Data'!$B:$B,$D22)=0,"",SUMIFS('Forecast Data'!$E:$E,'Forecast Data'!$C:$C,AP$6,'Forecast Data'!$B:$B,$D22)) -> 0.76 | AQ22: =IF(SUMIFS('Forecast Data'!$E:$E,'Forecast Data'!$C:$C,AQ$6,'Forecast Data'!$B:$B,$D22)=0,"",SUMIFS('Forecast Data'!$E:$E,'Forecast Data'!$C:$C,AQ$6,'Forecast Data'!$B:$B,$D22)) -> 0.92 | ... AU22: =IF(SUMIFS('Forecast Data'!$E:$E,'Forecast Data'!$C:$C,AU$6,'Forecast Data'!$B:$B,$D22)=0,"",SUMIFS('Forecast Data'!$E:$E,'Forecast Data'!$C:$C,AU$6,'Forecast Data'!$B:$B,$D22)) -> 0.9 | AW22: =SUMIFS('OP Units'!E:E,'OP Units'!$A:$A,$D22) -> 2001 | AX22: =SUMIFS('OP Units'!F:F,'OP Units'!$A:$A,$D22) -> 2350 | AY22: =SUMIFS('OP Units'!G:G,'OP Units'!$A:$A,$D22) -> 3323 | AZ22: =SUMIFS('OP Units'!H:H,'OP Units'!$A:$A,$D22) -> 2745 | BA22: =SUMIFS('OP Units'!I:I,'OP Units'!$A:$A,$D22) -> 1435 | BB22: =SUMIFS('OP Units'!J:J,'OP Units'!$A:$A,$D22) -> 1516 | BC22: =SUMIFS('OP Units'!K:K,'OP Units'!$A:$A,$D22) -> 2787 | BD22: =SUMIFS('OP Units'!L:L,'OP Units'!$A:$A,$D22) -> 3565 | BE22: =SUMIFS('OP Units'!M:M,'OP Units'!$A:$A,$D22) -> 3028 | BF22: =SUMIFS('OP Units'!N:N,'OP Units'!$A:$A,$D22) -> 672 | BG22: =SUMIFS('OP Units'!O:O,'OP Units'!$A:$A,$D22) -> 1029 | BH22: =SUMIFS('OP Units'!P:P,'OP Units'!$A:$A,$D22) -> 1375 | BJ22: =IFERROR((SUMIFS('OP Units'!E:E,'OP Units'!$A:$A,$D22)-SUMIFS('Forecast Data'!$H:$H,'Forecast Data'!$C:$C,BJ$6,'Forecast Data'!$B:$B,$D22))/SUMIFS('Forecast Data'!$H:$H,'Forecast Data'!$C:$C,BJ$6,'Forecast Data'!$B:$B,$D22),"") -> 3.0588235 | BK22: =IFERROR((SUMIFS('OP Units'!F:F,'OP Units'!$A:$A,$D22)-SUMIFS('Forecast Data'!$H:$H,'Forecast Data'!$C:$C,BK$6,'Forecast Data'!$B:$B,$D22))/SUMIFS('Forecast Data'!$H:$H,'Forecast Data'!$C:$C,BK$6,'Forecast Data'!$B:$B,$D22),"") -> 2.4763314 | BL22: =IFERROR((SUMIFS('OP Units'!G:G,'OP Units'!$A:$A,$D22)-SUMIFS('Forecast Data'!$H:$H,'Forecast Data'!$C:$C,BL$6,'Forecast Data'!$B:$B,$D22))/SUMIFS('Forecast Data'!$H:$H,'Forecast Data'!$C:$C,BL$6,'Forecast Data'!$B:$B,$D22),"") -> 2.7718502 | BM22: =IFERROR((SUMIFS('OP Units'!H:H,'OP Units'!$A:$A,$D22)-SUMIFS('Forecast Data'!$H:$H,'Forecast Data'!$C:$C,BM$6,'Forecast Data'!$B:$B,$D22))/SUMIFS('Forecast Data'!$H:$H,'Forecast Data'!$C:$C,BM$6,'Forecast Data'!$B:$B,$D22),"") -> 0.91556176 | BN22: =IFERROR((SUMIFS('OP Units'!I:I,'OP Units'!$A:$A,$D22)-SUMIFS('Forecast Data'!$H:$H,'Forecast Data'!$C:$C,BN$6,'Forecast Data'!$B:$B,$D22))/SUMIFS('Forecast Data'!$H:$H,'Forecast Data'!$C:$C,BN$6,'Forecast Data'!$B:$B,$D22),"") -> -0.15588235 | BO22: =IFERROR((SUMIFS('OP Units'!J:J,'OP Units'!$A:$A,$D22)-SUMIFS('Forecast Data'!$H:$H,'Forecast Data'!$C:$C,BO$6,'Forecast Data'!$B:$B,$D22))/SUMIFS('Forecast Data'!$H:$H,'Forecast Data'!$C:$C,BO$6,'Forecast Data'!$B:$B,$D22),"") -> -0.3589852 | BP22: =IFERROR((SUMIFS('OP Units'!K:K,'OP Units'!$A:$A,$D22)-SUMIFS('Forecast Data'!$H:$H,'Forecast Data'!$C:$C,BP$6,'Forecast Data'!$B:$B,$D22))/SUMIFS('Forecast Data'!$H:$H,'Forecast Data'!$C:$C,BP$6,'Forecast Data'!$B:$B,$D22),"") -> 0.024255788 | BQ22: =IFERROR((SUMIFS('OP Units'!L:L,'OP Units'!$A:$A,$D22)-SUMIFS('Forecast Data'!$H:$H,'Forecast Data'!$C:$C,BQ$6,'Forecast Data'!$B:$B,$D22))/SUMIFS('Forecast Data'!$H:$H,'Forecast Data'!$C:$C,BQ$6,'Forecast Data'!$B:$B,$D22),"") -> 0.44683442 | BR22: =IFERROR((SUMIFS('OP Units'!M:M,'OP Units'!$A:$A,$D22)-SUMIFS('Forecast Data'!$H:$H,'Forecast Data'!$C:$C,BR$6,'Forecast Data'!$B:$B,$D22))/SUMIFS('Forecast Data'!$H:$H,'Forecast Data'!$C:$C,BR$6,'Forecast Data'!$B:$B,$D22),"") -> 0.76148924 | BS22: =IFERROR((SUMIFS('OP Units'!N:N,'OP Units'!$A:$A,$D22)-SUMIFS('Forecast Data'!$H:$H,'Forecast Data'!$C:$C,BS$6,'Forecast Data'!$B:$B,$D22))/SUMIFS('Forecast Data'!$H:$H,'Forecast Data'!$C:$C,BS$6,'Forecast Data'!$B:$B,$D22),"") -> -0.60400707 | BT22: =IFERROR((SUMIFS('OP Units'!O:O,'OP Units'!$A:$A,$D22)-SUMIFS('Forecast Data'!$H:$H,'Forecast Data'!$C:$C,BT$6,'Forecast Data'!$B:$B,$D22))/SUMIFS('Forecast Data'!$H:$H,'Forecast Data'!$C:$C,BT$6,'Forecast Data'!$B:$B,$D22),"") -> -0.63012221 | BU22: =IFERROR((SUMIFS('OP Units'!P:P,'OP Units'!$A:$A,$D22)-SUMIFS('Forecast Data'!$H:$H,'Forecast Data'!$C:$C,BU$6,'Forecast Data'!$B:$B,$D22))/SUMIFS('Forecast Data'!$H:$H,'Forecast Data'!$C:$C,BU$6,'Forecast Data'!$B:$B,$D22),"") -> -0.3883452 | BW22: =(SUMIFS('Forecast Data'!H:H,'Forecast Data'!B:B,D22,'Forecast Data'!C:C,BK$6)+SUMIFS('Forecast Data'!H:H,'Forecast Data'!B:B,D22,'Forecast Data'!C:C,BL$6)+SUMIFS('Forecast Data'!H:H,'Forecast Data'!B:B,D22,'Forecast Data'!C:C,BM$6)+SUMIFS('Forecast Data'!H:H,'Forecast Data'!B:B,D22,'Forecast Data'!C:C,BN$6)+SUMIFS('Forecast Data'!H:H,'Forecast Data'!B:B,D22,'Forecast Data'!C:C,BO$6)+SUMIFS('Forecast Data'!H:H,'Forecast Data'!B:B,D22,'Forecast Data'!C:C,BP$6)+SUMIFS('Forecast Data'!H:H,'Forecast Data'!B:B,D22,'Forecast Data'!C:C,BQ$6)+SUMIFS('Forecast Data'!H:H,'Forecast Data'!B:B,D22,'Forecast Data'!C:C,BJ$6))/8 -> 1591.625 | BX22: =IFERROR((SUM(W22:AD22)-(SUMIFS('Forecast Data'!H:H,'Forecast Data'!B:B,B22,'Forecast Data'!C:C,BJ$6)+SUMIFS('Forecast Data'!H:H,'Forecast Data'!B:B,B22,'Forecast Data'!C:C,BK$6)+SUMIFS('Forecast Data'!H:H,'Forecast Data'!B:B,B22,'Forecast Data'!C:C,BL$6)+SUMIFS('Forecast Data'!H:H,'Forecast Data'!B:B,B22,'Forecast Data'!C:C,BM$6)+SUMIFS('Forecast Data'!H:H,'Forecast Data'!B:B,B22,'Forecast Data'!C:C,BN$6)+SUMIFS('Forecast Data'!H:H,'Forecast Data'!B:B,B22,'Forecast Data'!C:C,BO$6)+SUMIFS('Forecast Data'!H:H,'Forecast Data'!B:B,B22,'Forecast Data'!C:C,BP$6)+SUMIFS('Forecast Data'!H:H,'Forecast Data'!B:B,B22,'Forecast Data'!C:C,BQ$6)))/(SUMIFS('Forecast Data'!H:H,'Forecast Data'!B:B,B22,'Forecast Data'!C:C,BJ$6)+SUMIFS('Forecast Data'!H:H,'Forecast Data'!B:B,B22,'Forecast Data'!C:C,BK$6)+SUMIFS('Forecast Data'!H:H,'Forecast Data'!B:B,B22,'Forecast Data'!C:C,BL$6)+SUMIFS('Forecast Data'!H:H,'Forecast Data'!B:B,B22,'Forecast Data'!C:C,BM$6)+SUMIFS('Forecast Data'!H:H,'Forecast Data'!B:B,B22,'Forecast Data'!C:C,BN$6)+SUMIFS('Forecast Data'!H:H,'Forecast Data'!B:B,B22,'Forecast Data'!C:C,BO$6)+SUMIFS('Forecast Data'!H:H,'Forecast Data'!B:B,B22,'Forecast Data'!C:C,BP$6)+SUMIFS('Forecast Data'!H:H,'Forecast Data'!B:B,B22,'Forecast Data'!C:C,BQ$6)),"") -> 1.3154795 | BY22: =((L22-E22)/($L$4-$E$4))*$M$4 -> 0.00019368957 | BZ22: =((AVERAGE(W22:AD22)-BW22)/(AVERAGE($W$4:$AD$4)-$BW$4))*$BX$4 -> 0.0017216886 | CA22: =(BY22-BZ22)*100 -> -0.1527999 | CB22: =ABS(CA22)/100 -> 0.001527999 | CD22: =(SUMIFS('Forecast Data'!H:H,'Forecast Data'!B:B,D22,'Forecast Data'!C:C,BK$6)+SUMIFS('Forecast Data'!H:H,'Forecast Data'!B:B,D22,'Forecast Data'!C:C,BL$6)+SUMIFS('Forecast Data'!H:H,'Forecast Data'!B:B,D22,'Forecast Data'!C:C,BM$6)+SUMIFS('Forecast Data'!H:H,'Forecast Data'!B:B,D22,'Forecast Data'!C:C,BJ$6))/4 -> 870.75 | CE22: =IFERROR((SUM(W22:Z22)-(SUMIFS('Forecast Data'!H:H,'Forecast Data'!B:B,D22,'Forecast Data'!C:C,BJ$6)+SUMIFS('Forecast Data'!H:H,'Forecast Data'!B:B,D22,'Forecast Data'!C:C,BK$6)+SUMIFS('Forecast Data'!H:H,'Forecast Data'!B:B,D22,'Forecast Data'!C:C,BL$6)+SUMIFS('Forecast Data'!H:H,'Forecast Data'!B:B,D22,'Forecast Data'!C:C,BM$6)))/(SUMIFS('Forecast Data'!H:H,'Forecast Data'!B:B,D22,'Forecast Data'!C:C,BJ$6)+SUMIFS('Forecast Data'!H:H,'Forecast Data'!B:B,D22,'Forecast Data'!C:C,BK$6)+SUMIFS('Forecast Data'!H:H,'Forecast Data'!B:B,D22,'Forecast Data'!C:C,BL$6)+SUMIFS('Forecast Data'!H:H,'Forecast Data'!B:B,D22,'Forecast Data'!C:C,BM$6)),"") -> 2.8403675 | CF22: =(($L22-$E22)/($L$4-$E$4))*$M$4 -> 0.00019368957 | CG22: =((AVERAGE(W22:Z22)-CD22)/(AVERAGE($W$4:$Z$4)-$CD$4))*$CE$4 -> 0.0020735376 | CH22: =(CF22-CG22)*100 -> -0.18798481
B23: =D23 -> KONG | C23: Holiday | D23: KONG | E23: =SUMIFS('Fin Data'!F:F,'Fin Data'!A:A,D23) -> 29698 | F23: =SUMIFS('Fin Data with 6 week hist'!I:I,'Fin Data with 6 week hist'!$A:$A,$D23) -> 34587 | G23: =SUMIFS('Fin Data with 6 week hist'!J:J,'Fin Data with 6 week hist'!$A:$A,$D23) -> 36216 | H23: =SUMIFS('Fin Data with 6 week hist'!K:K,'Fin Data with 6 week hist'!$A:$A,$D23)+SUMIFS('Unit Cancellations'!D:D,'Unit Cancellations'!$B:$B,$D23) -> 35683 | I23: =SUMIFS('Fin Data with 6 week hist'!L:L,'Fin Data with 6 week hist'!$A:$A,$D23)+SUMIFS('Unit Cancellations'!E:E,'Unit Cancellations'!$B:$B,$D23) -> 34769 | J23: =SUMIFS('Fin Data with 6 week hist'!M:M,'Fin Data with 6 week hist'!$A:$A,$D23)+SUMIFS('Unit Cancellations'!F:F,'Unit Cancellations'!$B:$B,$D23) -> 34457 | K23: =SUMIFS('Fin Data with 6 week hist'!N:N,'Fin Data with 6 week hist'!$A:$A,$D23)+SUMIFS('Unit Cancellations'!G:G,'Unit Cancellations'!$B:$B,$D23) -> 34286 | L23: =SUMIFS('Fin Data'!AN:AN,'Fin Data'!A:A,D23) -> 34999.5 | M23: =IFERROR(SUMIFS('Fin Data'!AO:AO,'Fin Data'!A:A,D23),"") -> 0.1785137 | O23: =AVERAGE(W23:Z23) -> 36304 | P23: =CE23 -> 0.27091484 | R23: =AVERAGE(W23:AD23) -> 36627.625 | S23: =BX23 -> 0.29467982 | T23: =AVERAGE(AW23:BD23) -> 31883.25 | U23: =#REF! -> #REF! | W23: =SUMIFS('Forecast Data'!$D:$D,'Forecast Data'!$C:$C,W$6,'Forecast Data'!$B:$B,$D23) -> 36134 | X23: =SUMIFS('Forecast Data'!$D:$D,'Forecast Data'!$C:$C,X$6,'Forecast Data'!$B:$B,$D23) -> 36096 | Y23: =SUMIFS('Forecast Data'!$D:$D,'Forecast Data'!$C:$C,Y$6,'Forecast Data'!$B:$B,$D23) -> 36404 | Z23: =SUMIFS('Forecast Data'!$D:$D,'Forecast Data'!$C:$C,Z$6,'Forecast Data'!$B:$B,$D23) -> 36582 | AA23: =SUMIFS('Forecast Data'!$D:$D,'Forecast Data'!$C:$C,AA$6,'Forecast Data'!$B:$B,$D23) -> 36690 | AB23: =SUMIFS('Forecast Data'!$D:$D,'Forecast Data'!$C:$C,AB$6,'Forecast Data'!$B:$B,$D23) -> 36735 | AC23: =SUMIFS('Forecast Data'!$D:$D,'Forecast Data'!$C:$C,AC$6,'Forecast Data'!$B:$B,$D23) -> 37171 | AD23: =SUMIFS('Forecast Data'!$D:$D,'Forecast Data'!$C:$C,AD$6,'Forecast Data'!$B:$B,$D23) -> 37209 | ... AH23: =SUMIFS('Forecast Data'!$D:$D,'Forecast Data'!$C:$C,AH$6,'Forecast Data'!$B:$B,$D23) -> 37509 | AJ23: =IF(SUMIFS('Forecast Data'!$E:$E,'Forecast Data'!$C:$C,AJ$6,'Forecast Data'!$B:$B,$D23)=0,"",SUMIFS('Forecast Data'!$E:$E,'Forecast Data'!$C:$C,AJ$6,'Forecast Data'!$B:$B,$D23)) -> 0.26 | AK23: =IF(SUMIFS('Forecast Data'!$E:$E,'Forecast Data'!$C:$C,AK$6,'Forecast Data'!$B:$B,$D23)=0,"",SUMIFS('Forecast Data'!$E:$E,'Forecast Data'!$C:$C,AK$6,'Forecast Data'!$B:$B,$D23)) -> 0.28 | AL23: =IF(SUMIFS('Forecast Data'!$E:$E,'Forecast Data'!$C:$C,AL$6,'Forecast Data'!$B:$B,$D23)=0,"",SUMIFS('Forecast Data'!$E:$E,'Forecast Data'!$C:$C,AL$6,'Forecast Data'!$B:$B,$D23)) -> 0.27 | AM23: =IF(SUMIFS('Forecast Data'!$E:$E,'Forecast Data'!$C:$C,AM$6,'Forecast Data'!$B:$B,$D23)=0,"",SUMIFS('Forecast Data'!$E:$E,'Forecast Data'!$C:$C,AM$6,'Forecast Data'!$B:$B,$D23)) -> 0.28 | AN23: =IF(SUMIFS('Forecast Data'!$E:$E,'Forecast Data'!$C:$C,AN$6,'Forecast Data'!$B:$B,$D23)=0,"",SUMIFS('Forecast Data'!$E:$E,'Forecast Data'!$C:$C,AN$6,'Forecast Data'!$B:$B,$D23)) -> 0.33 | AO23: =IF(SUMIFS('Forecast Data'!$E:$E,'Forecast Data'!$C:$C,AO$6,'Forecast Data'!$B:$B,$D23)=0,"",SUMIFS('Forecast Data'!$E:$E,'Forecast Data'!$C:$C,AO$6,'Forecast Data'!$B:$B,$D23)) -> 0.27 | AP23: =IF(SUMIFS('Forecast Data'!$E:$E,'Forecast Data'!$C:$C,AP$6,'Forecast Data'!$B:$B,$D23)=0,"",SUMIFS('Forecast Data'!$E:$E,'Forecast Data'!$C:$C,AP$6,'Forecast Data'!$B:$B,$D23)) -> 0.37 | AQ23: =IF(SUMIFS('Forecast Data'!$E:$E,'Forecast Data'!$C:$C,AQ$6,'Forecast Data'!$B:$B,$D23)=0,"",SUMIFS('Forecast Data'!$E:$E,'Forecast Data'!$C:$C,AQ$6,'Forecast Data'!$B:$B,$D23)) -> 0.3 | ... AU23: =IF(SUMIFS('Forecast Data'!$E:$E,'Forecast Data'!$C:$C,AU$6,'Forecast Data'!$B:$B,$D23)=0,"",SUMIFS('Forecast Data'!$E:$E,'Forecast Data'!$C:$C,AU$6,'Forecast Data'!$B:$B,$D23)) -> 0.32 | AW23: =SUMIFS('OP Units'!E:E,'OP Units'!$A:$A,$D23) -> 31894 | AX23: =SUMIFS('OP Units'!F:F,'OP Units'!$A:$A,$D23) -> 32308 | AY23: =SUMIFS('OP Units'!G:G,'OP Units'!$A:$A,$D23) -> 32029 | AZ23: =SUMIFS('OP Units'!H:H,'OP Units'!$A:$A,$D23) -> 31357 | BA23: =SUMIFS('OP Units'!I:I,'OP Units'!$A:$A,$D23) -> 34006 | BB23: =SUMIFS('OP Units'!J:J,'OP Units'!$A:$A,$D23) -> 33290 | BC23: =SUMIFS('OP Units'!K:K,'OP Units'!$A:$A,$D23) -> 30513 | BD23: =SUMIFS('OP Units'!L:L,'OP Units'!$A:$A,$D23) -> 29669 | BE23: =SUMIFS('OP Units'!M:M,'OP Units'!$A:$A,$D23) -> 28845 | BF23: =SUMIFS('OP Units'!N:N,'OP Units'!$A:$A,$D23) -> 29228 | BG23: =SUMIFS('OP Units'!O:O,'OP Units'!$A:$A,$D23) -> 28408 | BH23: =SUMIFS('OP Units'!P:P,'OP Units'!$A:$A,$D23) -> 28685 | BJ23: =IFERROR((SUMIFS('OP Units'!E:E,'OP Units'!$A:$A,$D23)-SUMIFS('Forecast Data'!$H:$H,'Forecast Data'!$C:$C,BJ$6,'Forecast Data'!$B:$B,$D23))/SUMIFS('Forecast Data'!$H:$H,'Forecast Data'!$C:$C,BJ$6,'Forecast Data'!$B:$B,$D23),"") -> 0.10935652 | BK23: =IFERROR((SUMIFS('OP Units'!F:F,'OP Units'!$A:$A,$D23)-SUMIFS('Forecast Data'!$H:$H,'Forecast Data'!$C:$C,BK$6,'Forecast Data'!$B:$B,$D23))/SUMIFS('Forecast Data'!$H:$H,'Forecast Data'!$C:$C,BK$6,'Forecast Data'!$B:$B,$D23),"") -> 0.14388897 | BL23: =IFERROR((SUMIFS('OP Units'!G:G,'OP Units'!$A:$A,$D23)-SUMIFS('Forecast Data'!$H:$H,'Forecast Data'!$C:$C,BL$6,'Forecast Data'!$B:$B,$D23))/SUMIFS('Forecast Data'!$H:$H,'Forecast Data'!$C:$C,BL$6,'Forecast Data'!$B:$B,$D23),"") -> 0.11358737 | BM23: =IFERROR((SUMIFS('OP Units'!H:H,'OP Units'!$A:$A,$D23)-SUMIFS('Forecast Data'!$H:$H,'Forecast Data'!$C:$C,BM$6,'Forecast Data'!$B:$B,$D23))/SUMIFS('Forecast Data'!$H:$H,'Forecast Data'!$C:$C,BM$6,'Forecast Data'!$B:$B,$D23),"") -> 0.10005262 | BN23: =IFERROR((SUMIFS('OP Units'!I:I,'OP Units'!$A:$A,$D23)-SUMIFS('Forecast Data'!$H:$H,'Forecast Data'!$C:$C,BN$6,'Forecast Data'!$B:$B,$D23))/SUMIFS('Forecast Data'!$H:$H,'Forecast Data'!$C:$C,BN$6,'Forecast Data'!$B:$B,$D23),"") -> 0.2337554 | BO23: =IFERROR((SUMIFS('OP Units'!J:J,'OP Units'!$A:$A,$D23)-SUMIFS('Forecast Data'!$H:$H,'Forecast Data'!$C:$C,BO$6,'Forecast Data'!$B:$B,$D23))/SUMIFS('Forecast Data'!$H:$H,'Forecast Data'!$C:$C,BO$6,'Forecast Data'!$B:$B,$D23),"") -> 0.15433961 | BP23: =IFERROR((SUMIFS('OP Units'!K:K,'OP Units'!$A:$A,$D23)-SUMIFS('Forecast Data'!$H:$H,'Forecast Data'!$C:$C,BP$6,'Forecast Data'!$B:$B,$D23))/SUMIFS('Forecast Data'!$H:$H,'Forecast Data'!$C:$C,BP$6,'Forecast Data'!$B:$B,$D23),"") -> 0.124613 | BQ23: =IFERROR((SUMIFS('OP Units'!L:L,'OP Units'!$A:$A,$D23)-SUMIFS('Forecast Data'!$H:$H,'Forecast Data'!$C:$C,BQ$6,'Forecast Data'!$B:$B,$D23))/SUMIFS('Forecast Data'!$H:$H,'Forecast Data'!$C:$C,BQ$6,'Forecast Data'!$B:$B,$D23),"") -> 0.039849993 | BR23: =IFERROR((SUMIFS('OP Units'!M:M,'OP Units'!$A:$A,$D23)-SUMIFS('Forecast Data'!$H:$H,'Forecast Data'!$C:$C,BR$6,'Forecast Data'!$B:$B,$D23))/SUMIFS('Forecast Data'!$H:$H,'Forecast Data'!$C:$C,BR$6,'Forecast Data'!$B:$B,$D23),"") -> 0.0099436294 | BS23: =IFERROR((SUMIFS('OP Units'!N:N,'OP Units'!$A:$A,$D23)-SUMIFS('Forecast Data'!$H:$H,'Forecast Data'!$C:$C,BS$6,'Forecast Data'!$B:$B,$D23))/SUMIFS('Forecast Data'!$H:$H,'Forecast Data'!$C:$C,BS$6,'Forecast Data'!$B:$B,$D23),"") -> 0.056841192 | BT23: =IFERROR((SUMIFS('OP Units'!O:O,'OP Units'!$A:$A,$D23)-SUMIFS('Forecast Data'!$H:$H,'Forecast Data'!$C:$C,BT$6,'Forecast Data'!$B:$B,$D23))/SUMIFS('Forecast Data'!$H:$H,'Forecast Data'!$C:$C,BT$6,'Forecast Data'!$B:$B,$D23),"") -> -0.018518519 | BU23: =IFERROR((SUMIFS('OP Units'!P:P,'OP Units'!$A:$A,$D23)-SUMIFS('Forecast Data'!$H:$H,'Forecast Data'!$C:$C,BU$6,'Forecast Data'!$B:$B,$D23))/SUMIFS('Forecast Data'!$H:$H,'Forecast Data'!$C:$C,BU$6,'Forecast Data'!$B:$B,$D23),"") -> 0.013246203 | BW23: =(SUMIFS('Forecast Data'!H:H,'Forecast Data'!B:B,D23,'Forecast Data'!C:C,BK$6)+SUMIFS('Forecast Data'!H:H,'Forecast Data'!B:B,D23,'Forecast Data'!C:C,BL$6)+SUMIFS('Forecast Data'!H:H,'Forecast Data'!B:B,D23,'Forecast Data'!C:C,BM$6)+SUMIFS('Forecast Data'!H:H,'Forecast Data'!B:B,D23,'Forecast Data'!C:C,BN$6)+SUMIFS('Forecast Data'!H:H,'Forecast Data'!B:B,D23,'Forecast Data'!C:C,BO$6)+SUMIFS('Forecast Data'!H:H,'Forecast Data'!B:B,D23,'Forecast Data'!C:C,BP$6)+SUMIFS('Forecast Data'!H:H,'Forecast Data'!B:B,D23,'Forecast Data'!C:C,BQ$6)+SUMIFS('Forecast Data'!H:H,'Forecast Data'!B:B,D23,'Forecast Data'!C:C,BJ$6))/8 -> 28290.875 | BX23: =IFERROR((SUM(W23:AD23)-(SUMIFS('Forecast Data'!H:H,'Forecast Data'!B:B,B23,'Forecast Data'!C:C,BJ$6)+SUMIFS('Forecast Data'!H:H,'Forecast Data'!B:B,B23,'Forecast Data'!C:C,BK$6)+SUMIFS('Forecast Data'!H:H,'Forecast Data'!B:B,B23,'Forecast Data'!C:C,BL$6)+SUMIFS('Forecast Data'!H:H,'Forecast Data'!B:B,B23,'Forecast Data'!C:C,BM$6)+SUMIFS('Forecast Data'!H:H,'Forecast Data'!B:B,B23,'Forecast Data'!C:C,BN$6)+SUMIFS('Forecast Data'!H:H,'Forecast Data'!B:B,B23,'Forecast Data'!C:C,BO$6)+SUMIFS('Forecast Data'!H:H,'Forecast Data'!B:B,B23,'Forecast Data'!C:C,BP$6)+SUMIFS('Forecast Data'!H:H,'Forecast Data'!B:B,B23,'Forecast Data'!C:C,BQ$6)))/(SUMIFS('Forecast Data'!H:H,'Forecast Data'!B:B,B23,'Forecast Data'!C:C,BJ$6)+SUMIFS('Forecast Data'!H:H,'Forecast Data'!B:B,B23,'Forecast Data'!C:C,BK$6)+SUMIFS('Forecast Data'!H:H,'Forecast Data'!B:B,B23,'Forecast Data'!C:C,BL$6)+SUMIFS('Forecast Data'!H:H,'Forecast Data'!B:B,B23,'Forecast Data'!C:C,BM$6)+SUMIFS('Forecast Data'!H:H,'Forecast Data'!B:B,B23,'Forecast Data'!C:C,BN$6)+SUMIFS('Forecast Data'!H:H,'Forecast Data'!B:B,B23,'Forecast Data'!C:C,BO$6)+SUMIFS('Forecast Data'!H:H,'Forecast Data'!B:B,B23,'Forecast Data'!C:C,BP$6)+SUMIFS('Forecast Data'!H:H,'Forecast Data'!B:B,B23,'Forecast Data'!C:C,BQ$6)),"") -> 0.29467982 | BY23: =((L23-E23)/($L$4-$E$4))*$M$4 -> 0.0045335331 | BZ23: =((AVERAGE(W23:AD23)-BW23)/(AVERAGE($W$4:$AD$4)-$BW$4))*$BX$4 -> 0.0068553014 | CA23: =(BY23-BZ23)*100 -> -0.23217683 | CB23: =ABS(CA23)/100 -> 0.0023217683 | CD23: =(SUMIFS('Forecast Data'!H:H,'Forecast Data'!B:B,D23,'Forecast Data'!C:C,BK$6)+SUMIFS('Forecast Data'!H:H,'Forecast Data'!B:B,D23,'Forecast Data'!C:C,BL$6)+SUMIFS('Forecast Data'!H:H,'Forecast Data'!B:B,D23,'Forecast Data'!C:C,BM$6)+SUMIFS('Forecast Data'!H:H,'Forecast Data'!B:B,D23,'Forecast Data'!C:C,BJ$6))/4 -> 28565.25 | CE23: =IFERROR((SUM(W23:Z23)-(SUMIFS('Forecast Data'!H:H,'Forecast Data'!B:B,D23,'Forecast Data'!C:C,BJ$6)+SUMIFS('Forecast Data'!H:H,'Forecast Data'!B:B,D23,'Forecast Data'!C:C,BK$6)+SUMIFS('Forecast Data'!H:H,'Forecast Data'!B:B,D23,'Forecast Data'!C:C,BL$6)+SUMIFS('Forecast Data'!H:H,'Forecast Data'!B:B,D23,'Forecast Data'!C:C,BM$6)))/(SUMIFS('Forecast Data'!H:H,'Forecast Data'!B:B,D23,'Forecast Data'!C:C,BJ$6)+SUMIFS('Forecast Data'!H:H,'Forecast Data'!B:B,D23,'Forecast Data'!C:C,BK$6)+SUMIFS('Forecast Data'!H:H,'Forecast Data'!B:B,D23,'Forecast Data'!C:C,BL$6)+SUMIFS('Forecast Data'!H:H,'Forecast Data'!B:B,D23,'Forecast Data'!C:C,BM$6)),"") -> 0.27091484 | CF23: =(($L23-$E23)/($L$4-$E$4))*$M$4 -> 0.0045335331 | CG23: =((AVERAGE(W23:Z23)-CD23)/(AVERAGE($W$4:$Z$4)-$CD$4))*$CE$4 -> 0.006488058 | CH23: =(CF23-CG23)*100 -> -0.19545249
D24: Keeps | E24: =SUMIFS('Fin Data'!F:F,'Fin Data'!A:A,D24) -> 0 | F24: =SUMIFS('Fin Data with 6 week hist'!I:I,'Fin Data with 6 week hist'!$A:$A,$D24) -> 0 | G24: =SUMIFS('Fin Data with 6 week hist'!J:J,'Fin Data with 6 week hist'!$A:$A,$D24) -> 0 | H24: =SUMIFS('Fin Data with 6 week hist'!K:K,'Fin Data with 6 week hist'!$A:$A,$D24)+SUMIFS('Unit Cancellations'!D:D,'Unit Cancellations'!$B:$B,$D24) -> 743 | I24: =SUMIFS('Fin Data with 6 week hist'!L:L,'Fin Data with 6 week hist'!$A:$A,$D24)+SUMIFS('Unit Cancellations'!E:E,'Unit Cancellations'!$B:$B,$D24) -> 805 | J24: =SUMIFS('Fin Data with 6 week hist'!M:M,'Fin Data with 6 week hist'!$A:$A,$D24)+SUMIFS('Unit Cancellations'!F:F,'Unit Cancellations'!$B:$B,$D24) -> 1258 | K24: =SUMIFS('Fin Data with 6 week hist'!N:N,'Fin Data with 6 week hist'!$A:$A,$D24)+SUMIFS('Unit Cancellations'!G:G,'Unit Cancellations'!$B:$B,$D24) -> 1988 | L24: =SUMIFS('Fin Data'!AN:AN,'Fin Data'!A:A,D24) -> 799 | M24: =IFERROR(SUMIFS('Fin Data'!AO:AO,'Fin Data'!A:A,D24),"") -> 0 | O24: =AVERAGE(W24:Z24) -> 2916.5 | P24: =CE24 | R24: =AVERAGE(W24:AD24) -> 2947.75 | S24: =BX24 | T24: =AVERAGE(AW24:BD24) -> 0 | U24: =#REF! -> #REF! | W24: =SUMIFS('Forecast Data'!$D:$D,'Forecast Data'!$C:$C,W$6,'Forecast Data'!$B:$B,$D24) -> 2801 | X24: =SUMIFS('Forecast Data'!$D:$D,'Forecast Data'!$C:$C,X$6,'Forecast Data'!$B:$B,$D24) -> 2914 | Y24: =SUMIFS('Forecast Data'!$D:$D,'Forecast Data'!$C:$C,Y$6,'Forecast Data'!$B:$B,$D24) -> 2972 | Z24: =SUMIFS('Forecast Data'!$D:$D,'Forecast Data'!$C:$C,Z$6,'Forecast Data'!$B:$B,$D24) -> 2979 | AA24: =SUMIFS('Forecast Data'!$D:$D,'Forecast Data'!$C:$C,AA$6,'Forecast Data'!$B:$B,$D24) -> 2979 | AB24: =SUMIFS('Forecast Data'!$D:$D,'Forecast Data'!$C:$C,AB$6,'Forecast Data'!$B:$B,$D24) -> 2979 | AC24: =SUMIFS('Forecast Data'!$D:$D,'Forecast Data'!$C:$C,AC$6,'Forecast Data'!$B:$B,$D24) -> 2979 | AD24: =SUMIFS('Forecast Data'!$D:$D,'Forecast Data'!$C:$C,AD$6,'Forecast Data'!$B:$B,$D24) -> 2979 | ... AH24: =SUMIFS('Forecast Data'!$D:$D,'Forecast Data'!$C:$C,AH$6,'Forecast Data'!$B:$B,$D24) -> 2979 | AJ24: =IF(SUMIFS('Forecast Data'!$E:$E,'Forecast Data'!$C:$C,AJ$6,'Forecast Data'!$B:$B,$D24)=0,"",SUMIFS('Forecast Data'!$E:$E,'Forecast Data'!$C:$C,AJ$6,'Forecast Data'!$B:$B,$D24)) | AK24: =IF(SUMIFS('Forecast Data'!$E:$E,'Forecast Data'!$C:$C,AK$6,'Forecast Data'!$B:$B,$D24)=0,"",SUMIFS('Forecast Data'!$E:$E,'Forecast Data'!$C:$C,AK$6,'Forecast Data'!$B:$B,$D24)) | AL24: =IF(SUMIFS('Forecast Data'!$E:$E,'Forecast Data'!$C:$C,AL$6,'Forecast Data'!$B:$B,$D24)=0,"",SUMIFS('Forecast Data'!$E:$E,'Forecast Data'!$C:$C,AL$6,'Forecast Data'!$B:$B,$D24)) | AM24: =IF(SUMIFS('Forecast Data'!$E:$E,'Forecast Data'!$C:$C,AM$6,'Forecast Data'!$B:$B,$D24)=0,"",SUMIFS('Forecast Data'!$E:$E,'Forecast Data'!$C:$C,AM$6,'Forecast Data'!$B:$B,$D24)) | AN24: =IF(SUMIFS('Forecast Data'!$E:$E,'Forecast Data'!$C:$C,AN$6,'Forecast Data'!$B:$B,$D24)=0,"",SUMIFS('Forecast Data'!$E:$E,'Forecast Data'!$C:$C,AN$6,'Forecast Data'!$B:$B,$D24)) | AO24: =IF(SUMIFS('Forecast Data'!$E:$E,'Forecast Data'!$C:$C,AO$6,'Forecast Data'!$B:$B,$D24)=0,"",SUMIFS('Forecast Data'!$E:$E,'Forecast Data'!$C:$C,AO$6,'Forecast Data'!$B:$B,$D24)) | AP24: =IF(SUMIFS('Forecast Data'!$E:$E,'Forecast Data'!$C:$C,AP$6,'Forecast Data'!$B:$B,$D24)=0,"",SUMIFS('Forecast Data'!$E:$E,'Forecast Data'!$C:$C,AP$6,'Forecast Data'!$B:$B,$D24)) | AQ24: =IF(SUMIFS('Forecast Data'!$E:$E,'Forecast Data'!$C:$C,AQ$6,'Forecast Data'!$B:$B,$D24)=0,"",SUMIFS('Forecast Data'!$E:$E,'Forecast Data'!$C:$C,AQ$6,'Forecast Data'!$B:$B,$D24)) | ... AU24: =IF(SUMIFS('Forecast Data'!$E:$E,'Forecast Data'!$C:$C,AU$6,'Forecast Data'!$B:$B,$D24)=0,"",SUMIFS('Forecast Data'!$E:$E,'Forecast Data'!$C:$C,AU$6,'Forecast Data'!$B:$B,$D24)) | AW24: =SUMIFS('OP Units'!E:E,'OP Units'!$A:$A,$D24) -> 0 | AX24: =SUMIFS('OP Units'!F:F,'OP Units'!$A:$A,$D24) -> 0 | AY24: =SUMIFS('OP Units'!G:G,'OP Units'!$A:$A,$D24) -> 0 | AZ24: =SUMIFS('OP Units'!H:H,'OP Units'!$A:$A,$D24) -> 0 | BA24: =SUMIFS('OP Units'!I:I,'OP Units'!$A:$A,$D24) -> 0 | BB24: =SUMIFS('OP Units'!J:J,'OP Units'!$A:$A,$D24) -> 0 | BC24: =SUMIFS('OP Units'!K:K,'OP Units'!$A:$A,$D24) -> 0 | BD24: =SUMIFS('OP Units'!L:L,'OP Units'!$A:$A,$D24) -> 0 | BE24: =SUMIFS('OP Units'!M:M,'OP Units'!$A:$A,$D24) -> 0 | BF24: =SUMIFS('OP Units'!N:N,'OP Units'!$A:$A,$D24) -> 0 | BG24: =SUMIFS('OP Units'!O:O,'OP Units'!$A:$A,$D24) -> 0 | BH24: =SUMIFS('OP Units'!P:P,'OP Units'!$A:$A,$D24) -> 0 | BJ24: =IFERROR((SUMIFS('OP Units'!E:E,'OP Units'!$A:$A,$D24)-SUMIFS('Forecast Data'!$H:$H,'Forecast Data'!$C:$C,BJ$6,'Forecast Data'!$B:$B,$D24))/SUMIFS('Forecast Data'!$H:$H,'Forecast Data'!$C:$C,BJ$6,'Forecast Data'!$B:$B,$D24),"") | BK24: =IFERROR((SUMIFS('OP Units'!F:F,'OP Units'!$A:$A,$D24)-SUMIFS('Forecast Data'!$H:$H,'Forecast Data'!$C:$C,BK$6,'Forecast Data'!$B:$B,$D24))/SUMIFS('Forecast Data'!$H:$H,'Forecast Data'!$C:$C,BK$6,'Forecast Data'!$B:$B,$D24),"") | BL24: =IFERROR((SUMIFS('OP Units'!G:G,'OP Units'!$A:$A,$D24)-SUMIFS('Forecast Data'!$H:$H,'Forecast Data'!$C:$C,BL$6,'Forecast Data'!$B:$B,$D24))/SUMIFS('Forecast Data'!$H:$H,'Forecast Data'!$C:$C,BL$6,'Forecast Data'!$B:$B,$D24),"") | BM24: =IFERROR((SUMIFS('OP Units'!H:H,'OP Units'!$A:$A,$D24)-SUMIFS('Forecast Data'!$H:$H,'Forecast Data'!$C:$C,BM$6,'Forecast Data'!$B:$B,$D24))/SUMIFS('Forecast Data'!$H:$H,'Forecast Data'!$C:$C,BM$6,'Forecast Data'!$B:$B,$D24),"") | BN24: =IFERROR((SUMIFS('OP Units'!I:I,'OP Units'!$A:$A,$D24)-SUMIFS('Forecast Data'!$H:$H,'Forecast Data'!$C:$C,BN$6,'Forecast Data'!$B:$B,$D24))/SUMIFS('Forecast Data'!$H:$H,'Forecast Data'!$C:$C,BN$6,'Forecast Data'!$B:$B,$D24),"") | BO24: =IFERROR((SUMIFS('OP Units'!J:J,'OP Units'!$A:$A,$D24)-SUMIFS('Forecast Data'!$H:$H,'Forecast Data'!$C:$C,BO$6,'Forecast Data'!$B:$B,$D24))/SUMIFS('Forecast Data'!$H:$H,'Forecast Data'!$C:$C,BO$6,'Forecast Data'!$B:$B,$D24),"") | BP24: =IFERROR((SUMIFS('OP Units'!K:K,'OP Units'!$A:$A,$D24)-SUMIFS('Forecast Data'!$H:$H,'Forecast Data'!$C:$C,BP$6,'Forecast Data'!$B:$B,$D24))/SUMIFS('Forecast Data'!$H:$H,'Forecast Data'!$C:$C,BP$6,'Forecast Data'!$B:$B,$D24),"") | BQ24: =IFERROR((SUMIFS('OP Units'!L:L,'OP Units'!$A:$A,$D24)-SUMIFS('Forecast Data'!$H:$H,'Forecast Data'!$C:$C,BQ$6,'Forecast Data'!$B:$B,$D24))/SUMIFS('Forecast Data'!$H:$H,'Forecast Data'!$C:$C,BQ$6,'Forecast Data'!$B:$B,$D24),"") | BR24: =IFERROR((SUMIFS('OP Units'!M:M,'OP Units'!$A:$A,$D24)-SUMIFS('Forecast Data'!$H:$H,'Forecast Data'!$C:$C,BR$6,'Forecast Data'!$B:$B,$D24))/SUMIFS('Forecast Data'!$H:$H,'Forecast Data'!$C:$C,BR$6,'Forecast Data'!$B:$B,$D24),"") | BS24: =IFERROR((SUMIFS('OP Units'!N:N,'OP Units'!$A:$A,$D24)-SUMIFS('Forecast Data'!$H:$H,'Forecast Data'!$C:$C,BS$6,'Forecast Data'!$B:$B,$D24))/SUMIFS('Forecast Data'!$H:$H,'Forecast Data'!$C:$C,BS$6,'Forecast Data'!$B:$B,$D24),"") | BT24: =IFERROR((SUMIFS('OP Units'!O:O,'OP Units'!$A:$A,$D24)-SUMIFS('Forecast Data'!$H:$H,'Forecast Data'!$C:$C,BT$6,'Forecast Data'!$B:$B,$D24))/SUMIFS('Forecast Data'!$H:$H,'Forecast Data'!$C:$C,BT$6,'Forecast Data'!$B:$B,$D24),"") | BU24: =IFERROR((SUMIFS('OP Units'!P:P,'OP Units'!$A:$A,$D24)-SUMIFS('Forecast Data'!$H:$H,'Forecast Data'!$C:$C,BU$6,'Forecast Data'!$B:$B,$D24))/SUMIFS('Forecast Data'!$H:$H,'Forecast Data'!$C:$C,BU$6,'Forecast Data'!$B:$B,$D24),"") | BW24: =(SUMIFS('Forecast Data'!H:H,'Forecast Data'!B:B,D24,'Forecast Data'!C:C,BK$6)+SUMIFS('Forecast Data'!H:H,'Forecast Data'!B:B,D24,'Forecast Data'!C:C,BL$6)+SUMIFS('Forecast Data'!H:H,'Forecast Data'!B:B,D24,'Forecast Data'!C:C,BM$6)+SUMIFS('Forecast Data'!H:H,'Forecast Data'!B:B,D24,'Forecast Data'!C:C,BN$6)+SUMIFS('Forecast Data'!H:H,'Forecast Data'!B:B,D24,'Forecast Data'!C:C,BO$6)+SUMIFS('Forecast Data'!H:H,'Forecast Data'!B:B,D24,'Forecast Data'!C:C,BP$6)+SUMIFS('Forecast Data'!H:H,'Forecast Data'!B:B,D24,'Forecast Data'!C:C,BQ$6)+SUMIFS('Forecast Data'!H:H,'Forecast Data'!B:B,D24,'Forecast Data'!C:C,BJ$6))/8 -> 0 | BX24: =IFERROR((SUM(W24:AD24)-(SUMIFS('Forecast Data'!H:H,'Forecast Data'!B:B,B24,'Forecast Data'!C:C,BJ$6)+SUMIFS('Forecast Data'!H:H,'Forecast Data'!B:B,B24,'Forecast Data'!C:C,BK$6)+SUMIFS('Forecast Data'!H:H,'Forecast Data'!B:B,B24,'Forecast Data'!C:C,BL$6)+SUMIFS('Forecast Data'!H:H,'Forecast Data'!B:B,B24,'Forecast Data'!C:C,BM$6)+SUMIFS('Forecast Data'!H:H,'Forecast Data'!B:B,B24,'Forecast Data'!C:C,BN$6)+SUMIFS('Forecast Data'!H:H,'Forecast Data'!B:B,B24,'Forecast Data'!C:C,BO$6)+SUMIFS('Forecast Data'!H:H,'Forecast Data'!B:B,B24,'Forecast Data'!C:C,BP$6)+SUMIFS('Forecast Data'!H:H,'Forecast Data'!B:B,B24,'Forecast Data'!C:C,BQ$6)))/(SUMIFS('Forecast Data'!H:H,'Forecast Data'!B:B,B24,'Forecast Data'!C:C,BJ$6)+SUMIFS('Forecast Data'!H:H,'Forecast Data'!B:B,B24,'Forecast Data'!C:C,BK$6)+SUMIFS('Forecast Data'!H:H,'Forecast Data'!B:B,B24,'Forecast Data'!C:C,BL$6)+SUMIFS('Forecast Data'!H:H,'Forecast Data'!B:B,B24,'Forecast Data'!C:C,BM$6)+SUMIFS('Forecast Data'!H:H,'Forecast Data'!B:B,B24,'Forecast Data'!C:C,BN$6)+SUMIFS('Forecast Data'!H:H,'Forecast Data'!B:B,B24,'Forecast Data'!C:C,BO$6)+SUMIFS('Forecast Data'!H:H,'Forecast Data'!B:B,B24,'Forecast Data'!C:C,BP$6)+SUMIFS('Forecast Data'!H:H,'Forecast Data'!B:B,B24,'Forecast Data'!C:C,BQ$6)),"") | BY24: =((L24-E24)/($L$4-$E$4))*$M$4 -> 0.00068325812 | BZ24: =((AVERAGE(W24:AD24)-BW24)/(AVERAGE($W$4:$AD$4)-$BW$4))*$BX$4 -> 0.0024239319 | CA24: =(BY24-BZ24)*100 -> -0.17406738 | CB24: =ABS(CA24)/100 -> 0.0017406738 | CD24: =(SUMIFS('Forecast Data'!H:H,'Forecast Data'!B:B,D24,'Forecast Data'!C:C,BK$6)+SUMIFS('Forecast Data'!H:H,'Forecast Data'!B:B,D24,'Forecast Data'!C:C,BL$6)+SUMIFS('Forecast Data'!H:H,'Forecast Data'!B:B,D24,'Forecast Data'!C:C,BM$6)+SUMIFS('Forecast Data'!H:H,'Forecast Data'!B:B,D24,'Forecast Data'!C:C,BJ$6))/4 -> 0 | CE24: =IFERROR((SUM(W24:Z24)-(SUMIFS('Forecast Data'!H:H,'Forecast Data'!B:B,B24,'Forecast Data'!C:C,BJ$6)+SUMIFS('Forecast Data'!H:H,'Forecast Data'!B:B,B24,'Forecast Data'!C:C,BK$6)+SUMIFS('Forecast Data'!H:H,'Forecast Data'!B:B,B24,'Forecast Data'!C:C,BL$6)+SUMIFS('Forecast Data'!H:H,'Forecast Data'!B:B,B24,'Forecast Data'!C:C,BM$6)))/(SUMIFS('Forecast Data'!H:H,'Forecast Data'!B:B,B24,'Forecast Data'!C:C,BJ$6)+SUMIFS('Forecast Data'!H:H,'Forecast Data'!B:B,B24,'Forecast Data'!C:C,BK$6)+SUMIFS('Forecast Data'!H:H,'Forecast Data'!B:B,B24,'Forecast Data'!C:C,BL$6)+SUMIFS('Forecast Data'!H:H,'Forecast Data'!B:B,B24,'Forecast Data'!C:C,BM$6)),"") | CF24: =(($L24-$E24)/($L$4-$E$4))*$M$4 -> 0.00068325812 | CG24: =((AVERAGE(W24:Z24)-CD24)/(AVERAGE($W$4:$Z$4)-$CD$4))*$CE$4 -> 0.0024451521 | CH24: =(CF24-CG24)*100 -> -0.1761894
